Workbook

Sheet START HERE
B2: Order Fulfilment & Installation Performance Analysis Dashboard
B3: Business Operations Analytics Case Study for Neo Heat Pump - Sai Heating and Cooling Solutions
B5: IMPORTANT - SIMULATED DATA: all 160 orders are synthetic records generated for a portfolio case study. They do not describe real orders, customers, prices or performance of the company. Findings illustrate an analysis method; recommendations are proposals only.
B7: What this is | C7: An operations-analysis workbook that turns raw order records into KPIs, a management dashboard, findings and recommendations for order fulfilment, delivery and installation.
B8: Why it was built | C8: Management needs one reliable view of: how many orders are done, pending or cancelled; whether deliveries and installations keep their promised dates; which open orders are overdue; and where the process gets stuck.
B9: Data period | C9: Orders booked 1-Jan-2026 to 30-Jun-2026. Report as-of date: 30-Jun-2026 (editable on KPI ANALYSIS, cell C4).
B10: Prepared by | C10: [Your Name] - portfolio project (not an employee report).
B12: HOW TO NAVIGATE (click a sheet name)
B13: OPERATIONS DASHBOARD | C13: Start here if you have 2 minutes: KPI cards, 6 charts, overdue-order list. Yellow boxes filter everything.
B14: KPI ANALYSIS | C14: Every KPI with formula, numerator, denominator, exclusions and interpretation.
B15: PIVOT ANALYSIS | C15: Summary tables by product, month, customer type, region, stage and delay reason.
B16: BUSINESS RECOMMENDATIONS | C16: Findings (with live supporting numbers) and 9 prioritised recommendations.
B17: CLEANED DATA | C17: The validated dataset. Dark headers = inputs, teal headers = formula columns.
B18: RAW DATA | C18: The original export, untouched, including its errors.
B19: DATA QUALITY LOG | C19: Live quality checks, the cleaning rules and every cell that was changed or flagged.
B20: DATA DICTIONARY | C20: Meaning of every column in RAW and CLEANED data.
B22: HOW TO READ THE DASHBOARD
B23: Order completion | C23: Completed (installed) orders ÷ non-cancelled orders. Recent orders that are not due yet still count as open, so June looks lower.
B24: On-time delivery | C24: Deliveries on or before the promised date ÷ deliveries with valid dates. Undelivered and cancelled orders are not in this rate.
B25: Installation completion | C25: Installations that were due by the as-of date and are done ÷ installations due.
B26: Overdue | C26: An open order past the promise for the stage it is in. A promise after the as-of date is 'not yet due', never overdue.
B27: Colours | C27: Teal = performance, red = late/overdue, amber = in progress, grey = cancelled/neutral.
B29: TOOLS
C30: Excel formulas (COUNTIFS, SUMIFS, AVERAGEIFS, INDEX/MATCH, LARGE, SUMPRODUCT), named cells, data validation dropdowns, conditional formatting, charts. The file was generated with Python (pandas, openpyxl) and recalculated in LibreOffice; open it in Excel and press Ctrl+Alt+F9 once to force a full recalculation. PivotTables/slicers are not included because the generator cannot create them - PIVOT ANALYSIS gives formula equivalents and 5 steps to add one.

Sheet RAW DATA
A1: RAW DATA - original export exactly as received (do not edit)
A2: SIMULATED DATA - synthetic records created for a portfolio case study. Not real company performance.
A3: 163 rows including 3 duplicate rows and deliberate data-entry problems. Values are stored as text, as an export would deliver them. The cleaned version is on CLEANED DATA.
A5: Order ID | B5: Order Date | C5: Customer Ref | D5: Customer Type | E5: Region | F5: Product Category | G5: Units | H5: Order Value (INR) | I5: Expected Delivery | J5: Dispatch Date | K5: Delivery Date | L5: Expected Installation | M5: Installation Date | N5: Status | O5: Delivery Delay Reason | P5: Installation Delay Reason | Q5: Cancellation Reason | R5: Notes
A6: NHP-0001 | B6: 03-01-2026 | C6: CUST-7126 | D6: Institutional | E6: Other States | F6: Commercial Heat Pump | G6: 2 | H6: 794000 | I6: 25-01-2026 | J6: 09-01-2026 | K6: 15-01-2026 | L6: 30-01-2026 | M6: 20-01-2026 | N6: Completed
A7: NHP-0002 | B7: 08-01-2026 | C7: CUST-6574 | D7: Institutional | E7: Other States | F7: Commercial Heat Pump | G7: 2 | H7: 1090000 | I7: 30-01-2026 | J7: 03-02-2026 | K7: 18-02-2026 | L7: 04-02-2026 | M7: 23-02-2026 | N7: Completed | O7: Component shortage | P7: Knock-on from late delivery | R7: Customer requested weekend install
A8: NHP-0003 | B8: 10-01-2026 | C8: CUST-4483 | D8: Commercial | E8: Bengaluru | F8: Commercial Heat Pump | G8: 4 | H8: 2232000 | I8: 28-01-2026 | J8: 31-01-2026 | K8: 02-02-2026 | L8: 02-02-2026 | M8: 06-02-2026 | N8: Completed | O8: Component shortage | R8: Site survey done
A9: NHP-0004 | B9: 12-01-2026 | C9: CUST-6930 | D9: Commercial | E9: Rest of Karnataka | F9: Heat Pump Dryer | G9: 1 | H9: 783000 | I9: 04-02-2026 | J9: 01-02-2026 | K9: 05-02-2026 | L9: 09-02-2026 | M9: 13-02-2026 | N9: Completed | O9: Production backlog | P9: Technician availability | R9: Site survey done
A10: NHP-0005 | B10: 15-01-2026 | C10: CUST-7543 | D10: Institutional | E10: Other States | F10: Commercial Heat Pump | G10: 3 | H10: 1998000 | I10: 06-02-2026 | J10: 02-02-2026 | K10: 11-02-2026 | L10: 11-02-2026 | M10: 28-02-2026 | N10: Completed | O10: Production backlog | R10: Site survey done
A11: NHP-0006 | B11: 21-01-2026 | C11: CUST-5374 | D11: Institutional | E11: Bengaluru | F11: Custom Requirement | G11: 2 | H11: 2244000 | I11: 20-02-2026 | J11: 18-02-2026 | K11: 20-02-2026 | L11: 25-02-2026 | M11: 17-02-2026 | N11: Completed | R11: Site survey done
A12: NHP-0007 | B12: 22-01-2026 | C12: CUST-6573 | D12: Commercial | E12: Bengaluru | F12: Custom Requirement | G12: 1 | H12: 783000 | I12: 21-02-2026 | J12: 19-02-2026 | K12: 31-02-2026 | L12: 26-02-2026 | M12: 25-02-2026 | N12: COMPLETED | R12: Electrical load checked
A13: NHP-0008 | B13: 2026/01/23 | C13: CUST-5339 | D13: Institutional | E13: Bengaluru | F13: Commercial Heat Pump | G13: 2 | H13: 1038000 | I13: 10-02-2026 | J13: 31-01-2026 | K13: 02-02-2026 | L13: 15-02-2026 | M13: 16-02-2026 | N13: Completed | R13: Customer requested weekend install
A14: NHP-0009 | B14: 24-01-2026 | C14: CUST-1520 | D14: Institutional | E14: Bengaluru | F14: Commercial Heat Pump | G14: 2 | H14: 1594000 | I14: 11-02-2026 | J14: 15-02-2026 | K14: 16-02-2026 | L14: 16-02-2026 | M14: 19-02-2026 | N14: Completed | O14: Component shortage | P14: Knock-on from late delivery
A15: NHP-0010 | B15: 26-01-2026 | C15: CUST-2679 | D15: Residential | E15: Bengaluru | F15: Swimming Pool Heat Pump | G15: 1 | H15: 249000 | I15: 09-02-2026 | J15: 04-02-2026 | K15: 05-02-2026 | L15: 12-02-2026 | M15: 06-02-2026 | N15: Completed | R15: Customer requested weekend install
A16: NHP-0011 | B16: 29-01-2026 | C16: CUST-6881 | D16: Commercial | E16: Rest of Karnataka | F16: Heat Pump Dryer | G16: 2 | H16: 846000 | I16: 21-02-2026 | J16: 22-02-2026 | K16: 26-02-2026 | L16: 26-02-2026 | M16: 01-03-2026 | N16: Completed | O16: Production backlog | P16: Knock-on from late delivery
A17: NHP-0012 | B17: 29-01-2026 | C17: CUST-5374 | D17: Residential | E17: Other States | F17: Heat Pump Water Heater | G17: 1 | H17: 174000 | I17: 12-02-2026 | J17: 01-02-2026 | K17: 08-02-2026 | L17: 15-02-2026 | M17: 09-02-2026 | N17: Completed
A18: NHP-0013 | B18: 30-01-2026 | C18: CUST-9669 | D18: Residential | E18: Rest of Karnataka | F18: Heat Pump Water Heater | G18: 1 | H18: 131000 | I18: 11-02-2026 | J18: 07-02-2026 | K18: 11-02-2026 | L18: 14-02-2026 | M18: 12-02-2026 | N18: Completed | R18: Replacement of old geyser
A19: NHP-0014 | B19: 01-02-2026 | C19: CUST-2519 | D19: Institutional | E19: Bengaluru | F19: Commercial Heat Pump | G19: 1 | H19: 448000 | I19: 19-02-2026 | J19: 13-02-2026 | K19: 15-02-2026 | L19: 24-02-2026 | M19: 18-02-2026 | N19: Completed | R19: Customer requested weekend install
A20: NHP-0015 | B20: 02-02-2026 | C20: CUST-5315 | D20: Commercial | E20: Rest of Karnataka | F20: Commercial Heat Pump | G20: 1 | H20: 798000 | I20: 22-02-2026 | J20: 24-02-2026 | K20: 26-02-2026 | L20: 27-02-2026 | M20: 03-03-2026 | N20: Completed | O20: Production backlog | P20: Knock-on from late delivery | R20: Electrical load checked
A21: NHP-0016 | B21: 03-02-2026 | C21: CUST-6573 | D21: Commercial | E21: Other States | F21: Heat Pump Dryer | G21: 1 | H21: 574000 | I21: 28-02-2026 | J21: 26-02-2026 | K21: 08-03-2026 | L21: 05-03-2026 | M21: 19-03-2026 | N21: Completed | O21: Component shortage | P21: Customer site not ready
A22: NHP-0017 | B22: 03-02-2026 | C22: CUST-1488 | D22: Commercial | E22: Bengaluru | F22: Custom Requirement | G22: 2 | H22: 2040000 | I22: 05-03-2026 | J22: 11-02-2026 | K22: 13-02-2026 | L22: 10-03-2026 | N22: Cancelled | Q22: Customer postponed project | R22: Unit returned to factory after delivery
A23: NHP-0018 | B23: 03-02-2026 | C23: CUST-3621 | D23: Commercial | E23: Rest of Karnataka | F23: Custom Requirement | G23: 1 | H23: 1311000 | I23: 07-03-2026 | J23: 04-03-2026 | K23: 08-03-2026 | L23: 12-03-2026 | M23: 13-03-2026 | N23: Completed | O23: Production backlog | P23: Knock-on from late delivery
A24: NHP-0019 | B24: 07-02-2026 | C24: CUST-7065 | D24: Commercial | E24: Bengaluru | F24: Heat Pump Dryer | G24: 2 | H24: 1122000 | I24: 28-02-2026 | J24: 25-02-2026 | K24: 26-02-2026 | L24: 05-03-2026 | M24: 12-03-2026 | N24: Completed
A25: NHP-0020 | B25: 07-02-2026 | C25: CUST-3340 | D25: Residential | E25: Other States | F25: HP Water Heater | G25: 1 | H25: 160000 | I25: 21-02-2026 | J25: 12-02-2026 | K25: 21-02-2026 | L25: 24-02-2026 | M25: 26-02-2026 | N25: Completed | P25: Technician availability | R25: Electrical load checked
A26: NHP-0021 | B26: 08-02-2026 | C26: CUST-4657 | D26: residential | E26: Bengaluru | F26: Heat Pump Water Heater | G26: 1 | H26: 153000 | I26: 18-02-2026 | J26: 12-02-2026 | L26: 21-02-2026 | N26: Canceled | Q26: Long lead time
A27: NHP-0022 | B27: 09-02-2026 | C27: CUST-4811 | D27: Commercial | E27: Bengaluru | F27: Pool Heat Pump | G27: 2 | H27: 870000 | I27: 23-02-2026 | J27: 17-02-2026 | K27: 18-02-2026 | L27: 26-02-2026 | M27: 20-02-2026 | N27: completed | R27: Site survey done
A28: NHP-0023 | B28: 10-02-2026 | C28: CUST-1916 | D28: Institutional | E28: Bengaluru | F28: Custom Requirement | G28: 2 | H28: 1898000 | I28: 12-03-2026 | L28: 17-03-2026 | N28: Canceled | Q28: Price / budget | R28: Electrical load checked
A29: NHP-0024 | B29: 11-02-2026 | C29: CUST-2824 | D29: Commercial | E29: Bengaluru | F29: Custom Requirement | G29: 2 | H29: 1434000 | I29: 13-03-2026 | J29: 05-03-2026 | K29: 06-03-2026 | L29: 18-03-2026 | M29: 19-03-2026 | N29: Completed | P29: Customer site not ready | R29: Pipe routing confirmed
A30: NHP-0025 | B30: 14-02-2026 | C30: CUST-4657 | D30: Residential | E30: Rest of Karnataka | F30: Heat Pump Water Heater | G30: 1 | H30: 157000 | I30: 26-02-2026 | J30: 19-02-2026 | K30: 22-02-2026 | L30: 01-03-2026 | M30: 23-02-2026 | N30: Completed | R30: Pipe routing confirmed
A31: NHP-0026 | B31: 14-02-2026 | C31: CUST-7126 | D31: Comm. | E31: Bengaluru | F31: Swimming Pool Heat Pump | G31: 2 | H31: 632000 | I31: 28-02-2026 | J31: 25-02-2026 | K31: 27-02-2026 | L31: 03-03-2026 | M31: 28-02-2026 | N31: Completed | R31: Pipe routing confirmed
A32: NHP-0027 | B32: 17-02-2026 | C32: CUST-3664 | D32: Residential | E32: Rest of Karnataka | F32: HP Water Heater | G32: 1 | H32: 185000 | I32: 01-03-2026 | J32: 21-02-2026 | K32: 25-02-2026 | L32: 04-03-2026 | M32: 27-02-2026 | N32: Completed | R32: Customer requested weekend install
A33: NHP-0028 | B33: 17-02-2026 | C33: CUST-6574 | D33: Commercial | E33: Bengaluru | F33: Custom Requirement | G33: 2 | H33: 1670000 | I33: 19-03-2026 | J33: 27-03-2026 | K33: 28-03-2026 | L33: 24-03-2026 | M33: 01-04-2026 | N33: Completed | O33: Production backlog
A34: NHP-0029 | B34: 18-02-2026 | C34: CUST-4432 | D34: Commercial | E34: Bengaluru | F34: Swimming Pool Heat Pump | G34: 2 | H34: 900000 | I34: 04-03-2026 | J34: 27-02-2026 | K34: 01-03-2026 | L34: 07-03-2026 | M34: 03-03-2026 | N34: Completed
A35: NHP-0030 | B35: 20-02-2026 | C35: CUST-9669 | D35: Institutional | E35: Bengaluru | F35: Commercial Heat Pump | G35: 3 | H35: 3144000 | I35: 10-03-2026 | J35: 15-03-2026 | K35: 17-03-2026 | L35: 15-03-2026 | M35: 22-03-2026 | N35: Completed | O35: Production backlog | P35: Knock-on from late delivery | R35: Replacement of old geyser
A36: NHP-0031 | B36: 20-02-2026 | C36: CUST-5808 | D36: Commercial | E36: Bengaluru | F36: Heat Pump Dryer | G36: 1 | H36: 619000 | I36: 13-03-2026 | J36: 24-02-2026 | K36: 26-02-2026 | L36: 18-03-2026 | M36: 03-03-2026 | N36: Completed | R36: Replacement of old geyser
A37: NHP-0031 | B37: 20-02-2026 | C37: CUST-5808 | D37: Commercial | E37: Bengaluru | F37: Heat Pump Dryer | G37: 1 | H37: 619000 | I37: 13-03-2026 | J37: 24-02-2026 | K37: 26-02-2026 | L37: 18-03-2026 | M37: 03-03-2026 | N37: Completed | R37: Replacement of old geyser
A38: NHP-0032 | B38: 2026/02/24 | C38: CUST-5119 | D38: Residential | E38: Rest of Karnataka | F38: Heat Pump Water Heater | G38: 1 | H38: 183000 | I38: 08-03-2026 | J38: 04-03-2026 | K38: 08-03-2026 | L38: 11-03-2026 | M38: 16-03-2026 | N38: Completed
A39: NHP-0033 | B39: 24-02-2026 | C39: CUST-4150 | D39: Commercial | E39: Bengaluru | F39: Commercial Heat Pump | G39: 4 | H39: 2952000 | I39: 14-03-2026 | J39: 17-03-2026 | K39: 18-03-2026 | L39: 19-03-2026 | M39: 15-03-2026 | N39: Completed | P39: Knock-on from late delivery
A40: NHP-0034 | B40: 25-02-2026 | C40: CUST-3547 | D40: Commercial | E40: Bengaluru | F40: Swimming Pool Heat Pump | G40: 2 | H40: 488000 | I40: 11-03-2026 | J40: 02-03-2026 | K40: 04-03-2026 | L40: 14-03-2026 | M40: 16-03-2026 | N40: Completed | P40: Customer site not ready
A41: NHP-0035 | B41: 25-02-2026 | C41: CUST-8428 | D41: Residential | E41: Bengaluru | F41: Swimming Pool Heat Pump | G41: 1 | I41: 11-03-2026 | J41: 12-03-2026 | K41: 14-03-2026 | L41: 14-03-2026 | M41: 17-03-2026 | N41: Completed | O41: Production backlog | P41: Knock-on from late delivery
A42: NHP-0036 | B42: 26-02-2026 | C42: CUST-4257 | D42: Commercial | E42: Bengaluru | F42: Heat Pump Water Heater | G42: 2 | H42: 264000 | I42: 08-03-2026 | J42: 27-02-2026 | K42: 28-02-2026 | L42: 11-03-2026 | M42: 09-03-2026 | N42: Completed | R42: Customer requested weekend install
A43: NHP-0037 | B43: 27-02-2026 | C43: CUST-5371 | D43: Commercial | E43: Bengaluru | F43: Commercial Heat Pump | G43: 1 | H43: Rs. 1,055,000 | I43: 17-03-2026 | J43: 09-03-2026 | K43: 11-03-2026 | L43: 22-03-2026 | M43: 15-03-2026 | N43: Completed | R43: Electrical load checked
A44: NHP-0038 | B44: 01-03-2026 | C44: CUST-4527 | D44: Institutional | E44: Bengaluru | F44: Heat Pump Dryer | G44: 1 | H44: 753000 | I44: 22-03-2026 | L44: 27-03-2026 | N44: Cancelled | Q44: Customer postponed project | R44: Electrical load checked
A45: NHP-0039 | B45: 01-03-2026 | C45: CUST-7916 | D45: Institutional | E45: Bengaluru | F45: Heat Pump Water Heater | G45: 2 | H45: 260000 | I45: 11-03-2026 | J45: 04-03-2026 | K45: 05-03-2026 | L45: 14-03-2026 | M45: 06-03-2026 | N45: Completed
A46: NHP-0040 | B46: 02-03-2026 | C46: CUST-1916 | D46: Institutional | E46: Bengaluru | F46: Heat Pump Dryer | G46: 2 | H46: 1030000 | I46: 23-03-2026 | J46: 17-03-2026 | K46: 18-03-2026 | L46: 28-03-2026 | M46: 02-04-2026 | N46: Completed | P46: Customer site not ready | R46: Electrical load checked
A47: NHP-0041 | B47: 03-03-2026 | C47: CUST-2084 | D47: Commercial | E47: Bengaluru | F47: Swimming Pool Heat Pump | G47: 1 | H47: 426000 | I47: 17-03-2026 | J47: 13-03-2026 | K47: 14-03-2026 | L47: 20-03-2026 | M47: 15-03-2026 | N47: Completed
A48: NHP-0042 | B48: 09-03-2026 | C48: CUST-7912 | D48: Institutional | E48: Bengaluru | F48: Commercial Heat Pump | G48: 3 | H48: 1974000 | I48: 27-03-2026 | J48: 21-03-2026 | K48: 23-03-2026 | L48: 01-04-2026 | M48: 27-03-2026 | N48: Completed | R48: Electrical load checked
A49: NHP-0043 | B49: 10-03-2026 | C49: CUST-5741 | D49: Residential | E49: Bengaluru | F49: Swimming Pool Heat Pump | G49: 1 | H49: 225000 | I49: 24-03-2026 | J49: 21-03-2026 | K49: 23-03-2026 | L49: 27-03-2026 | M49: 24-03-2026 | N49: Completed | R49: Electrical load checked
A50: NHP-0044 | B50: 14-03-2026 | C50: CUST-6313 | D50: Commercial | E50: Bengaluru | F50: Swimming Pool Heat Pump | G50: 2 | H50: 1174000 | I50: 28-03-2026 | J50: 25-03-2026 | K50: 27-03-2026 | L50: 31-03-2026 | M50: 29-03-2026 | N50: Completed
A51: NHP-0045 | B51: 15-03-2026 | C51: CUST-9179 | D51: Residential | E51: Rest of Karnataka | F51: Swimming Pool Heat Pump | G51: 1 | H51: 499000 | I51: 31-03-2026 | J51: 23-03-2026 | K51: 26-03-2026 | L51: 03-04-2026 | M51: 27-03-2026 | N51: Completed
A52: NHP-0046 | B52: 17-03-2026 | C52: CUST-9830 | D52: Residential | E52: Bengaluru | F52: Heat Pump Water Heater | G52: 1 | H52: 197000 | I52: 27-03-2026 | J52: 25-03-2026 | K52: 26-03-2026 | L52: 30-03-2026 | M52: 25-06-2026 | N52: completed | P52: Customer site not ready | R52: Site survey done
A53: NHP-0047 | B53: 18-03-2026 | C53: CUST-7224 | D53: Commercial | E53: Bengaluru | F53: Swimming Pool Heat Pump | G53: 1 | H53: 517000 | I53: 01-04-2026 | J53: 25-03-2026 | K53: 27-03-2026 | L53: 04-04-2026 | M53: 28-03-2026 | N53: Completed | R53: Electrical load checked
A54: NHP-0048 | B54: 18-03-2026 | C54: CUST-7252 | D54: Commercial | E54: Rest of Karnataka | F54: Swimming Pool Heat Pump | G54: 1 | H54: 469000 | I54: 03-04-2026 | J54: 28-03-2026 | K54: 30-03-2026 | L54: 06-04-2026 | M54: 31-03-2026 | N54: Completed | R54: Pipe routing confirmed
A55: NHP-0049 | B55: 19-03-2026 | C55: CUST-2291 | D55: Residential | E55: Bengaluru | F55: Heat Pump Water Heater | G55: 1 | H55: 198000 | I55: 29-03-2026 | J55: 23-03-2026 | K55: 25-03-2026 | L55: 01-04-2026 | M55: 27-03-2026 | N55: Completed | R55: Electrical load checked
A56: NHP-0050 | B56: 19-03-2026 | C56: CUST-2824 | D56: Institutional | E56: Other States | F56: Custom Requirement | G56: 1 | H56: 503000 | I56: 22-04-2026 | J56: 17-04-2026 | K56: 02-05-2026 | L56: 27-04-2026 | N56: Pending | O56: Transport scheduling
A57: NHP-0051 | B57: 21-03-2026 | C57: CUST-2169 | D57: Commercial | E57: Bengaluru | F57: Swimming Pool Heat Pump | G57: 1 | H57: 347000 | I57: 04-04-2026 | J57: 31-03-2026 | K57: 02-04-2026 | L57: 07-04-2026 | M57: 04-04-2026 | N57: Completed | R57: Site survey done
A58: NHP-0052 | B58: 25-03-2026 | C58: CUST-5119 | D58: Residential | E58: Bengaluru | F58: Swimming Pool Heat Pump | G58: 1 | H58: 439000 | I58: 08-04-2026 | J58: 05-04-2026 | K58: 07-04-2026 | L58: 11-04-2026 | M58: 08-04-2026 | N58: Completed | R58: Site survey done
A59: NHP-0053 | B59: 25-03-2026 | C59: CUST-2169 | D59: Institutional | E59: Bengaluru | F59: Commercial Heat Pump | G59: 1 | H59: 1005000 | I59: 12-04-2026 | J59: 06-04-2026 | K59: 07-04-2026 | L59: 17-04-2026 | M59: 12-04-2026 | N59: Completed | R59: Customer requested weekend install
A60: NHP-0054 | B60: 25-03-2026 | C60: CUST-5304 | D60: Commercial | E60: Other States | F60: Heat Pump Water Heater | G60: 1 | H60: 117000 | I60: 08-04-2026 | J60: 27-03-2026 | K60: 07-04-2026 | L60: 11-04-2026 | M60: 08-04-2026 | N60: Completed
A61: NHP-0055 | B61: 26-03-2026 | C61: CUST-3287 | D61: Residential | E61: Other States | F61: Swimming Pool Heat Pump | G61: 1 | H61: 372000 | I61: 13-04-2026 | J61: 06-04-2026 | K61: 14-04-2026 | L61: 16-04-2026 | M61: 15-04-2026 | N61: Completed | O61: Dispatch scheduling
A62: NHP-0056 | B62: 2026/03/27 | C62: CUST-1488 | D62: Commercial | E62: Bengaluru | F62: Heat Pump Dryer | G62: 2 | H62: 1000000 | I62: 17-04-2026 | J62: 08-04-2026 | K62: 09-04-2026 | L62: 22-04-2026 | M62: 14-04-2026 | N62: Complete | R62: Pipe routing confirmed
A63: NHP-0057 | B63: 27-03-2026 | C63: CUST-9279 | D63: residential | E63: Bengaluru | F63: Heat Pump Water Heater | G63: 1 | H63: 174000 | I63: 06-04-2026 | J63: 28-03-2026 | K63: 29-03-2026 | L63: 09-04-2026 | M63: 30-03-2026 | N63: Completed | R63: Electrical load checked
A64: NHP-0058 | B64: 28-03-2026 | C64: CUST-3266 | D64: Commercial | E64: Bengaluru | F64: HP Water Heater | G64: 1 | H64: 202000 | I64: 07-04-2026 | J64: 31-03-2026 | L64: 10-04-2026 | N64: Cancelled | Q64: Long lead time | R64: Site survey done
A65: NHP-0059 | B65: 28-03-2026 | C65: CUST-9179 | D65: Residential | E65: Bengaluru | F65: Heat Pump Water Heater | G65: 1 | H65: 134000 | I65: 07-04-2026 | J65: 04-04-2026 | K65: 05-04-2026 | L65: 10-04-2026 | N65: Pending | P65: Customer site not ready | R65: Customer civil work in progress
A66: NHP-0060 | B66: 28-03-2026 | C66: CUST-2307 | D66: Institutional | E66: Bengaluru | F66: Custom Requirement | G66: 1 | H66: 1023000 | I66: 27-04-2026 | J66: 25-06-2026 | K66: 26-06-2026 | L66: 02-05-2026 | M66: 29-06-2026 | N66: Completed | O66: Component shortage | P66: Knock-on from late delivery | R66: Pipe routing confirmed
A67: NHP-0061 | B67: 30-03-2026 | C67: CUST-4456 | D67: Residential | E67: Rest of Karnataka | F67: Swimming Pool Heat Pump | G67: 1 | H67: 498000 | I67: 15-04-2026 | J67: 10-04-2026 | K67: 13-04-2026 | L67: 18-04-2026 | M67: 15-04-2026 | N67: Completed | R67: Site survey done
A68: NHP-0062 | B68: 31-03-2026 | C68: CUST-3287 | D68: Institutional | E68: Other States | F68: Heat Pump Water Heater | G68: 2 | H68: 312000 | I68: 14-04-2026 | J68: 05-04-2026 | K68: 11-04-2026 | L68: 17-04-2026 | M68: 22-06-2026 | N68: Completed | R68: Electrical load checked
A69: NHP-0063 | B69: 03-04-2026 | C69: CUST-1106 | D69: Commercial | E69: Rest of Karnataka | F69: Pool Heat Pump | G69: 1 | H69: 225000 | I69: 19-04-2026 | J69: 19-04-2026 | K69: 23-04-2026 | L69: 22-04-2026 | M69: 06-05-2026 | N69: Completed | O69: Production backlog | P69: Customer site not ready | R69: Electrical load checked
A70: NHP-0064 | B70: 04-04-2026 | C70: CUST-3591 | D70: Residential | E70: Bengaluru | F70: Heat Pump Water Heater | G70: 1 | H70: 208000 | I70: 14-04-2026 | J70: 11-04-2026 | K70: 13-04-2026 | L70: 17-04-2026 | M70: 15-04-2026 | N70: Completed
A71: NHP-0065 | B71: 04-04-2026 | C71: CUST-2876 | D71: Commercial | E71: Bengaluru | F71: Commercial Heat Pump | G71: 4 | H71: 1348000 | I71: 22-04-2026 | J71: 18-04-2026 | K71: 19-04-2026 | L71: 27-04-2026 | M71: 30-05-2026 | N71: Completed | P71: Customer site not ready
A72: NHP-0066 | B72: 05-04-2026 | C72: CUST-3677 | D72: Institutional | E72: Bengaluru | F72: Commercial Heat Pump | G72: 4 | H72: 1476000 | I72: 23-04-2026 | J72: 23-04-2026 | K72: 24-04-2026 | L72: 28-04-2026 | M72: 27-04-2026 | N72: Completed | O72: Production backlog
A73: NHP-0067 | B73: 05-04-2026 | C73: CUST-5554 | D73: Commercial | E73: Other States | F73: Commercial Heat Pump | G73: 2 | H73: 1190000 | I73: 27-04-2026 | J73: 19-04-2026 | K73: 26-04-2026 | L73: 02-05-2026 | M73: 01-05-2026 | N73: Completed | R73: Pipe routing confirmed
A74: NHP-0068 | B74: 08-04-2026 | C74: CUST-1520 | D74: Residential | E74: Bengaluru | F74: Heat Pump Water Heater | G74: 1 | H74: 213000 | I74: 18-04-2026 | J74: 11-04-2026 | L74: 21-04-2026 | N74: Cancelled | Q74: Price / budget
A75: NHP-0069 | B75: 08-04-2026 | C75: CUST-6635 | D75: Residential | E75: Other States | F75: Heat Pump Water Heater | G75: 1 | H75: 175000 | I75: 22-04-2026 | J75: 16-04-2026 | K75: 24-04-2026 | L75: 25-04-2026 | N75: PENDING | P75: Customer site not ready | R75: Customer civil work in progress
A76: NHP-0070 | B76: 09-04-2026 | C76: CUST-2674 | D76: Institutional | E76: Rest of Karnataka | F76: Commercial Heat Pump | G76: 1 | H76: 433000 | I76: 29-04-2026 | J76: 20-04-2026 | K76: 23-04-2026 | L76: 04-05-2026 | M76: 03-05-2026 | N76: Completed | R76: Site survey done
A77: NHP-0071 | B77: 12-04-2026 | C77: CUST-4257 | D77: Commercial | E77: Bengaluru | F77: Heat Pump Water Heater | G77: 1 | H77: 147000 | I77: 22-04-2026 | J77: 22-04-2026 | K77: 23-04-2026 | L77: 25-04-2026 | M77: 24-04-2026 | N77: Completed | R77: Replacement of old geyser
A78: NHP-0072 | B78: 12-04-2026 | C78: CUST-6925 | D78: Commercial | E78: Bengaluru | F78: Commercial Heat Pump | G78: 2 | H78: 1284000 | I78: 30-04-2026 | J78: 30-04-2026 | K78: 01-05-2026 | L78: 05-05-2026 | M78: 05-05-2026 | N78: Completed | R78: Replacement of old geyser
A79: NHP-0073 | B79: 14-04-2026 | C79: CUST-6514 | D79: Institutional | E79: Bengaluru | F79: Commercial Heat Pump | G79: 2 | H79: 692000 | I79: 02-05-2026 | J79: 30-04-2026 | K79: 02-05-2026 | L79: 07-05-2026 | M79: 05-05-2026 | N79: Completed | R79: Customer requested weekend install
A80: NHP-0074 | B80: 15-04-2026 | C80: CUST-7216 | D80: Residential | E80: Bengaluru | F80: Swimming Pool Heat Pump | G80: 1 | H80: 597000 | I80: 29-04-2026 | J80: 22-04-2026 | K80: 23-04-2026 | L80: 02-05-2026 | M80: 26-04-2026 | N80: Completed | R80: Customer requested weekend install
A81: NHP-0075 | B81: 15-04-2026 | C81: CUST-7224 | D81: Residential | E81: Bengaluru | F81: Pool Heat Pump | G81: 1 | I81: 29-04-2026 | J81: 24-04-2026 | K81: 26-04-2026 | L81: 02-05-2026 | M81: 28-04-2026 | N81: Completed
A82: NHP-0076 | B82: 20-04-2026 | C82: CUST-4752 | D82: Commercial | E82: Other States | F82: Commercial Heat Pump | G82: 2 | H82: 708000 | I82: 12-05-2026 | J82: 08-05-2026 | K82: 20-05-2026 | L82: 17-05-2026 | N82: In Progress | O82: Transport scheduling | P82: Customer site not ready | R82: Customer civil work in progress
A83: NHP-0077 | B83: 20-04-2026 | C83: CUST-1188 | D83: Commercial | E83: Bengaluru | F83: Commercial Heat Pump | G83: 3 | H83: 2628000 | I83: 08-05-2026 | J83: 11-05-2026 | K83: 13-05-2026 | L83: 13-05-2026 | M83: 16-05-2026 | N83: Completed | O83: Production backlog | P83: Knock-on from late delivery
A84: NHP-0078 | B84: 20-04-2026 | C84: CUST-4432 | D84: Commercial | E84: Rest of Karnataka | F84: Commercial Heat Pump | G84: 1 | H84: 1175000 | I84: 10-05-2026 | J84: 17-05-2026 | K84: 21-05-2026 | L84: 15-05-2026 | M84: 25-05-2026 | N84: Completed | O84: Production backlog | R84: Electrical load checked
A85: NHP-0079 | B85: 22-04-2026 | C85: CUST-2519 | D85: Commercial | E85: Bengaluru | F85: Custom Requirement | G85: 1 | H85: 801000 | I85: 22-05-2026 | J85: 29-05-2026 | K85: 30-05-2026 | L85: 27-05-2026 | M85: 04-06-2026 | N85: Completed | O85: Component shortage | P85: Knock-on from late delivery | R85: Customer requested weekend install
A86: NHP-0079 | B86: 22-04-2026 | C86: CUST-2519 | D86: Commercial | E86: Bengaluru | F86: Custom Requirement | G86: 1 | H86: 801000 | I86: 22-05-2026 | J86: 29-05-2026 | K86: 30-05-2026 | L86: 27-05-2026 | M86: 04-06-2026 | N86: Completed | O86: Component shortage | P86: Knock-on from late delivery | R86: Customer requested weekend install
A87: NHP-0080 | B87: 23-04-2026 | C87: CUST-2679 | D87: Commercial | E87: Rest of Karnataka | F87: Heat Pump Water Heater | G87: 1 | H87: 179000 | I87: 05-05-2026 | J87: 02-05-2026 | K87: 05-05-2026 | L87: 08-05-2026 | M87: 12-05-2026 | N87: Completed | P87: Customer site not ready | R87: Customer requested weekend install
A88: NHP-0081 | B88: 24-04-2026 | C88: CUST-1520 | D88: Commercial | E88: Bengaluru | F88: Heat Pump Dryer | G88: 2 | H88: 1116000 | I88: 15-05-2026 | J88: 12-05-2026 | K88: 13-05-2026 | L88: 20-05-2026 | M88: 28-05-2026 | N88: Completed
A89: NHP-0082 | B89: 24-04-2026 | C89: CUST-2743 | D89: Residential | E89: Bengaluru | F89: Swimming Pool Heat Pump | G89: 1 | H89: 233000 | I89: 08-05-2026 | J89: 01-01-2026 | K89: 10-05-2026 | L89: 11-05-2026 | M89: 11-05-2026 | N89: Completed | R89: Electrical load checked
A90: NHP-0083 | B90: 26-04-2026 | C90: CUST-4593 | D90: Commercial | E90: Other States | F90: Swimming Pool Heat Pump | G90: 1 | H90: 593000 | I90: 14-05-2026 | J90: 28-04-2026 | K90: 08-05-2026 | L90: 17-05-2026 | M90: 10-05-2026 | N90: Completed | R90: Replacement of old geyser
A91: NHP-0084 | B91: 2026/04/27 | C91: CUST-9928 | D91: Residential | E91: Bengaluru | F91: Heat Pump Water Heater | G91: 1 | H91: 117000 | I91: 07-05-2026 | J91: 02-05-2026 | K91: 03-05-2026 | L91: 10-05-2026 | M91: 13-05-2026 | N91: Completed | P91: Customer site not ready
A92: NHP-0085 | B92: 27-04-2026 | C92: CUST-9317 | D92: Commercial | E92: Bengaluru | F92: Commercial Heat Pump | G92: 2 | H92: 944000 | I92: 15-05-2026 | J92: 05-05-2026 | K92: 07-05-2026 | L92: 20-05-2026 | N92: Pending | R92: Customer requested weekend install
A93: NHP-0086 | B93: 2026/04/27 | C93: CUST-8019 | D93: Commercial | E93: Bengaluru | F93: Heat Pump Water Heater | G93: 2 | H93: 328000 | I93: 07-05-2026 | J93: 01-05-2026 | K93: 03-05-2026 | L93: 10-05-2026 | M93: 15-05-2026 | N93: Completed | P93: Customer site not ready | R93: Site survey done
A94: NHP-0087 | B94: 27-04-2026 | C94: CUST-4593 | D94: Commercial | E94: Bengaluru | F94: Commercial Heat Pump | G94: 3 | H94: 1158000 | I94: 15-05-2026 | J94: 05-05-2026 | K94: 07-05-2026 | L94: 20-05-2026 | M94: 16-05-2026 | N94: Completed
A95: NHP-0088 | B95: 27-04-2026 | C95: CUST-1711 | D95: Commercial | E95: Bengaluru | F95: Heat Pump Dryer | G95: 1 | H95: 410000 | I95: 18-05-2026 | J95: 16-05-2026 | K95: 18-05-2026 | L95: 23-05-2026 | M95: 21-05-2026 | N95: Completed | R95: Site survey done
A96: NHP-0089 | B96: 01-05-2026 | C96: CUST-3266 | D96: Institutional | E96: Bengaluru | F96: Commercial Heat Pump | G96: 2 | H96: 924000 | I96: 19-05-2026 | J96: 13-05-2026 | K96: 15-05-2026 | L96: 24-05-2026 | M96: 19-05-2026 | N96: Completed | R96: Pipe routing confirmed
A97: NHP-0090 | B97: 03-05-2026 | C97: CUST-9348 | D97: Commercial | E97: Bengaluru | F97: Commercial Heat Pump | G97: 1 | H97: 661000 | I97: 21-05-2026 | J97: 31-05-2026 | K97: 02-06-2026 | L97: 26-05-2026 | M97: 05-06-2026 | N97: Completed | O97: Component shortage | P97: Knock-on from late delivery | R97: Site survey done
A98: NHP-0091 | B98: 03-05-2026 | C98: CUST-6977 | D98: Commercial | E98: Other States | F98: commercial heat pump | G98: 1 | H98: 1161000 | I98: 25-05-2026 | J98: 12-05-2026 | K98: 21-05-2026 | L98: 30-05-2026 | M98: 01-06-2026 | N98: Completed | R98: Customer requested weekend install
A99: NHP-0092 | B99: 03-05-2026 | C99: CUST-9279 | D99: Commercial | E99: Rest of Karnataka | F99: commercial heat pump | G99: 1 | H99: 306000 | I99: 23-05-2026 | L99: 28-05-2026 | N99: Cancelled | Q99: Long lead time | R99: Site survey done
A100: NHP-0093 | B100: 2026/05/06 | C100: CUST-3591 | D100: Residential | E100: Rest of Karnataka | F100: Swimming Pool Heat Pump | G100: 1 | H100: 584000 | I100: 22-05-2026 | J100: 11-05-2026 | K100: 15-05-2026 | L100: 25-05-2026 | M100: 18-05-2026 | N100: Completed | R100: Electrical load checked
A101: NHP-0094 | B101: 06-05-2026 | C101: CUST-3287 | D101: Institutional | E101: Rest of Karnataka | F101: Custom Requirement | G101: 1 | H101: 1017000 | I101: 07-06-2026 | J101: 06-06-2026 | K101: 09-06-2026 | L101: 12-06-2026 | M101: 12-06-2026 | N101: Completed | O101: Production backlog | R101: Pipe routing confirmed
...

Sheet CLEANED DATA
A1: Order_ID | B1: Order_Date | C1: Customer_Ref | D1: Customer_Type | E1: Region | F1: Product_Category | G1: Units | H1: Order_Value_INR | I1: Expected_Delivery_Date | J1: Dispatch_Date | K1: Actual_Delivery_Date | L1: Expected_Installation_Date | M1: Actual_Installation_Date | N1: Order_Status | O1: Delivery_Delay_Reason | P1: Installation_Delay_Reason | Q1: Cancellation_Reason | R1: Operational_Notes | S1: DQ_Flag | T1: Valid_Dispatch_Timing | U1: Valid_Delivery_Timing | V1: Valid_Install_Timing | W1: Order_Month | X1: Delivery_Due | Y1: Delivered | Z1: Delivery_Delay_Days | AA1: Delivery_Timeliness | AB1: Install_Due | AC1: Installed | AD1: Install_Delay_Days | AE1: Install_Timeliness | AF1: Production_Days | AG1: Transit_Days | AH1: Install_Lead_Days | AI1: Order_To_Delivery_Days | AJ1: Order_Cycle_Days | AK1: Current_Stage | AL1: Overdue | AM1: Days_Overdue | AN1: Overdue_Stage | AO1: In_Dashboard_Filter | AP1: Overdue_Rank_Key | AR1: Dark headers = validated input values. Teal headers = formulas (do not type over).
A2: NHP-0001 | B2: 46025 | C2: CUST-7126 | D2: Institutional | E2: Other States | F2: Commercial Heat Pump | G2: 2 | H2: 794000 | I2: 46047 | J2: 46031 | K2: 46037 | L2: 46052 | M2: 46042 | N2: Completed | S2: OK | T2: 1 | U2: 1 | V2: 1 | W2: =DATE(YEAR(B2),MONTH(B2),1) -> 46023 | X2: =IF(AND(N2<>"Cancelled",I2<=AsOf),1,0) -> 1 | Y2: =IF(AND(N2<>"Cancelled",OR(ISNUMBER(K2),N2="Completed")),1,0) -> 1 | Z2: =IF(AND(Y2=1,U2=1,ISNUMBER(K2)),K2-I2,"") -> -10 | AA2: =IF(Z2="","",IF(Z2<0,"Early",IF(Z2=0,"On Time","Late"))) -> Early | AB2: =IF(AND(N2<>"Cancelled",L2<=AsOf),1,0) -> 1 | AC2: =IF(AND(N2<>"Cancelled",OR(ISNUMBER(M2),N2="Completed")),1,0) -> 1 | AD2: =IF(AND(AC2=1,V2=1,ISNUMBER(M2)),M2-L2,"") -> -10 | AE2: =IF(AD2="","",IF(AD2<0,"Early",IF(AD2=0,"On Time","Late"))) -> Early | AF2: =IF(AND(T2=1,ISNUMBER(J2),N2<>"Cancelled"),J2-B2,"") -> 6 | AG2: =IF(AND(AF2<>"",Z2<>""),K2-J2,"") -> 6 | AH2: =IF(AND(Z2<>"",AD2<>""),M2-K2,"") -> 5 | AI2: =IF(Z2<>"",K2-B2,"") -> 12 | AJ2: =IF(AND(N2="Completed",AD2<>""),M2-B2,"") -> 17 | AK2: =IF(N2="Cancelled","Cancelled",IF(N2="Completed","Completed",IF(Y2=1,"Awaiting Installation",IF(ISNUMBER(J2),"In Transit","In Production")))) -> Completed | AL2: =IF(AND(N2="Pending",OR(AND(Y2=0,I2<AsOf),AND(Y2=1,L2<AsOf))),1,0) -> 0 | AM2: =IF(AL2=1,IF(Y2=0,AsOf-I2,AsOf-L2),"") | AN2: =IF(AL2=1,IF(Y2=0,"Delivery","Installation"),"") | AO2: =IF(AND(OR(fCat="All",F2=fCat),OR(fCust="All",D2=fCust),OR(fReg="All",E2=fReg)),1,0) -> 1 | AP2: =IF(AND(AL2=1,AO2=1),AM2+ROW()/100000,0) -> 0
A3: NHP-0002 | B3: 46030 | C3: CUST-6574 | D3: Institutional | E3: Other States | F3: Commercial Heat Pump | G3: 2 | H3: 1090000 | I3: 46052 | J3: 46056 | K3: 46071 | L3: 46057 | M3: 46076 | N3: Completed | O3: Component shortage | P3: Knock-on from late delivery | R3: Customer requested weekend install | S3: OK | T3: 1 | U3: 1 | V3: 1 | W3: =DATE(YEAR(B3),MONTH(B3),1) -> 46023 | X3: =IF(AND(N3<>"Cancelled",I3<=AsOf),1,0) -> 1 | Y3: =IF(AND(N3<>"Cancelled",OR(ISNUMBER(K3),N3="Completed")),1,0) -> 1 | Z3: =IF(AND(Y3=1,U3=1,ISNUMBER(K3)),K3-I3,"") -> 19 | AA3: =IF(Z3="","",IF(Z3<0,"Early",IF(Z3=0,"On Time","Late"))) -> Late | AB3: =IF(AND(N3<>"Cancelled",L3<=AsOf),1,0) -> 1 | AC3: =IF(AND(N3<>"Cancelled",OR(ISNUMBER(M3),N3="Completed")),1,0) -> 1 | AD3: =IF(AND(AC3=1,V3=1,ISNUMBER(M3)),M3-L3,"") -> 19 | AE3: =IF(AD3="","",IF(AD3<0,"Early",IF(AD3=0,"On Time","Late"))) -> Late | AF3: =IF(AND(T3=1,ISNUMBER(J3),N3<>"Cancelled"),J3-B3,"") -> 26 | AG3: =IF(AND(AF3<>"",Z3<>""),K3-J3,"") -> 15 | AH3: =IF(AND(Z3<>"",AD3<>""),M3-K3,"") -> 5 | AI3: =IF(Z3<>"",K3-B3,"") -> 41 | AJ3: =IF(AND(N3="Completed",AD3<>""),M3-B3,"") -> 46 | AK3: =IF(N3="Cancelled","Cancelled",IF(N3="Completed","Completed",IF(Y3=1,"Awaiting Installation",IF(ISNUMBER(J3),"In Transit","In Production")))) -> Completed | AL3: =IF(AND(N3="Pending",OR(AND(Y3=0,I3<AsOf),AND(Y3=1,L3<AsOf))),1,0) -> 0 | AM3: =IF(AL3=1,IF(Y3=0,AsOf-I3,AsOf-L3),"") | AN3: =IF(AL3=1,IF(Y3=0,"Delivery","Installation"),"") | AO3: =IF(AND(OR(fCat="All",F3=fCat),OR(fCust="All",D3=fCust),OR(fReg="All",E3=fReg)),1,0) -> 1 | AP3: =IF(AND(AL3=1,AO3=1),AM3+ROW()/100000,0) -> 0
A4: NHP-0003 | B4: 46032 | C4: CUST-4483 | D4: Commercial | E4: Bengaluru | F4: Commercial Heat Pump | G4: 4 | H4: 2232000 | I4: 46050 | J4: 46053 | K4: 46055 | L4: 46055 | M4: 46059 | N4: Completed | O4: Component shortage | R4: Site survey done | S4: OK | T4: 1 | U4: 1 | V4: 1 | W4: =DATE(YEAR(B4),MONTH(B4),1) -> 46023 | X4: =IF(AND(N4<>"Cancelled",I4<=AsOf),1,0) -> 1 | Y4: =IF(AND(N4<>"Cancelled",OR(ISNUMBER(K4),N4="Completed")),1,0) -> 1 | Z4: =IF(AND(Y4=1,U4=1,ISNUMBER(K4)),K4-I4,"") -> 5 | AA4: =IF(Z4="","",IF(Z4<0,"Early",IF(Z4=0,"On Time","Late"))) -> Late | AB4: =IF(AND(N4<>"Cancelled",L4<=AsOf),1,0) -> 1 | AC4: =IF(AND(N4<>"Cancelled",OR(ISNUMBER(M4),N4="Completed")),1,0) -> 1 | AD4: =IF(AND(AC4=1,V4=1,ISNUMBER(M4)),M4-L4,"") -> 4 | AE4: =IF(AD4="","",IF(AD4<0,"Early",IF(AD4=0,"On Time","Late"))) -> Late | AF4: =IF(AND(T4=1,ISNUMBER(J4),N4<>"Cancelled"),J4-B4,"") -> 21 | AG4: =IF(AND(AF4<>"",Z4<>""),K4-J4,"") -> 2 | AH4: =IF(AND(Z4<>"",AD4<>""),M4-K4,"") -> 4 | AI4: =IF(Z4<>"",K4-B4,"") -> 23 | AJ4: =IF(AND(N4="Completed",AD4<>""),M4-B4,"") -> 27 | AK4: =IF(N4="Cancelled","Cancelled",IF(N4="Completed","Completed",IF(Y4=1,"Awaiting Installation",IF(ISNUMBER(J4),"In Transit","In Production")))) -> Completed | AL4: =IF(AND(N4="Pending",OR(AND(Y4=0,I4<AsOf),AND(Y4=1,L4<AsOf))),1,0) -> 0 | AM4: =IF(AL4=1,IF(Y4=0,AsOf-I4,AsOf-L4),"") | AN4: =IF(AL4=1,IF(Y4=0,"Delivery","Installation"),"") | AO4: =IF(AND(OR(fCat="All",F4=fCat),OR(fCust="All",D4=fCust),OR(fReg="All",E4=fReg)),1,0) -> 1 | AP4: =IF(AND(AL4=1,AO4=1),AM4+ROW()/100000,0) -> 0
A5: NHP-0004 | B5: 46034 | C5: CUST-6930 | D5: Commercial | E5: Rest of Karnataka | F5: Heat Pump Dryer | G5: 1 | H5: 783000 | I5: 46057 | J5: 46054 | K5: 46058 | L5: 46062 | M5: 46066 | N5: Completed | O5: Production backlog | P5: Technician availability | R5: Site survey done | S5: OK | T5: 1 | U5: 1 | V5: 1 | W5: =DATE(YEAR(B5),MONTH(B5),1) -> 46023 | X5: =IF(AND(N5<>"Cancelled",I5<=AsOf),1,0) -> 1 | Y5: =IF(AND(N5<>"Cancelled",OR(ISNUMBER(K5),N5="Completed")),1,0) -> 1 | Z5: =IF(AND(Y5=1,U5=1,ISNUMBER(K5)),K5-I5,"") -> 1 | AA5: =IF(Z5="","",IF(Z5<0,"Early",IF(Z5=0,"On Time","Late"))) -> Late | AB5: =IF(AND(N5<>"Cancelled",L5<=AsOf),1,0) -> 1 | AC5: =IF(AND(N5<>"Cancelled",OR(ISNUMBER(M5),N5="Completed")),1,0) -> 1 | AD5: =IF(AND(AC5=1,V5=1,ISNUMBER(M5)),M5-L5,"") -> 4 | AE5: =IF(AD5="","",IF(AD5<0,"Early",IF(AD5=0,"On Time","Late"))) -> Late | AF5: =IF(AND(T5=1,ISNUMBER(J5),N5<>"Cancelled"),J5-B5,"") -> 20 | AG5: =IF(AND(AF5<>"",Z5<>""),K5-J5,"") -> 4 | AH5: =IF(AND(Z5<>"",AD5<>""),M5-K5,"") -> 8 | AI5: =IF(Z5<>"",K5-B5,"") -> 24 | AJ5: =IF(AND(N5="Completed",AD5<>""),M5-B5,"") -> 32 | AK5: =IF(N5="Cancelled","Cancelled",IF(N5="Completed","Completed",IF(Y5=1,"Awaiting Installation",IF(ISNUMBER(J5),"In Transit","In Production")))) -> Completed | AL5: =IF(AND(N5="Pending",OR(AND(Y5=0,I5<AsOf),AND(Y5=1,L5<AsOf))),1,0) -> 0 | AM5: =IF(AL5=1,IF(Y5=0,AsOf-I5,AsOf-L5),"") | AN5: =IF(AL5=1,IF(Y5=0,"Delivery","Installation"),"") | AO5: =IF(AND(OR(fCat="All",F5=fCat),OR(fCust="All",D5=fCust),OR(fReg="All",E5=fReg)),1,0) -> 1 | AP5: =IF(AND(AL5=1,AO5=1),AM5+ROW()/100000,0) -> 0
A6: NHP-0005 | B6: 46037 | C6: CUST-7543 | D6: Institutional | E6: Other States | F6: Commercial Heat Pump | G6: 3 | H6: 1998000 | I6: 46059 | J6: 46055 | K6: 46064 | L6: 46064 | M6: 46081 | N6: Completed | O6: Production backlog | R6: Site survey done | S6: OK | T6: 1 | U6: 1 | V6: 1 | W6: =DATE(YEAR(B6),MONTH(B6),1) -> 46023 | X6: =IF(AND(N6<>"Cancelled",I6<=AsOf),1,0) -> 1 | Y6: =IF(AND(N6<>"Cancelled",OR(ISNUMBER(K6),N6="Completed")),1,0) -> 1 | Z6: =IF(AND(Y6=1,U6=1,ISNUMBER(K6)),K6-I6,"") -> 5 | AA6: =IF(Z6="","",IF(Z6<0,"Early",IF(Z6=0,"On Time","Late"))) -> Late | AB6: =IF(AND(N6<>"Cancelled",L6<=AsOf),1,0) -> 1 | AC6: =IF(AND(N6<>"Cancelled",OR(ISNUMBER(M6),N6="Completed")),1,0) -> 1 | AD6: =IF(AND(AC6=1,V6=1,ISNUMBER(M6)),M6-L6,"") -> 17 | AE6: =IF(AD6="","",IF(AD6<0,"Early",IF(AD6=0,"On Time","Late"))) -> Late | AF6: =IF(AND(T6=1,ISNUMBER(J6),N6<>"Cancelled"),J6-B6,"") -> 18 | AG6: =IF(AND(AF6<>"",Z6<>""),K6-J6,"") -> 9 | AH6: =IF(AND(Z6<>"",AD6<>""),M6-K6,"") -> 17 | AI6: =IF(Z6<>"",K6-B6,"") -> 27 | AJ6: =IF(AND(N6="Completed",AD6<>""),M6-B6,"") -> 44 | AK6: =IF(N6="Cancelled","Cancelled",IF(N6="Completed","Completed",IF(Y6=1,"Awaiting Installation",IF(ISNUMBER(J6),"In Transit","In Production")))) -> Completed | AL6: =IF(AND(N6="Pending",OR(AND(Y6=0,I6<AsOf),AND(Y6=1,L6<AsOf))),1,0) -> 0 | AM6: =IF(AL6=1,IF(Y6=0,AsOf-I6,AsOf-L6),"") | AN6: =IF(AL6=1,IF(Y6=0,"Delivery","Installation"),"") | AO6: =IF(AND(OR(fCat="All",F6=fCat),OR(fCust="All",D6=fCust),OR(fReg="All",E6=fReg)),1,0) -> 1 | AP6: =IF(AND(AL6=1,AO6=1),AM6+ROW()/100000,0) -> 0
A7: NHP-0006 | B7: 46043 | C7: CUST-5374 | D7: Institutional | E7: Bengaluru | F7: Custom Requirement | G7: 2 | H7: 2244000 | I7: 46073 | J7: 46071 | K7: 46073 | L7: 46078 | M7: 46070 | N7: Completed | R7: Site survey done | S7: Installed before delivery | T7: 1 | U7: 1 | V7: 0 | W7: =DATE(YEAR(B7),MONTH(B7),1) -> 46023 | X7: =IF(AND(N7<>"Cancelled",I7<=AsOf),1,0) -> 1 | Y7: =IF(AND(N7<>"Cancelled",OR(ISNUMBER(K7),N7="Completed")),1,0) -> 1 | Z7: =IF(AND(Y7=1,U7=1,ISNUMBER(K7)),K7-I7,"") -> 0 | AA7: =IF(Z7="","",IF(Z7<0,"Early",IF(Z7=0,"On Time","Late"))) -> On Time | AB7: =IF(AND(N7<>"Cancelled",L7<=AsOf),1,0) -> 1 | AC7: =IF(AND(N7<>"Cancelled",OR(ISNUMBER(M7),N7="Completed")),1,0) -> 1 | AD7: =IF(AND(AC7=1,V7=1,ISNUMBER(M7)),M7-L7,"") | AE7: =IF(AD7="","",IF(AD7<0,"Early",IF(AD7=0,"On Time","Late"))) | AF7: =IF(AND(T7=1,ISNUMBER(J7),N7<>"Cancelled"),J7-B7,"") -> 28 | AG7: =IF(AND(AF7<>"",Z7<>""),K7-J7,"") -> 2 | AH7: =IF(AND(Z7<>"",AD7<>""),M7-K7,"") | AI7: =IF(Z7<>"",K7-B7,"") -> 30 | AJ7: =IF(AND(N7="Completed",AD7<>""),M7-B7,"") | AK7: =IF(N7="Cancelled","Cancelled",IF(N7="Completed","Completed",IF(Y7=1,"Awaiting Installation",IF(ISNUMBER(J7),"In Transit","In Production")))) -> Completed | AL7: =IF(AND(N7="Pending",OR(AND(Y7=0,I7<AsOf),AND(Y7=1,L7<AsOf))),1,0) -> 0 | AM7: =IF(AL7=1,IF(Y7=0,AsOf-I7,AsOf-L7),"") | AN7: =IF(AL7=1,IF(Y7=0,"Delivery","Installation"),"") | AO7: =IF(AND(OR(fCat="All",F7=fCat),OR(fCust="All",D7=fCust),OR(fReg="All",E7=fReg)),1,0) -> 1 | AP7: =IF(AND(AL7=1,AO7=1),AM7+ROW()/100000,0) -> 0
A8: NHP-0007 | B8: 46044 | C8: CUST-6573 | D8: Commercial | E8: Bengaluru | F8: Custom Requirement | G8: 1 | H8: 783000 | I8: 46074 | J8: 46072 | L8: 46079 | M8: 46078 | N8: Completed | R8: Electrical load checked | S8: Invalid Delivery Date | T8: 1 | U8: 0 | V8: 1 | W8: =DATE(YEAR(B8),MONTH(B8),1) -> 46023 | X8: =IF(AND(N8<>"Cancelled",I8<=AsOf),1,0) -> 1 | Y8: =IF(AND(N8<>"Cancelled",OR(ISNUMBER(K8),N8="Completed")),1,0) -> 1 | Z8: =IF(AND(Y8=1,U8=1,ISNUMBER(K8)),K8-I8,"") | AA8: =IF(Z8="","",IF(Z8<0,"Early",IF(Z8=0,"On Time","Late"))) | AB8: =IF(AND(N8<>"Cancelled",L8<=AsOf),1,0) -> 1 | AC8: =IF(AND(N8<>"Cancelled",OR(ISNUMBER(M8),N8="Completed")),1,0) -> 1 | AD8: =IF(AND(AC8=1,V8=1,ISNUMBER(M8)),M8-L8,"") -> -1 | AE8: =IF(AD8="","",IF(AD8<0,"Early",IF(AD8=0,"On Time","Late"))) -> Early | AF8: =IF(AND(T8=1,ISNUMBER(J8),N8<>"Cancelled"),J8-B8,"") -> 28 | AG8: =IF(AND(AF8<>"",Z8<>""),K8-J8,"") | AH8: =IF(AND(Z8<>"",AD8<>""),M8-K8,"") | AI8: =IF(Z8<>"",K8-B8,"") | AJ8: =IF(AND(N8="Completed",AD8<>""),M8-B8,"") -> 34 | AK8: =IF(N8="Cancelled","Cancelled",IF(N8="Completed","Completed",IF(Y8=1,"Awaiting Installation",IF(ISNUMBER(J8),"In Transit","In Production")))) -> Completed | AL8: =IF(AND(N8="Pending",OR(AND(Y8=0,I8<AsOf),AND(Y8=1,L8<AsOf))),1,0) -> 0 | AM8: =IF(AL8=1,IF(Y8=0,AsOf-I8,AsOf-L8),"") | AN8: =IF(AL8=1,IF(Y8=0,"Delivery","Installation"),"") | AO8: =IF(AND(OR(fCat="All",F8=fCat),OR(fCust="All",D8=fCust),OR(fReg="All",E8=fReg)),1,0) -> 1 | AP8: =IF(AND(AL8=1,AO8=1),AM8+ROW()/100000,0) -> 0
A9: NHP-0008 | B9: 46045 | C9: CUST-5339 | D9: Institutional | E9: Bengaluru | F9: Commercial Heat Pump | G9: 2 | H9: 1038000 | I9: 46063 | J9: 46053 | K9: 46055 | L9: 46068 | M9: 46069 | N9: Completed | R9: Customer requested weekend install | S9: OK | T9: 1 | U9: 1 | V9: 1 | W9: =DATE(YEAR(B9),MONTH(B9),1) -> 46023 | X9: =IF(AND(N9<>"Cancelled",I9<=AsOf),1,0) -> 1 | Y9: =IF(AND(N9<>"Cancelled",OR(ISNUMBER(K9),N9="Completed")),1,0) -> 1 | Z9: =IF(AND(Y9=1,U9=1,ISNUMBER(K9)),K9-I9,"") -> -8 | AA9: =IF(Z9="","",IF(Z9<0,"Early",IF(Z9=0,"On Time","Late"))) -> Early | AB9: =IF(AND(N9<>"Cancelled",L9<=AsOf),1,0) -> 1 | AC9: =IF(AND(N9<>"Cancelled",OR(ISNUMBER(M9),N9="Completed")),1,0) -> 1 | AD9: =IF(AND(AC9=1,V9=1,ISNUMBER(M9)),M9-L9,"") -> 1 | AE9: =IF(AD9="","",IF(AD9<0,"Early",IF(AD9=0,"On Time","Late"))) -> Late | AF9: =IF(AND(T9=1,ISNUMBER(J9),N9<>"Cancelled"),J9-B9,"") -> 8 | AG9: =IF(AND(AF9<>"",Z9<>""),K9-J9,"") -> 2 | AH9: =IF(AND(Z9<>"",AD9<>""),M9-K9,"") -> 14 | AI9: =IF(Z9<>"",K9-B9,"") -> 10 | AJ9: =IF(AND(N9="Completed",AD9<>""),M9-B9,"") -> 24 | AK9: =IF(N9="Cancelled","Cancelled",IF(N9="Completed","Completed",IF(Y9=1,"Awaiting Installation",IF(ISNUMBER(J9),"In Transit","In Production")))) -> Completed | AL9: =IF(AND(N9="Pending",OR(AND(Y9=0,I9<AsOf),AND(Y9=1,L9<AsOf))),1,0) -> 0 | AM9: =IF(AL9=1,IF(Y9=0,AsOf-I9,AsOf-L9),"") | AN9: =IF(AL9=1,IF(Y9=0,"Delivery","Installation"),"") | AO9: =IF(AND(OR(fCat="All",F9=fCat),OR(fCust="All",D9=fCust),OR(fReg="All",E9=fReg)),1,0) -> 1 | AP9: =IF(AND(AL9=1,AO9=1),AM9+ROW()/100000,0) -> 0
A10: NHP-0009 | B10: 46046 | C10: CUST-1520 | D10: Institutional | E10: Bengaluru | F10: Commercial Heat Pump | G10: 2 | H10: 1594000 | I10: 46064 | J10: 46068 | K10: 46069 | L10: 46069 | M10: 46072 | N10: Completed | O10: Component shortage | P10: Knock-on from late delivery | S10: OK | T10: 1 | U10: 1 | V10: 1 | W10: =DATE(YEAR(B10),MONTH(B10),1) -> 46023 | X10: =IF(AND(N10<>"Cancelled",I10<=AsOf),1,0) -> 1 | Y10: =IF(AND(N10<>"Cancelled",OR(ISNUMBER(K10),N10="Completed")),1,0) -> 1 | Z10: =IF(AND(Y10=1,U10=1,ISNUMBER(K10)),K10-I10,"") -> 5 | AA10: =IF(Z10="","",IF(Z10<0,"Early",IF(Z10=0,"On Time","Late"))) -> Late | AB10: =IF(AND(N10<>"Cancelled",L10<=AsOf),1,0) -> 1 | AC10: =IF(AND(N10<>"Cancelled",OR(ISNUMBER(M10),N10="Completed")),1,0) -> 1 | AD10: =IF(AND(AC10=1,V10=1,ISNUMBER(M10)),M10-L10,"") -> 3 | AE10: =IF(AD10="","",IF(AD10<0,"Early",IF(AD10=0,"On Time","Late"))) -> Late | AF10: =IF(AND(T10=1,ISNUMBER(J10),N10<>"Cancelled"),J10-B10,"") -> 22 | AG10: =IF(AND(AF10<>"",Z10<>""),K10-J10,"") -> 1 | AH10: =IF(AND(Z10<>"",AD10<>""),M10-K10,"") -> 3 | AI10: =IF(Z10<>"",K10-B10,"") -> 23 | AJ10: =IF(AND(N10="Completed",AD10<>""),M10-B10,"") -> 26 | AK10: =IF(N10="Cancelled","Cancelled",IF(N10="Completed","Completed",IF(Y10=1,"Awaiting Installation",IF(ISNUMBER(J10),"In Transit","In Production")))) -> Completed | AL10: =IF(AND(N10="Pending",OR(AND(Y10=0,I10<AsOf),AND(Y10=1,L10<AsOf))),1,0) -> 0 | AM10: =IF(AL10=1,IF(Y10=0,AsOf-I10,AsOf-L10),"") | AN10: =IF(AL10=1,IF(Y10=0,"Delivery","Installation"),"") | AO10: =IF(AND(OR(fCat="All",F10=fCat),OR(fCust="All",D10=fCust),OR(fReg="All",E10=fReg)),1,0) -> 1 | AP10: =IF(AND(AL10=1,AO10=1),AM10+ROW()/100000,0) -> 0
A11: NHP-0010 | B11: 46048 | C11: CUST-2679 | D11: Residential | E11: Bengaluru | F11: Swimming Pool Heat Pump | G11: 1 | H11: 249000 | I11: 46062 | J11: 46057 | K11: 46058 | L11: 46065 | M11: 46059 | N11: Completed | R11: Customer requested weekend install | S11: OK | T11: 1 | U11: 1 | V11: 1 | W11: =DATE(YEAR(B11),MONTH(B11),1) -> 46023 | X11: =IF(AND(N11<>"Cancelled",I11<=AsOf),1,0) -> 1 | Y11: =IF(AND(N11<>"Cancelled",OR(ISNUMBER(K11),N11="Completed")),1,0) -> 1 | Z11: =IF(AND(Y11=1,U11=1,ISNUMBER(K11)),K11-I11,"") -> -4 | AA11: =IF(Z11="","",IF(Z11<0,"Early",IF(Z11=0,"On Time","Late"))) -> Early | AB11: =IF(AND(N11<>"Cancelled",L11<=AsOf),1,0) -> 1 | AC11: =IF(AND(N11<>"Cancelled",OR(ISNUMBER(M11),N11="Completed")),1,0) -> 1 | AD11: =IF(AND(AC11=1,V11=1,ISNUMBER(M11)),M11-L11,"") -> -6 | AE11: =IF(AD11="","",IF(AD11<0,"Early",IF(AD11=0,"On Time","Late"))) -> Early | AF11: =IF(AND(T11=1,ISNUMBER(J11),N11<>"Cancelled"),J11-B11,"") -> 9 | AG11: =IF(AND(AF11<>"",Z11<>""),K11-J11,"") -> 1 | AH11: =IF(AND(Z11<>"",AD11<>""),M11-K11,"") -> 1 | AI11: =IF(Z11<>"",K11-B11,"") -> 10 | AJ11: =IF(AND(N11="Completed",AD11<>""),M11-B11,"") -> 11 | AK11: =IF(N11="Cancelled","Cancelled",IF(N11="Completed","Completed",IF(Y11=1,"Awaiting Installation",IF(ISNUMBER(J11),"In Transit","In Production")))) -> Completed | AL11: =IF(AND(N11="Pending",OR(AND(Y11=0,I11<AsOf),AND(Y11=1,L11<AsOf))),1,0) -> 0 | AM11: =IF(AL11=1,IF(Y11=0,AsOf-I11,AsOf-L11),"") | AN11: =IF(AL11=1,IF(Y11=0,"Delivery","Installation"),"") | AO11: =IF(AND(OR(fCat="All",F11=fCat),OR(fCust="All",D11=fCust),OR(fReg="All",E11=fReg)),1,0) -> 1 | AP11: =IF(AND(AL11=1,AO11=1),AM11+ROW()/100000,0) -> 0
A12: NHP-0011 | B12: 46051 | C12: CUST-6881 | D12: Commercial | E12: Rest of Karnataka | F12: Heat Pump Dryer | G12: 2 | H12: 846000 | I12: 46074 | J12: 46075 | K12: 46079 | L12: 46079 | M12: 46082 | N12: Completed | O12: Production backlog | P12: Knock-on from late delivery | S12: OK | T12: 1 | U12: 1 | V12: 1 | W12: =DATE(YEAR(B12),MONTH(B12),1) -> 46023 | X12: =IF(AND(N12<>"Cancelled",I12<=AsOf),1,0) -> 1 | Y12: =IF(AND(N12<>"Cancelled",OR(ISNUMBER(K12),N12="Completed")),1,0) -> 1 | Z12: =IF(AND(Y12=1,U12=1,ISNUMBER(K12)),K12-I12,"") -> 5 | AA12: =IF(Z12="","",IF(Z12<0,"Early",IF(Z12=0,"On Time","Late"))) -> Late | AB12: =IF(AND(N12<>"Cancelled",L12<=AsOf),1,0) -> 1 | AC12: =IF(AND(N12<>"Cancelled",OR(ISNUMBER(M12),N12="Completed")),1,0) -> 1 | AD12: =IF(AND(AC12=1,V12=1,ISNUMBER(M12)),M12-L12,"") -> 3 | AE12: =IF(AD12="","",IF(AD12<0,"Early",IF(AD12=0,"On Time","Late"))) -> Late | AF12: =IF(AND(T12=1,ISNUMBER(J12),N12<>"Cancelled"),J12-B12,"") -> 24 | AG12: =IF(AND(AF12<>"",Z12<>""),K12-J12,"") -> 4 | AH12: =IF(AND(Z12<>"",AD12<>""),M12-K12,"") -> 3 | AI12: =IF(Z12<>"",K12-B12,"") -> 28 | AJ12: =IF(AND(N12="Completed",AD12<>""),M12-B12,"") -> 31 | AK12: =IF(N12="Cancelled","Cancelled",IF(N12="Completed","Completed",IF(Y12=1,"Awaiting Installation",IF(ISNUMBER(J12),"In Transit","In Production")))) -> Completed | AL12: =IF(AND(N12="Pending",OR(AND(Y12=0,I12<AsOf),AND(Y12=1,L12<AsOf))),1,0) -> 0 | AM12: =IF(AL12=1,IF(Y12=0,AsOf-I12,AsOf-L12),"") | AN12: =IF(AL12=1,IF(Y12=0,"Delivery","Installation"),"") | AO12: =IF(AND(OR(fCat="All",F12=fCat),OR(fCust="All",D12=fCust),OR(fReg="All",E12=fReg)),1,0) -> 1 | AP12: =IF(AND(AL12=1,AO12=1),AM12+ROW()/100000,0) -> 0
A13: NHP-0012 | B13: 46051 | C13: CUST-5374 | D13: Residential | E13: Other States | F13: Heat Pump Water Heater | G13: 1 | H13: 174000 | I13: 46065 | J13: 46054 | K13: 46061 | L13: 46068 | M13: 46062 | N13: Completed | S13: OK | T13: 1 | U13: 1 | V13: 1 | W13: =DATE(YEAR(B13),MONTH(B13),1) -> 46023 | X13: =IF(AND(N13<>"Cancelled",I13<=AsOf),1,0) -> 1 | Y13: =IF(AND(N13<>"Cancelled",OR(ISNUMBER(K13),N13="Completed")),1,0) -> 1 | Z13: =IF(AND(Y13=1,U13=1,ISNUMBER(K13)),K13-I13,"") -> -4 | AA13: =IF(Z13="","",IF(Z13<0,"Early",IF(Z13=0,"On Time","Late"))) -> Early | AB13: =IF(AND(N13<>"Cancelled",L13<=AsOf),1,0) -> 1 | AC13: =IF(AND(N13<>"Cancelled",OR(ISNUMBER(M13),N13="Completed")),1,0) -> 1 | AD13: =IF(AND(AC13=1,V13=1,ISNUMBER(M13)),M13-L13,"") -> -6 | AE13: =IF(AD13="","",IF(AD13<0,"Early",IF(AD13=0,"On Time","Late"))) -> Early | AF13: =IF(AND(T13=1,ISNUMBER(J13),N13<>"Cancelled"),J13-B13,"") -> 3 | AG13: =IF(AND(AF13<>"",Z13<>""),K13-J13,"") -> 7 | AH13: =IF(AND(Z13<>"",AD13<>""),M13-K13,"") -> 1 | AI13: =IF(Z13<>"",K13-B13,"") -> 10 | AJ13: =IF(AND(N13="Completed",AD13<>""),M13-B13,"") -> 11 | AK13: =IF(N13="Cancelled","Cancelled",IF(N13="Completed","Completed",IF(Y13=1,"Awaiting Installation",IF(ISNUMBER(J13),"In Transit","In Production")))) -> Completed | AL13: =IF(AND(N13="Pending",OR(AND(Y13=0,I13<AsOf),AND(Y13=1,L13<AsOf))),1,0) -> 0 | AM13: =IF(AL13=1,IF(Y13=0,AsOf-I13,AsOf-L13),"") | AN13: =IF(AL13=1,IF(Y13=0,"Delivery","Installation"),"") | AO13: =IF(AND(OR(fCat="All",F13=fCat),OR(fCust="All",D13=fCust),OR(fReg="All",E13=fReg)),1,0) -> 1 | AP13: =IF(AND(AL13=1,AO13=1),AM13+ROW()/100000,0) -> 0
A14: NHP-0013 | B14: 46052 | C14: CUST-9669 | D14: Residential | E14: Rest of Karnataka | F14: Heat Pump Water Heater | G14: 1 | H14: 131000 | I14: 46064 | J14: 46060 | K14: 46064 | L14: 46067 | M14: 46065 | N14: Completed | R14: Replacement of old geyser | S14: OK | T14: 1 | U14: 1 | V14: 1 | W14: =DATE(YEAR(B14),MONTH(B14),1) -> 46023 | X14: =IF(AND(N14<>"Cancelled",I14<=AsOf),1,0) -> 1 | Y14: =IF(AND(N14<>"Cancelled",OR(ISNUMBER(K14),N14="Completed")),1,0) -> 1 | Z14: =IF(AND(Y14=1,U14=1,ISNUMBER(K14)),K14-I14,"") -> 0 | AA14: =IF(Z14="","",IF(Z14<0,"Early",IF(Z14=0,"On Time","Late"))) -> On Time | AB14: =IF(AND(N14<>"Cancelled",L14<=AsOf),1,0) -> 1 | AC14: =IF(AND(N14<>"Cancelled",OR(ISNUMBER(M14),N14="Completed")),1,0) -> 1 | AD14: =IF(AND(AC14=1,V14=1,ISNUMBER(M14)),M14-L14,"") -> -2 | AE14: =IF(AD14="","",IF(AD14<0,"Early",IF(AD14=0,"On Time","Late"))) -> Early | AF14: =IF(AND(T14=1,ISNUMBER(J14),N14<>"Cancelled"),J14-B14,"") -> 8 | AG14: =IF(AND(AF14<>"",Z14<>""),K14-J14,"") -> 4 | AH14: =IF(AND(Z14<>"",AD14<>""),M14-K14,"") -> 1 | AI14: =IF(Z14<>"",K14-B14,"") -> 12 | AJ14: =IF(AND(N14="Completed",AD14<>""),M14-B14,"") -> 13 | AK14: =IF(N14="Cancelled","Cancelled",IF(N14="Completed","Completed",IF(Y14=1,"Awaiting Installation",IF(ISNUMBER(J14),"In Transit","In Production")))) -> Completed | AL14: =IF(AND(N14="Pending",OR(AND(Y14=0,I14<AsOf),AND(Y14=1,L14<AsOf))),1,0) -> 0 | AM14: =IF(AL14=1,IF(Y14=0,AsOf-I14,AsOf-L14),"") | AN14: =IF(AL14=1,IF(Y14=0,"Delivery","Installation"),"") | AO14: =IF(AND(OR(fCat="All",F14=fCat),OR(fCust="All",D14=fCust),OR(fReg="All",E14=fReg)),1,0) -> 1 | AP14: =IF(AND(AL14=1,AO14=1),AM14+ROW()/100000,0) -> 0
A15: NHP-0014 | B15: 46054 | C15: CUST-2519 | D15: Institutional | E15: Bengaluru | F15: Commercial Heat Pump | G15: 1 | H15: 448000 | I15: 46072 | J15: 46066 | K15: 46068 | L15: 46077 | M15: 46071 | N15: Completed | R15: Customer requested weekend install | S15: OK | T15: 1 | U15: 1 | V15: 1 | W15: =DATE(YEAR(B15),MONTH(B15),1) -> 46054 | X15: =IF(AND(N15<>"Cancelled",I15<=AsOf),1,0) -> 1 | Y15: =IF(AND(N15<>"Cancelled",OR(ISNUMBER(K15),N15="Completed")),1,0) -> 1 | Z15: =IF(AND(Y15=1,U15=1,ISNUMBER(K15)),K15-I15,"") -> -4 | AA15: =IF(Z15="","",IF(Z15<0,"Early",IF(Z15=0,"On Time","Late"))) -> Early | AB15: =IF(AND(N15<>"Cancelled",L15<=AsOf),1,0) -> 1 | AC15: =IF(AND(N15<>"Cancelled",OR(ISNUMBER(M15),N15="Completed")),1,0) -> 1 | AD15: =IF(AND(AC15=1,V15=1,ISNUMBER(M15)),M15-L15,"") -> -6 | AE15: =IF(AD15="","",IF(AD15<0,"Early",IF(AD15=0,"On Time","Late"))) -> Early | AF15: =IF(AND(T15=1,ISNUMBER(J15),N15<>"Cancelled"),J15-B15,"") -> 12 | AG15: =IF(AND(AF15<>"",Z15<>""),K15-J15,"") -> 2 | AH15: =IF(AND(Z15<>"",AD15<>""),M15-K15,"") -> 3 | AI15: =IF(Z15<>"",K15-B15,"") -> 14 | AJ15: =IF(AND(N15="Completed",AD15<>""),M15-B15,"") -> 17 | AK15: =IF(N15="Cancelled","Cancelled",IF(N15="Completed","Completed",IF(Y15=1,"Awaiting Installation",IF(ISNUMBER(J15),"In Transit","In Production")))) -> Completed | AL15: =IF(AND(N15="Pending",OR(AND(Y15=0,I15<AsOf),AND(Y15=1,L15<AsOf))),1,0) -> 0 | AM15: =IF(AL15=1,IF(Y15=0,AsOf-I15,AsOf-L15),"") | AN15: =IF(AL15=1,IF(Y15=0,"Delivery","Installation"),"") | AO15: =IF(AND(OR(fCat="All",F15=fCat),OR(fCust="All",D15=fCust),OR(fReg="All",E15=fReg)),1,0) -> 1 | AP15: =IF(AND(AL15=1,AO15=1),AM15+ROW()/100000,0) -> 0
A16: NHP-0015 | B16: 46055 | C16: CUST-5315 | D16: Commercial | E16: Rest of Karnataka | F16: Commercial Heat Pump | G16: 1 | H16: 798000 | I16: 46075 | J16: 46077 | K16: 46079 | L16: 46080 | M16: 46084 | N16: Completed | O16: Production backlog | P16: Knock-on from late delivery | R16: Electrical load checked | S16: OK | T16: 1 | U16: 1 | V16: 1 | W16: =DATE(YEAR(B16),MONTH(B16),1) -> 46054 | X16: =IF(AND(N16<>"Cancelled",I16<=AsOf),1,0) -> 1 | Y16: =IF(AND(N16<>"Cancelled",OR(ISNUMBER(K16),N16="Completed")),1,0) -> 1 | Z16: =IF(AND(Y16=1,U16=1,ISNUMBER(K16)),K16-I16,"") -> 4 | AA16: =IF(Z16="","",IF(Z16<0,"Early",IF(Z16=0,"On Time","Late"))) -> Late | AB16: =IF(AND(N16<>"Cancelled",L16<=AsOf),1,0) -> 1 | AC16: =IF(AND(N16<>"Cancelled",OR(ISNUMBER(M16),N16="Completed")),1,0) -> 1 | AD16: =IF(AND(AC16=1,V16=1,ISNUMBER(M16)),M16-L16,"") -> 4 | AE16: =IF(AD16="","",IF(AD16<0,"Early",IF(AD16=0,"On Time","Late"))) -> Late | AF16: =IF(AND(T16=1,ISNUMBER(J16),N16<>"Cancelled"),J16-B16,"") -> 22 | AG16: =IF(AND(AF16<>"",Z16<>""),K16-J16,"") -> 2 | AH16: =IF(AND(Z16<>"",AD16<>""),M16-K16,"") -> 5 | AI16: =IF(Z16<>"",K16-B16,"") -> 24 | AJ16: =IF(AND(N16="Completed",AD16<>""),M16-B16,"") -> 29 | AK16: =IF(N16="Cancelled","Cancelled",IF(N16="Completed","Completed",IF(Y16=1,"Awaiting Installation",IF(ISNUMBER(J16),"In Transit","In Production")))) -> Completed | AL16: =IF(AND(N16="Pending",OR(AND(Y16=0,I16<AsOf),AND(Y16=1,L16<AsOf))),1,0) -> 0 | AM16: =IF(AL16=1,IF(Y16=0,AsOf-I16,AsOf-L16),"") | AN16: =IF(AL16=1,IF(Y16=0,"Delivery","Installation"),"") | AO16: =IF(AND(OR(fCat="All",F16=fCat),OR(fCust="All",D16=fCust),OR(fReg="All",E16=fReg)),1,0) -> 1 | AP16: =IF(AND(AL16=1,AO16=1),AM16+ROW()/100000,0) -> 0
A17: NHP-0016 | B17: 46056 | C17: CUST-6573 | D17: Commercial | E17: Other States | F17: Heat Pump Dryer | G17: 1 | H17: 574000 | I17: 46081 | J17: 46079 | K17: 46089 | L17: 46086 | M17: 46100 | N17: Completed | O17: Component shortage | P17: Customer site not ready | S17: OK | T17: 1 | U17: 1 | V17: 1 | W17: =DATE(YEAR(B17),MONTH(B17),1) -> 46054 | X17: =IF(AND(N17<>"Cancelled",I17<=AsOf),1,0) -> 1 | Y17: =IF(AND(N17<>"Cancelled",OR(ISNUMBER(K17),N17="Completed")),1,0) -> 1 | Z17: =IF(AND(Y17=1,U17=1,ISNUMBER(K17)),K17-I17,"") -> 8 | AA17: =IF(Z17="","",IF(Z17<0,"Early",IF(Z17=0,"On Time","Late"))) -> Late | AB17: =IF(AND(N17<>"Cancelled",L17<=AsOf),1,0) -> 1 | AC17: =IF(AND(N17<>"Cancelled",OR(ISNUMBER(M17),N17="Completed")),1,0) -> 1 | AD17: =IF(AND(AC17=1,V17=1,ISNUMBER(M17)),M17-L17,"") -> 14 | AE17: =IF(AD17="","",IF(AD17<0,"Early",IF(AD17=0,"On Time","Late"))) -> Late | AF17: =IF(AND(T17=1,ISNUMBER(J17),N17<>"Cancelled"),J17-B17,"") -> 23 | AG17: =IF(AND(AF17<>"",Z17<>""),K17-J17,"") -> 10 | AH17: =IF(AND(Z17<>"",AD17<>""),M17-K17,"") -> 11 | AI17: =IF(Z17<>"",K17-B17,"") -> 33 | AJ17: =IF(AND(N17="Completed",AD17<>""),M17-B17,"") -> 44 | AK17: =IF(N17="Cancelled","Cancelled",IF(N17="Completed","Completed",IF(Y17=1,"Awaiting Installation",IF(ISNUMBER(J17),"In Transit","In Production")))) -> Completed | AL17: =IF(AND(N17="Pending",OR(AND(Y17=0,I17<AsOf),AND(Y17=1,L17<AsOf))),1,0) -> 0 | AM17: =IF(AL17=1,IF(Y17=0,AsOf-I17,AsOf-L17),"") | AN17: =IF(AL17=1,IF(Y17=0,"Delivery","Installation"),"") | AO17: =IF(AND(OR(fCat="All",F17=fCat),OR(fCust="All",D17=fCust),OR(fReg="All",E17=fReg)),1,0) -> 1 | AP17: =IF(AND(AL17=1,AO17=1),AM17+ROW()/100000,0) -> 0
A18: NHP-0017 | B18: 46056 | C18: CUST-1488 | D18: Commercial | E18: Bengaluru | F18: Custom Requirement | G18: 2 | H18: 2040000 | I18: 46086 | J18: 46064 | K18: 46066 | L18: 46091 | N18: Cancelled | Q18: Customer postponed project | R18: Unit returned to factory after delivery | S18: Cancelled after delivery (returned) | T18: 1 | U18: 0 | V18: 1 | W18: =DATE(YEAR(B18),MONTH(B18),1) -> 46054 | X18: =IF(AND(N18<>"Cancelled",I18<=AsOf),1,0) -> 0 | Y18: =IF(AND(N18<>"Cancelled",OR(ISNUMBER(K18),N18="Completed")),1,0) -> 0 | Z18: =IF(AND(Y18=1,U18=1,ISNUMBER(K18)),K18-I18,"") | AA18: =IF(Z18="","",IF(Z18<0,"Early",IF(Z18=0,"On Time","Late"))) | AB18: =IF(AND(N18<>"Cancelled",L18<=AsOf),1,0) -> 0 | AC18: =IF(AND(N18<>"Cancelled",OR(ISNUMBER(M18),N18="Completed")),1,0) -> 0 | AD18: =IF(AND(AC18=1,V18=1,ISNUMBER(M18)),M18-L18,"") | AE18: =IF(AD18="","",IF(AD18<0,"Early",IF(AD18=0,"On Time","Late"))) | AF18: =IF(AND(T18=1,ISNUMBER(J18),N18<>"Cancelled"),J18-B18,"") | AG18: =IF(AND(AF18<>"",Z18<>""),K18-J18,"") | AH18: =IF(AND(Z18<>"",AD18<>""),M18-K18,"") | AI18: =IF(Z18<>"",K18-B18,"") | AJ18: =IF(AND(N18="Completed",AD18<>""),M18-B18,"") | AK18: =IF(N18="Cancelled","Cancelled",IF(N18="Completed","Completed",IF(Y18=1,"Awaiting Installation",IF(ISNUMBER(J18),"In Transit","In Production")))) -> Cancelled | AL18: =IF(AND(N18="Pending",OR(AND(Y18=0,I18<AsOf),AND(Y18=1,L18<AsOf))),1,0) -> 0 | AM18: =IF(AL18=1,IF(Y18=0,AsOf-I18,AsOf-L18),"") | AN18: =IF(AL18=1,IF(Y18=0,"Delivery","Installation"),"") | AO18: =IF(AND(OR(fCat="All",F18=fCat),OR(fCust="All",D18=fCust),OR(fReg="All",E18=fReg)),1,0) -> 1 | AP18: =IF(AND(AL18=1,AO18=1),AM18+ROW()/100000,0) -> 0
A19: NHP-0018 | B19: 46056 | C19: CUST-3621 | D19: Commercial | E19: Rest of Karnataka | F19: Custom Requirement | G19: 1 | H19: 1311000 | I19: 46088 | J19: 46085 | K19: 46089 | L19: 46093 | M19: 46094 | N19: Completed | O19: Production backlog | P19: Knock-on from late delivery | S19: OK | T19: 1 | U19: 1 | V19: 1 | W19: =DATE(YEAR(B19),MONTH(B19),1) -> 46054 | X19: =IF(AND(N19<>"Cancelled",I19<=AsOf),1,0) -> 1 | Y19: =IF(AND(N19<>"Cancelled",OR(ISNUMBER(K19),N19="Completed")),1,0) -> 1 | Z19: =IF(AND(Y19=1,U19=1,ISNUMBER(K19)),K19-I19,"") -> 1 | AA19: =IF(Z19="","",IF(Z19<0,"Early",IF(Z19=0,"On Time","Late"))) -> Late | AB19: =IF(AND(N19<>"Cancelled",L19<=AsOf),1,0) -> 1 | AC19: =IF(AND(N19<>"Cancelled",OR(ISNUMBER(M19),N19="Completed")),1,0) -> 1 | AD19: =IF(AND(AC19=1,V19=1,ISNUMBER(M19)),M19-L19,"") -> 1 | AE19: =IF(AD19="","",IF(AD19<0,"Early",IF(AD19=0,"On Time","Late"))) -> Late | AF19: =IF(AND(T19=1,ISNUMBER(J19),N19<>"Cancelled"),J19-B19,"") -> 29 | AG19: =IF(AND(AF19<>"",Z19<>""),K19-J19,"") -> 4 | AH19: =IF(AND(Z19<>"",AD19<>""),M19-K19,"") -> 5 | AI19: =IF(Z19<>"",K19-B19,"") -> 33 | AJ19: =IF(AND(N19="Completed",AD19<>""),M19-B19,"") -> 38 | AK19: =IF(N19="Cancelled","Cancelled",IF(N19="Completed","Completed",IF(Y19=1,"Awaiting Installation",IF(ISNUMBER(J19),"In Transit","In Production")))) -> Completed | AL19: =IF(AND(N19="Pending",OR(AND(Y19=0,I19<AsOf),AND(Y19=1,L19<AsOf))),1,0) -> 0 | AM19: =IF(AL19=1,IF(Y19=0,AsOf-I19,AsOf-L19),"") | AN19: =IF(AL19=1,IF(Y19=0,"Delivery","Installation"),"") | AO19: =IF(AND(OR(fCat="All",F19=fCat),OR(fCust="All",D19=fCust),OR(fReg="All",E19=fReg)),1,0) -> 1 | AP19: =IF(AND(AL19=1,AO19=1),AM19+ROW()/100000,0) -> 0
A20: NHP-0019 | B20: 46060 | C20: CUST-7065 | D20: Commercial | E20: Bengaluru | F20: Heat Pump Dryer | G20: 2 | H20: 1122000 | I20: 46081 | J20: 46078 | K20: 46079 | L20: 46086 | M20: 46093 | N20: Completed | S20: OK | T20: 1 | U20: 1 | V20: 1 | W20: =DATE(YEAR(B20),MONTH(B20),1) -> 46054 | X20: =IF(AND(N20<>"Cancelled",I20<=AsOf),1,0) -> 1 | Y20: =IF(AND(N20<>"Cancelled",OR(ISNUMBER(K20),N20="Completed")),1,0) -> 1 | Z20: =IF(AND(Y20=1,U20=1,ISNUMBER(K20)),K20-I20,"") -> -2 | AA20: =IF(Z20="","",IF(Z20<0,"Early",IF(Z20=0,"On Time","Late"))) -> Early | AB20: =IF(AND(N20<>"Cancelled",L20<=AsOf),1,0) -> 1 | AC20: =IF(AND(N20<>"Cancelled",OR(ISNUMBER(M20),N20="Completed")),1,0) -> 1 | AD20: =IF(AND(AC20=1,V20=1,ISNUMBER(M20)),M20-L20,"") -> 7 | AE20: =IF(AD20="","",IF(AD20<0,"Early",IF(AD20=0,"On Time","Late"))) -> Late | AF20: =IF(AND(T20=1,ISNUMBER(J20),N20<>"Cancelled"),J20-B20,"") -> 18 | AG20: =IF(AND(AF20<>"",Z20<>""),K20-J20,"") -> 1 | AH20: =IF(AND(Z20<>"",AD20<>""),M20-K20,"") -> 14 | AI20: =IF(Z20<>"",K20-B20,"") -> 19 | AJ20: =IF(AND(N20="Completed",AD20<>""),M20-B20,"") -> 33 | AK20: =IF(N20="Cancelled","Cancelled",IF(N20="Completed","Completed",IF(Y20=1,"Awaiting Installation",IF(ISNUMBER(J20),"In Transit","In Production")))) -> Completed | AL20: =IF(AND(N20="Pending",OR(AND(Y20=0,I20<AsOf),AND(Y20=1,L20<AsOf))),1,0) -> 0 | AM20: =IF(AL20=1,IF(Y20=0,AsOf-I20,AsOf-L20),"") | AN20: =IF(AL20=1,IF(Y20=0,"Delivery","Installation"),"") | AO20: =IF(AND(OR(fCat="All",F20=fCat),OR(fCust="All",D20=fCust),OR(fReg="All",E20=fReg)),1,0) -> 1 | AP20: =IF(AND(AL20=1,AO20=1),AM20+ROW()/100000,0) -> 0
A21: NHP-0020 | B21: 46060 | C21: CUST-3340 | D21: Residential | E21: Other States | F21: Heat Pump Water Heater | G21: 1 | H21: 160000 | I21: 46074 | J21: 46065 | K21: 46074 | L21: 46077 | M21: 46079 | N21: Completed | P21: Technician availability | R21: Electrical load checked | S21: OK | T21: 1 | U21: 1 | V21: 1 | W21: =DATE(YEAR(B21),MONTH(B21),1) -> 46054 | X21: =IF(AND(N21<>"Cancelled",I21<=AsOf),1,0) -> 1 | Y21: =IF(AND(N21<>"Cancelled",OR(ISNUMBER(K21),N21="Completed")),1,0) -> 1 | Z21: =IF(AND(Y21=1,U21=1,ISNUMBER(K21)),K21-I21,"") -> 0 | AA21: =IF(Z21="","",IF(Z21<0,"Early",IF(Z21=0,"On Time","Late"))) -> On Time | AB21: =IF(AND(N21<>"Cancelled",L21<=AsOf),1,0) -> 1 | AC21: =IF(AND(N21<>"Cancelled",OR(ISNUMBER(M21),N21="Completed")),1,0) -> 1 | AD21: =IF(AND(AC21=1,V21=1,ISNUMBER(M21)),M21-L21,"") -> 2 | AE21: =IF(AD21="","",IF(AD21<0,"Early",IF(AD21=0,"On Time","Late"))) -> Late | AF21: =IF(AND(T21=1,ISNUMBER(J21),N21<>"Cancelled"),J21-B21,"") -> 5 | AG21: =IF(AND(AF21<>"",Z21<>""),K21-J21,"") -> 9 | AH21: =IF(AND(Z21<>"",AD21<>""),M21-K21,"") -> 5 | AI21: =IF(Z21<>"",K21-B21,"") -> 14 | AJ21: =IF(AND(N21="Completed",AD21<>""),M21-B21,"") -> 19 | AK21: =IF(N21="Cancelled","Cancelled",IF(N21="Completed","Completed",IF(Y21=1,"Awaiting Installation",IF(ISNUMBER(J21),"In Transit","In Production")))) -> Completed | AL21: =IF(AND(N21="Pending",OR(AND(Y21=0,I21<AsOf),AND(Y21=1,L21<AsOf))),1,0) -> 0 | AM21: =IF(AL21=1,IF(Y21=0,AsOf-I21,AsOf-L21),"") | AN21: =IF(AL21=1,IF(Y21=0,"Delivery","Installation"),"") | AO21: =IF(AND(OR(fCat="All",F21=fCat),OR(fCust="All",D21=fCust),OR(fReg="All",E21=fReg)),1,0) -> 1 | AP21: =IF(AND(AL21=1,AO21=1),AM21+ROW()/100000,0) -> 0
A22: NHP-0021 | B22: 46061 | C22: CUST-4657 | D22: Residential | E22: Bengaluru | F22: Heat Pump Water Heater | G22: 1 | H22: 153000 | I22: 46071 | J22: 46065 | L22: 46074 | N22: Cancelled | Q22: Long lead time | S22: OK | T22: 1 | U22: 1 | V22: 1 | W22: =DATE(YEAR(B22),MONTH(B22),1) -> 46054 | X22: =IF(AND(N22<>"Cancelled",I22<=AsOf),1,0) -> 0 | Y22: =IF(AND(N22<>"Cancelled",OR(ISNUMBER(K22),N22="Completed")),1,0) -> 0 | Z22: =IF(AND(Y22=1,U22=1,ISNUMBER(K22)),K22-I22,"") | AA22: =IF(Z22="","",IF(Z22<0,"Early",IF(Z22=0,"On Time","Late"))) | AB22: =IF(AND(N22<>"Cancelled",L22<=AsOf),1,0) -> 0 | AC22: =IF(AND(N22<>"Cancelled",OR(ISNUMBER(M22),N22="Completed")),1,0) -> 0 | AD22: =IF(AND(AC22=1,V22=1,ISNUMBER(M22)),M22-L22,"") | AE22: =IF(AD22="","",IF(AD22<0,"Early",IF(AD22=0,"On Time","Late"))) | AF22: =IF(AND(T22=1,ISNUMBER(J22),N22<>"Cancelled"),J22-B22,"") | AG22: =IF(AND(AF22<>"",Z22<>""),K22-J22,"") | AH22: =IF(AND(Z22<>"",AD22<>""),M22-K22,"") | AI22: =IF(Z22<>"",K22-B22,"") | AJ22: =IF(AND(N22="Completed",AD22<>""),M22-B22,"") | AK22: =IF(N22="Cancelled","Cancelled",IF(N22="Completed","Completed",IF(Y22=1,"Awaiting Installation",IF(ISNUMBER(J22),"In Transit","In Production")))) -> Cancelled | AL22: =IF(AND(N22="Pending",OR(AND(Y22=0,I22<AsOf),AND(Y22=1,L22<AsOf))),1,0) -> 0 | AM22: =IF(AL22=1,IF(Y22=0,AsOf-I22,AsOf-L22),"") | AN22: =IF(AL22=1,IF(Y22=0,"Delivery","Installation"),"") | AO22: =IF(AND(OR(fCat="All",F22=fCat),OR(fCust="All",D22=fCust),OR(fReg="All",E22=fReg)),1,0) -> 1 | AP22: =IF(AND(AL22=1,AO22=1),AM22+ROW()/100000,0) -> 0
A23: NHP-0022 | B23: 46062 | C23: CUST-4811 | D23: Commercial | E23: Bengaluru | F23: Swimming Pool Heat Pump | G23: 2 | H23: 870000 | I23: 46076 | J23: 46070 | K23: 46071 | L23: 46079 | M23: 46073 | N23: Completed | R23: Site survey done | S23: OK | T23: 1 | U23: 1 | V23: 1 | W23: =DATE(YEAR(B23),MONTH(B23),1) -> 46054 | X23: =IF(AND(N23<>"Cancelled",I23<=AsOf),1,0) -> 1 | Y23: =IF(AND(N23<>"Cancelled",OR(ISNUMBER(K23),N23="Completed")),1,0) -> 1 | Z23: =IF(AND(Y23=1,U23=1,ISNUMBER(K23)),K23-I23,"") -> -5 | AA23: =IF(Z23="","",IF(Z23<0,"Early",IF(Z23=0,"On Time","Late"))) -> Early | AB23: =IF(AND(N23<>"Cancelled",L23<=AsOf),1,0) -> 1 | AC23: =IF(AND(N23<>"Cancelled",OR(ISNUMBER(M23),N23="Completed")),1,0) -> 1 | AD23: =IF(AND(AC23=1,V23=1,ISNUMBER(M23)),M23-L23,"") -> -6 | AE23: =IF(AD23="","",IF(AD23<0,"Early",IF(AD23=0,"On Time","Late"))) -> Early | AF23: =IF(AND(T23=1,ISNUMBER(J23),N23<>"Cancelled"),J23-B23,"") -> 8 | AG23: =IF(AND(AF23<>"",Z23<>""),K23-J23,"") -> 1 | AH23: =IF(AND(Z23<>"",AD23<>""),M23-K23,"") -> 2 | AI23: =IF(Z23<>"",K23-B23,"") -> 9 | AJ23: =IF(AND(N23="Completed",AD23<>""),M23-B23,"") -> 11 | AK23: =IF(N23="Cancelled","Cancelled",IF(N23="Completed","Completed",IF(Y23=1,"Awaiting Installation",IF(ISNUMBER(J23),"In Transit","In Production")))) -> Completed | AL23: =IF(AND(N23="Pending",OR(AND(Y23=0,I23<AsOf),AND(Y23=1,L23<AsOf))),1,0) -> 0 | AM23: =IF(AL23=1,IF(Y23=0,AsOf-I23,AsOf-L23),"") | AN23: =IF(AL23=1,IF(Y23=0,"Delivery","Installation"),"") | AO23: =IF(AND(OR(fCat="All",F23=fCat),OR(fCust="All",D23=fCust),OR(fReg="All",E23=fReg)),1,0) -> 1 | AP23: =IF(AND(AL23=1,AO23=1),AM23+ROW()/100000,0) -> 0
A24: NHP-0023 | B24: 46063 | C24: CUST-1916 | D24: Institutional | E24: Bengaluru | F24: Custom Requirement | G24: 2 | H24: 1898000 | I24: 46093 | L24: 46098 | N24: Cancelled | Q24: Price / budget | R24: Electrical load checked | S24: OK | T24: 1 | U24: 1 | V24: 1 | W24: =DATE(YEAR(B24),MONTH(B24),1) -> 46054 | X24: =IF(AND(N24<>"Cancelled",I24<=AsOf),1,0) -> 0 | Y24: =IF(AND(N24<>"Cancelled",OR(ISNUMBER(K24),N24="Completed")),1,0) -> 0 | Z24: =IF(AND(Y24=1,U24=1,ISNUMBER(K24)),K24-I24,"") | AA24: =IF(Z24="","",IF(Z24<0,"Early",IF(Z24=0,"On Time","Late"))) | AB24: =IF(AND(N24<>"Cancelled",L24<=AsOf),1,0) -> 0 | AC24: =IF(AND(N24<>"Cancelled",OR(ISNUMBER(M24),N24="Completed")),1,0) -> 0 | AD24: =IF(AND(AC24=1,V24=1,ISNUMBER(M24)),M24-L24,"") | AE24: =IF(AD24="","",IF(AD24<0,"Early",IF(AD24=0,"On Time","Late"))) | AF24: =IF(AND(T24=1,ISNUMBER(J24),N24<>"Cancelled"),J24-B24,"") | AG24: =IF(AND(AF24<>"",Z24<>""),K24-J24,"") | AH24: =IF(AND(Z24<>"",AD24<>""),M24-K24,"") | AI24: =IF(Z24<>"",K24-B24,"") | AJ24: =IF(AND(N24="Completed",AD24<>""),M24-B24,"") | AK24: =IF(N24="Cancelled","Cancelled",IF(N24="Completed","Completed",IF(Y24=1,"Awaiting Installation",IF(ISNUMBER(J24),"In Transit","In Production")))) -> Cancelled | AL24: =IF(AND(N24="Pending",OR(AND(Y24=0,I24<AsOf),AND(Y24=1,L24<AsOf))),1,0) -> 0 | AM24: =IF(AL24=1,IF(Y24=0,AsOf-I24,AsOf-L24),"") | AN24: =IF(AL24=1,IF(Y24=0,"Delivery","Installation"),"") | AO24: =IF(AND(OR(fCat="All",F24=fCat),OR(fCust="All",D24=fCust),OR(fReg="All",E24=fReg)),1,0) -> 1 | AP24: =IF(AND(AL24=1,AO24=1),AM24+ROW()/100000,0) -> 0
A25: NHP-0024 | B25: 46064 | C25: CUST-2824 | D25: Commercial | E25: Bengaluru | F25: Custom Requirement | G25: 2 | H25: 1434000 | I25: 46094 | J25: 46086 | K25: 46087 | L25: 46099 | M25: 46100 | N25: Completed | P25: Customer site not ready | R25: Pipe routing confirmed | S25: OK | T25: 1 | U25: 1 | V25: 1 | W25: =DATE(YEAR(B25),MONTH(B25),1) -> 46054 | X25: =IF(AND(N25<>"Cancelled",I25<=AsOf),1,0) -> 1 | Y25: =IF(AND(N25<>"Cancelled",OR(ISNUMBER(K25),N25="Completed")),1,0) -> 1 | Z25: =IF(AND(Y25=1,U25=1,ISNUMBER(K25)),K25-I25,"") -> -7 | AA25: =IF(Z25="","",IF(Z25<0,"Early",IF(Z25=0,"On Time","Late"))) -> Early | AB25: =IF(AND(N25<>"Cancelled",L25<=AsOf),1,0) -> 1 | AC25: =IF(AND(N25<>"Cancelled",OR(ISNUMBER(M25),N25="Completed")),1,0) -> 1 | AD25: =IF(AND(AC25=1,V25=1,ISNUMBER(M25)),M25-L25,"") -> 1 | AE25: =IF(AD25="","",IF(AD25<0,"Early",IF(AD25=0,"On Time","Late"))) -> Late | AF25: =IF(AND(T25=1,ISNUMBER(J25),N25<>"Cancelled"),J25-B25,"") -> 22 | AG25: =IF(AND(AF25<>"",Z25<>""),K25-J25,"") -> 1 | AH25: =IF(AND(Z25<>"",AD25<>""),M25-K25,"") -> 13 | AI25: =IF(Z25<>"",K25-B25,"") -> 23 | AJ25: =IF(AND(N25="Completed",AD25<>""),M25-B25,"") -> 36 | AK25: =IF(N25="Cancelled","Cancelled",IF(N25="Completed","Completed",IF(Y25=1,"Awaiting Installation",IF(ISNUMBER(J25),"In Transit","In Production")))) -> Completed | AL25: =IF(AND(N25="Pending",OR(AND(Y25=0,I25<AsOf),AND(Y25=1,L25<AsOf))),1,0) -> 0 | AM25: =IF(AL25=1,IF(Y25=0,AsOf-I25,AsOf-L25),"") | AN25: =IF(AL25=1,IF(Y25=0,"Delivery","Installation"),"") | AO25: =IF(AND(OR(fCat="All",F25=fCat),OR(fCust="All",D25=fCust),OR(fReg="All",E25=fReg)),1,0) -> 1 | AP25: =IF(AND(AL25=1,AO25=1),AM25+ROW()/100000,0) -> 0
A26: NHP-0025 | B26: 46067 | C26: CUST-4657 | D26: Residential | E26: Rest of Karnataka | F26: Heat Pump Water Heater | G26: 1 | H26: 157000 | I26: 46079 | J26: 46072 | K26: 46075 | L26: 46082 | M26: 46076 | N26: Completed | R26: Pipe routing confirmed | S26: OK | T26: 1 | U26: 1 | V26: 1 | W26: =DATE(YEAR(B26),MONTH(B26),1) -> 46054 | X26: =IF(AND(N26<>"Cancelled",I26<=AsOf),1,0) -> 1 | Y26: =IF(AND(N26<>"Cancelled",OR(ISNUMBER(K26),N26="Completed")),1,0) -> 1 | Z26: =IF(AND(Y26=1,U26=1,ISNUMBER(K26)),K26-I26,"") -> -4 | AA26: =IF(Z26="","",IF(Z26<0,"Early",IF(Z26=0,"On Time","Late"))) -> Early | AB26: =IF(AND(N26<>"Cancelled",L26<=AsOf),1,0) -> 1 | AC26: =IF(AND(N26<>"Cancelled",OR(ISNUMBER(M26),N26="Completed")),1,0) -> 1 | AD26: =IF(AND(AC26=1,V26=1,ISNUMBER(M26)),M26-L26,"") -> -6 | AE26: =IF(AD26="","",IF(AD26<0,"Early",IF(AD26=0,"On Time","Late"))) -> Early | AF26: =IF(AND(T26=1,ISNUMBER(J26),N26<>"Cancelled"),J26-B26,"") -> 5 | AG26: =IF(AND(AF26<>"",Z26<>""),K26-J26,"") -> 3 | AH26: =IF(AND(Z26<>"",AD26<>""),M26-K26,"") -> 1 | AI26: =IF(Z26<>"",K26-B26,"") -> 8 | AJ26: =IF(AND(N26="Completed",AD26<>""),M26-B26,"") -> 9 | AK26: =IF(N26="Cancelled","Cancelled",IF(N26="Completed","Completed",IF(Y26=1,"Awaiting Installation",IF(ISNUMBER(J26),"In Transit","In Production")))) -> Completed | AL26: =IF(AND(N26="Pending",OR(AND(Y26=0,I26<AsOf),AND(Y26=1,L26<AsOf))),1,0) -> 0 | AM26: =IF(AL26=1,IF(Y26=0,AsOf-I26,AsOf-L26),"") | AN26: =IF(AL26=1,IF(Y26=0,"Delivery","Installation"),"") | AO26: =IF(AND(OR(fCat="All",F26=fCat),OR(fCust="All",D26=fCust),OR(fReg="All",E26=fReg)),1,0) -> 1 | AP26: =IF(AND(AL26=1,AO26=1),AM26+ROW()/100000,0) -> 0
A27: NHP-0026 | B27: 46067 | C27: CUST-7126 | D27: Commercial | E27: Bengaluru | F27: Swimming Pool Heat Pump | G27: 2 | H27: 632000 | I27: 46081 | J27: 46078 | K27: 46080 | L27: 46084 | M27: 46081 | N27: Completed | R27: Pipe routing confirmed | S27: OK | T27: 1 | U27: 1 | V27: 1 | W27: =DATE(YEAR(B27),MONTH(B27),1) -> 46054 | X27: =IF(AND(N27<>"Cancelled",I27<=AsOf),1,0) -> 1 | Y27: =IF(AND(N27<>"Cancelled",OR(ISNUMBER(K27),N27="Completed")),1,0) -> 1 | Z27: =IF(AND(Y27=1,U27=1,ISNUMBER(K27)),K27-I27,"") -> -1 | AA27: =IF(Z27="","",IF(Z27<0,"Early",IF(Z27=0,"On Time","Late"))) -> Early | AB27: =IF(AND(N27<>"Cancelled",L27<=AsOf),1,0) -> 1 | AC27: =IF(AND(N27<>"Cancelled",OR(ISNUMBER(M27),N27="Completed")),1,0) -> 1 | AD27: =IF(AND(AC27=1,V27=1,ISNUMBER(M27)),M27-L27,"") -> -3 | AE27: =IF(AD27="","",IF(AD27<0,"Early",IF(AD27=0,"On Time","Late"))) -> Early | AF27: =IF(AND(T27=1,ISNUMBER(J27),N27<>"Cancelled"),J27-B27,"") -> 11 | AG27: =IF(AND(AF27<>"",Z27<>""),K27-J27,"") -> 2 | AH27: =IF(AND(Z27<>"",AD27<>""),M27-K27,"") -> 1 | AI27: =IF(Z27<>"",K27-B27,"") -> 13 | AJ27: =IF(AND(N27="Completed",AD27<>""),M27-B27,"") -> 14 | AK27: =IF(N27="Cancelled","Cancelled",IF(N27="Completed","Completed",IF(Y27=1,"Awaiting Installation",IF(ISNUMBER(J27),"In Transit","In Production")))) -> Completed | AL27: =IF(AND(N27="Pending",OR(AND(Y27=0,I27<AsOf),AND(Y27=1,L27<AsOf))),1,0) -> 0 | AM27: =IF(AL27=1,IF(Y27=0,AsOf-I27,AsOf-L27),"") | AN27: =IF(AL27=1,IF(Y27=0,"Delivery","Installation"),"") | AO27: =IF(AND(OR(fCat="All",F27=fCat),OR(fCust="All",D27=fCust),OR(fReg="All",E27=fReg)),1,0) -> 1 | AP27: =IF(AND(AL27=1,AO27=1),AM27+ROW()/100000,0) -> 0
A28: NHP-0027 | B28: 46070 | C28: CUST-3664 | D28: Residential | E28: Rest of Karnataka | F28: Heat Pump Water Heater | G28: 1 | H28: 185000 | I28: 46082 | J28: 46074 | K28: 46078 | L28: 46085 | M28: 46080 | N28: Completed | R28: Customer requested weekend install | S28: OK | T28: 1 | U28: 1 | V28: 1 | W28: =DATE(YEAR(B28),MONTH(B28),1) -> 46054 | X28: =IF(AND(N28<>"Cancelled",I28<=AsOf),1,0) -> 1 | Y28: =IF(AND(N28<>"Cancelled",OR(ISNUMBER(K28),N28="Completed")),1,0) -> 1 | Z28: =IF(AND(Y28=1,U28=1,ISNUMBER(K28)),K28-I28,"") -> -4 | AA28: =IF(Z28="","",IF(Z28<0,"Early",IF(Z28=0,"On Time","Late"))) -> Early | AB28: =IF(AND(N28<>"Cancelled",L28<=AsOf),1,0) -> 1 | AC28: =IF(AND(N28<>"Cancelled",OR(ISNUMBER(M28),N28="Completed")),1,0) -> 1 | AD28: =IF(AND(AC28=1,V28=1,ISNUMBER(M28)),M28-L28,"") -> -5 | AE28: =IF(AD28="","",IF(AD28<0,"Early",IF(AD28=0,"On Time","Late"))) -> Early | AF28: =IF(AND(T28=1,ISNUMBER(J28),N28<>"Cancelled"),J28-B28,"") -> 4 | AG28: =IF(AND(AF28<>"",Z28<>""),K28-J28,"") -> 4 | AH28: =IF(AND(Z28<>"",AD28<>""),M28-K28,"") -> 2 | AI28: =IF(Z28<>"",K28-B28,"") -> 8 | AJ28: =IF(AND(N28="Completed",AD28<>""),M28-B28,"") -> 10 | AK28: =IF(N28="Cancelled","Cancelled",IF(N28="Completed","Completed",IF(Y28=1,"Awaiting Installation",IF(ISNUMBER(J28),"In Transit","In Production")))) -> Completed | AL28: =IF(AND(N28="Pending",OR(AND(Y28=0,I28<AsOf),AND(Y28=1,L28<AsOf))),1,0) -> 0 | AM28: =IF(AL28=1,IF(Y28=0,AsOf-I28,AsOf-L28),"") | AN28: =IF(AL28=1,IF(Y28=0,"Delivery","Installation"),"") | AO28: =IF(AND(OR(fCat="All",F28=fCat),OR(fCust="All",D28=fCust),OR(fReg="All",E28=fReg)),1,0) -> 1 | AP28: =IF(AND(AL28=1,AO28=1),AM28+ROW()/100000,0) -> 0
A29: NHP-0028 | B29: 46070 | C29: CUST-6574 | D29: Commercial | E29: Bengaluru | F29: Custom Requirement | G29: 2 | H29: 1670000 | I29: 46100 | J29: 46108 | K29: 46109 | L29: 46105 | M29: 46113 | N29: Completed | O29: Production backlog | S29: OK | T29: 1 | U29: 1 | V29: 1 | W29: =DATE(YEAR(B29),MONTH(B29),1) -> 46054 | X29: =IF(AND(N29<>"Cancelled",I29<=AsOf),1,0) -> 1 | Y29: =IF(AND(N29<>"Cancelled",OR(ISNUMBER(K29),N29="Completed")),1,0) -> 1 | Z29: =IF(AND(Y29=1,U29=1,ISNUMBER(K29)),K29-I29,"") -> 9 | AA29: =IF(Z29="","",IF(Z29<0,"Early",IF(Z29=0,"On Time","Late"))) -> Late | AB29: =IF(AND(N29<>"Cancelled",L29<=AsOf),1,0) -> 1 | AC29: =IF(AND(N29<>"Cancelled",OR(ISNUMBER(M29),N29="Completed")),1,0) -> 1 | AD29: =IF(AND(AC29=1,V29=1,ISNUMBER(M29)),M29-L29,"") -> 8 | AE29: =IF(AD29="","",IF(AD29<0,"Early",IF(AD29=0,"On Time","Late"))) -> Late | AF29: =IF(AND(T29=1,ISNUMBER(J29),N29<>"Cancelled"),J29-B29,"") -> 38 | AG29: =IF(AND(AF29<>"",Z29<>""),K29-J29,"") -> 1 | AH29: =IF(AND(Z29<>"",AD29<>""),M29-K29,"") -> 4 | AI29: =IF(Z29<>"",K29-B29,"") -> 39 | AJ29: =IF(AND(N29="Completed",AD29<>""),M29-B29,"") -> 43 | AK29: =IF(N29="Cancelled","Cancelled",IF(N29="Completed","Completed",IF(Y29=1,"Awaiting Installation",IF(ISNUMBER(J29),"In Transit","In Production")))) -> Completed | AL29: =IF(AND(N29="Pending",OR(AND(Y29=0,I29<AsOf),AND(Y29=1,L29<AsOf))),1,0) -> 0 | AM29: =IF(AL29=1,IF(Y29=0,AsOf-I29,AsOf-L29),"") | AN29: =IF(AL29=1,IF(Y29=0,"Delivery","Installation"),"") | AO29: =IF(AND(OR(fCat="All",F29=fCat),OR(fCust="All",D29=fCust),OR(fReg="All",E29=fReg)),1,0) -> 1 | AP29: =IF(AND(AL29=1,AO29=1),AM29+ROW()/100000,0) -> 0
A30: NHP-0029 | B30: 46071 | C30: CUST-4432 | D30: Commercial | E30: Bengaluru | F30: Swimming Pool Heat Pump | G30: 2 | H30: 900000 | I30: 46085 | J30: 46080 | K30: 46082 | L30: 46088 | M30: 46084 | N30: Completed | S30: OK | T30: 1 | U30: 1 | V30: 1 | W30: =DATE(YEAR(B30),MONTH(B30),1) -> 46054 | X30: =IF(AND(N30<>"Cancelled",I30<=AsOf),1,0) -> 1 | Y30: =IF(AND(N30<>"Cancelled",OR(ISNUMBER(K30),N30="Completed")),1,0) -> 1 | Z30: =IF(AND(Y30=1,U30=1,ISNUMBER(K30)),K30-I30,"") -> -3 | AA30: =IF(Z30="","",IF(Z30<0,"Early",IF(Z30=0,"On Time","Late"))) -> Early | AB30: =IF(AND(N30<>"Cancelled",L30<=AsOf),1,0) -> 1 | AC30: =IF(AND(N30<>"Cancelled",OR(ISNUMBER(M30),N30="Completed")),1,0) -> 1 | AD30: =IF(AND(AC30=1,V30=1,ISNUMBER(M30)),M30-L30,"") -> -4 | AE30: =IF(AD30="","",IF(AD30<0,"Early",IF(AD30=0,"On Time","Late"))) -> Early | AF30: =IF(AND(T30=1,ISNUMBER(J30),N30<>"Cancelled"),J30-B30,"") -> 9 | AG30: =IF(AND(AF30<>"",Z30<>""),K30-J30,"") -> 2 | AH30: =IF(AND(Z30<>"",AD30<>""),M30-K30,"") -> 2 | AI30: =IF(Z30<>"",K30-B30,"") -> 11 | AJ30: =IF(AND(N30="Completed",AD30<>""),M30-B30,"") -> 13 | AK30: =IF(N30="Cancelled","Cancelled",IF(N30="Completed","Completed",IF(Y30=1,"Awaiting Installation",IF(ISNUMBER(J30),"In Transit","In Production")))) -> Completed | AL30: =IF(AND(N30="Pending",OR(AND(Y30=0,I30<AsOf),AND(Y30=1,L30<AsOf))),1,0) -> 0 | AM30: =IF(AL30=1,IF(Y30=0,AsOf-I30,AsOf-L30),"") | AN30: =IF(AL30=1,IF(Y30=0,"Delivery","Installation"),"") | AO30: =IF(AND(OR(fCat="All",F30=fCat),OR(fCust="All",D30=fCust),OR(fReg="All",E30=fReg)),1,0) -> 1 | AP30: =IF(AND(AL30=1,AO30=1),AM30+ROW()/100000,0) -> 0
A31: NHP-0030 | B31: 46073 | C31: CUST-9669 | D31: Institutional | E31: Bengaluru | F31: Commercial Heat Pump | G31: 3 | H31: 3144000 | I31: 46091 | J31: 46096 | K31: 46098 | L31: 46096 | M31: 46103 | N31: Completed | O31: Production backlog | P31: Knock-on from late delivery | R31: Replacement of old geyser | S31: OK | T31: 1 | U31: 1 | V31: 1 | W31: =DATE(YEAR(B31),MONTH(B31),1) -> 46054 | X31: =IF(AND(N31<>"Cancelled",I31<=AsOf),1,0) -> 1 | Y31: =IF(AND(N31<>"Cancelled",OR(ISNUMBER(K31),N31="Completed")),1,0) -> 1 | Z31: =IF(AND(Y31=1,U31=1,ISNUMBER(K31)),K31-I31,"") -> 7 | AA31: =IF(Z31="","",IF(Z31<0,"Early",IF(Z31=0,"On Time","Late"))) -> Late | AB31: =IF(AND(N31<>"Cancelled",L31<=AsOf),1,0) -> 1 | AC31: =IF(AND(N31<>"Cancelled",OR(ISNUMBER(M31),N31="Completed")),1,0) -> 1 | AD31: =IF(AND(AC31=1,V31=1,ISNUMBER(M31)),M31-L31,"") -> 7 | AE31: =IF(AD31="","",IF(AD31<0,"Early",IF(AD31=0,"On Time","Late"))) -> Late | AF31: =IF(AND(T31=1,ISNUMBER(J31),N31<>"Cancelled"),J31-B31,"") -> 23 | AG31: =IF(AND(AF31<>"",Z31<>""),K31-J31,"") -> 2 | AH31: =IF(AND(Z31<>"",AD31<>""),M31-K31,"") -> 5 | AI31: =IF(Z31<>"",K31-B31,"") -> 25 | AJ31: =IF(AND(N31="Completed",AD31<>""),M31-B31,"") -> 30 | AK31: =IF(N31="Cancelled","Cancelled",IF(N31="Completed","Completed",IF(Y31=1,"Awaiting Installation",IF(ISNUMBER(J31),"In Transit","In Production")))) -> Completed | AL31: =IF(AND(N31="Pending",OR(AND(Y31=0,I31<AsOf),AND(Y31=1,L31<AsOf))),1,0) -> 0 | AM31: =IF(AL31=1,IF(Y31=0,AsOf-I31,AsOf-L31),"") | AN31: =IF(AL31=1,IF(Y31=0,"Delivery","Installation"),"") | AO31: =IF(AND(OR(fCat="All",F31=fCat),OR(fCust="All",D31=fCust),OR(fReg="All",E31=fReg)),1,0) -> 1 | AP31: =IF(AND(AL31=1,AO31=1),AM31+ROW()/100000,0) -> 0
A32: NHP-0031 | B32: 46073 | C32: CUST-5808 | D32: Commercial | E32: Bengaluru | F32: Heat Pump Dryer | G32: 1 | H32: 619000 | I32: 46094 | J32: 46077 | K32: 46079 | L32: 46099 | M32: 46084 | N32: Completed | R32: Replacement of old geyser | S32: OK | T32: 1 | U32: 1 | V32: 1 | W32: =DATE(YEAR(B32),MONTH(B32),1) -> 46054 | X32: =IF(AND(N32<>"Cancelled",I32<=AsOf),1,0) -> 1 | Y32: =IF(AND(N32<>"Cancelled",OR(ISNUMBER(K32),N32="Completed")),1,0) -> 1 | Z32: =IF(AND(Y32=1,U32=1,ISNUMBER(K32)),K32-I32,"") -> -15 | AA32: =IF(Z32="","",IF(Z32<0,"Early",IF(Z32=0,"On Time","Late"))) -> Early | AB32: =IF(AND(N32<>"Cancelled",L32<=AsOf),1,0) -> 1 | AC32: =IF(AND(N32<>"Cancelled",OR(ISNUMBER(M32),N32="Completed")),1,0) -> 1 | AD32: =IF(AND(AC32=1,V32=1,ISNUMBER(M32)),M32-L32,"") -> -15 | AE32: =IF(AD32="","",IF(AD32<0,"Early",IF(AD32=0,"On Time","Late"))) -> Early | AF32: =IF(AND(T32=1,ISNUMBER(J32),N32<>"Cancelled"),J32-B32,"") -> 4 | AG32: =IF(AND(AF32<>"",Z32<>""),K32-J32,"") -> 2 | AH32: =IF(AND(Z32<>"",AD32<>""),M32-K32,"") -> 5 | AI32: =IF(Z32<>"",K32-B32,"") -> 6 | AJ32: =IF(AND(N32="Completed",AD32<>""),M32-B32,"") -> 11 | AK32: =IF(N32="Cancelled","Cancelled",IF(N32="Completed","Completed",IF(Y32=1,"Awaiting Installation",IF(ISNUMBER(J32),"In Transit","In Production")))) -> Completed | AL32: =IF(AND(N32="Pending",OR(AND(Y32=0,I32<AsOf),AND(Y32=1,L32<AsOf))),1,0) -> 0 | AM32: =IF(AL32=1,IF(Y32=0,AsOf-I32,AsOf-L32),"") | AN32: =IF(AL32=1,IF(Y32=0,"Delivery","Installation"),"") | AO32: =IF(AND(OR(fCat="All",F32=fCat),OR(fCust="All",D32=fCust),OR(fReg="All",E32=fReg)),1,0) -> 1 | AP32: =IF(AND(AL32=1,AO32=1),AM32+ROW()/100000,0) -> 0
A33: NHP-0032 | B33: 46077 | C33: CUST-5119 | D33: Residential | E33: Rest of Karnataka | F33: Heat Pump Water Heater | G33: 1 | H33: 183000 | I33: 46089 | J33: 46085 | K33: 46089 | L33: 46092 | M33: 46097 | N33: Completed | S33: OK | T33: 1 | U33: 1 | V33: 1 | W33: =DATE(YEAR(B33),MONTH(B33),1) -> 46054 | X33: =IF(AND(N33<>"Cancelled",I33<=AsOf),1,0) -> 1 | Y33: =IF(AND(N33<>"Cancelled",OR(ISNUMBER(K33),N33="Completed")),1,0) -> 1 | Z33: =IF(AND(Y33=1,U33=1,ISNUMBER(K33)),K33-I33,"") -> 0 | AA33: =IF(Z33="","",IF(Z33<0,"Early",IF(Z33=0,"On Time","Late"))) -> On Time | AB33: =IF(AND(N33<>"Cancelled",L33<=AsOf),1,0) -> 1 | AC33: =IF(AND(N33<>"Cancelled",OR(ISNUMBER(M33),N33="Completed")),1,0) -> 1 | AD33: =IF(AND(AC33=1,V33=1,ISNUMBER(M33)),M33-L33,"") -> 5 | AE33: =IF(AD33="","",IF(AD33<0,"Early",IF(AD33=0,"On Time","Late"))) -> Late | AF33: =IF(AND(T33=1,ISNUMBER(J33),N33<>"Cancelled"),J33-B33,"") -> 8 | AG33: =IF(AND(AF33<>"",Z33<>""),K33-J33,"") -> 4 | AH33: =IF(AND(Z33<>"",AD33<>""),M33-K33,"") -> 8 | AI33: =IF(Z33<>"",K33-B33,"") -> 12 | AJ33: =IF(AND(N33="Completed",AD33<>""),M33-B33,"") -> 20 | AK33: =IF(N33="Cancelled","Cancelled",IF(N33="Completed","Completed",IF(Y33=1,"Awaiting Installation",IF(ISNUMBER(J33),"In Transit","In Production")))) -> Completed | AL33: =IF(AND(N33="Pending",OR(AND(Y33=0,I33<AsOf),AND(Y33=1,L33<AsOf))),1,0) -> 0 | AM33: =IF(AL33=1,IF(Y33=0,AsOf-I33,AsOf-L33),"") | AN33: =IF(AL33=1,IF(Y33=0,"Delivery","Installation"),"") | AO33: =IF(AND(OR(fCat="All",F33=fCat),OR(fCust="All",D33=fCust),OR(fReg="All",E33=fReg)),1,0) -> 1 | AP33: =IF(AND(AL33=1,AO33=1),AM33+ROW()/100000,0) -> 0
A34: NHP-0033 | B34: 46077 | C34: CUST-4150 | D34: Commercial | E34: Bengaluru | F34: Commercial Heat Pump | G34: 4 | H34: 2952000 | I34: 46095 | J34: 46098 | K34: 46099 | L34: 46100 | M34: 46096 | N34: Completed | P34: Knock-on from late delivery | S34: Installed before delivery | T34: 1 | U34: 1 | V34: 0 | W34: =DATE(YEAR(B34),MONTH(B34),1) -> 46054 | X34: =IF(AND(N34<>"Cancelled",I34<=AsOf),1,0) -> 1 | Y34: =IF(AND(N34<>"Cancelled",OR(ISNUMBER(K34),N34="Completed")),1,0) -> 1 | Z34: =IF(AND(Y34=1,U34=1,ISNUMBER(K34)),K34-I34,"") -> 4 | AA34: =IF(Z34="","",IF(Z34<0,"Early",IF(Z34=0,"On Time","Late"))) -> Late | AB34: =IF(AND(N34<>"Cancelled",L34<=AsOf),1,0) -> 1 | AC34: =IF(AND(N34<>"Cancelled",OR(ISNUMBER(M34),N34="Completed")),1,0) -> 1 | AD34: =IF(AND(AC34=1,V34=1,ISNUMBER(M34)),M34-L34,"") | AE34: =IF(AD34="","",IF(AD34<0,"Early",IF(AD34=0,"On Time","Late"))) | AF34: =IF(AND(T34=1,ISNUMBER(J34),N34<>"Cancelled"),J34-B34,"") -> 21 | AG34: =IF(AND(AF34<>"",Z34<>""),K34-J34,"") -> 1 | AH34: =IF(AND(Z34<>"",AD34<>""),M34-K34,"") | AI34: =IF(Z34<>"",K34-B34,"") -> 22 | AJ34: =IF(AND(N34="Completed",AD34<>""),M34-B34,"") | AK34: =IF(N34="Cancelled","Cancelled",IF(N34="Completed","Completed",IF(Y34=1,"Awaiting Installation",IF(ISNUMBER(J34),"In Transit","In Production")))) -> Completed | AL34: =IF(AND(N34="Pending",OR(AND(Y34=0,I34<AsOf),AND(Y34=1,L34<AsOf))),1,0) -> 0 | AM34: =IF(AL34=1,IF(Y34=0,AsOf-I34,AsOf-L34),"") | AN34: =IF(AL34=1,IF(Y34=0,"Delivery","Installation"),"") | AO34: =IF(AND(OR(fCat="All",F34=fCat),OR(fCust="All",D34=fCust),OR(fReg="All",E34=fReg)),1,0) -> 1 | AP34: =IF(AND(AL34=1,AO34=1),AM34+ROW()/100000,0) -> 0
A35: NHP-0034 | B35: 46078 | C35: CUST-3547 | D35: Commercial | E35: Bengaluru | F35: Swimming Pool Heat Pump | G35: 2 | H35: 488000 | I35: 46092 | J35: 46083 | K35: 46085 | L35: 46095 | M35: 46097 | N35: Completed | P35: Customer site not ready | S35: OK | T35: 1 | U35: 1 | V35: 1 | W35: =DATE(YEAR(B35),MONTH(B35),1) -> 46054 | X35: =IF(AND(N35<>"Cancelled",I35<=AsOf),1,0) -> 1 | Y35: =IF(AND(N35<>"Cancelled",OR(ISNUMBER(K35),N35="Completed")),1,0) -> 1 | Z35: =IF(AND(Y35=1,U35=1,ISNUMBER(K35)),K35-I35,"") -> -7 | AA35: =IF(Z35="","",IF(Z35<0,"Early",IF(Z35=0,"On Time","Late"))) -> Early | AB35: =IF(AND(N35<>"Cancelled",L35<=AsOf),1,0) -> 1 | AC35: =IF(AND(N35<>"Cancelled",OR(ISNUMBER(M35),N35="Completed")),1,0) -> 1 | AD35: =IF(AND(AC35=1,V35=1,ISNUMBER(M35)),M35-L35,"") -> 2 | AE35: =IF(AD35="","",IF(AD35<0,"Early",IF(AD35=0,"On Time","Late"))) -> Late | AF35: =IF(AND(T35=1,ISNUMBER(J35),N35<>"Cancelled"),J35-B35,"") -> 5 | AG35: =IF(AND(AF35<>"",Z35<>""),K35-J35,"") -> 2 | AH35: =IF(AND(Z35<>"",AD35<>""),M35-K35,"") -> 12 | AI35: =IF(Z35<>"",K35-B35,"") -> 7 | AJ35: =IF(AND(N35="Completed",AD35<>""),M35-B35,"") -> 19 | AK35: =IF(N35="Cancelled","Cancelled",IF(N35="Completed","Completed",IF(Y35=1,"Awaiting Installation",IF(ISNUMBER(J35),"In Transit","In Production")))) -> Completed | AL35: =IF(AND(N35="Pending",OR(AND(Y35=0,I35<AsOf),AND(Y35=1,L35<AsOf))),1,0) -> 0 | AM35: =IF(AL35=1,IF(Y35=0,AsOf-I35,AsOf-L35),"") | AN35: =IF(AL35=1,IF(Y35=0,"Delivery","Installation"),"") | AO35: =IF(AND(OR(fCat="All",F35=fCat),OR(fCust="All",D35=fCust),OR(fReg="All",E35=fReg)),1,0) -> 1 | AP35: =IF(AND(AL35=1,AO35=1),AM35+ROW()/100000,0) -> 0
A36: NHP-0035 | B36: 46078 | C36: CUST-8428 | D36: Residential | E36: Bengaluru | F36: Swimming Pool Heat Pump | G36: 1 | I36: 46092 | J36: 46093 | K36: 46095 | L36: 46095 | M36: 46098 | N36: Completed | O36: Production backlog | P36: Knock-on from late delivery | S36: Order value missing | T36: 1 | U36: 1 | V36: 1 | W36: =DATE(YEAR(B36),MONTH(B36),1) -> 46054 | X36: =IF(AND(N36<>"Cancelled",I36<=AsOf),1,0) -> 1 | Y36: =IF(AND(N36<>"Cancelled",OR(ISNUMBER(K36),N36="Completed")),1,0) -> 1 | Z36: =IF(AND(Y36=1,U36=1,ISNUMBER(K36)),K36-I36,"") -> 3 | AA36: =IF(Z36="","",IF(Z36<0,"Early",IF(Z36=0,"On Time","Late"))) -> Late | AB36: =IF(AND(N36<>"Cancelled",L36<=AsOf),1,0) -> 1 | AC36: =IF(AND(N36<>"Cancelled",OR(ISNUMBER(M36),N36="Completed")),1,0) -> 1 | AD36: =IF(AND(AC36=1,V36=1,ISNUMBER(M36)),M36-L36,"") -> 3 | AE36: =IF(AD36="","",IF(AD36<0,"Early",IF(AD36=0,"On Time","Late"))) -> Late | AF36: =IF(AND(T36=1,ISNUMBER(J36),N36<>"Cancelled"),J36-B36,"") -> 15 | AG36: =IF(AND(AF36<>"",Z36<>""),K36-J36,"") -> 2 | AH36: =IF(AND(Z36<>"",AD36<>""),M36-K36,"") -> 3 | AI36: =IF(Z36<>"",K36-B36,"") -> 17 | AJ36: =IF(AND(N36="Completed",AD36<>""),M36-B36,"") -> 20 | AK36: =IF(N36="Cancelled","Cancelled",IF(N36="Completed","Completed",IF(Y36=1,"Awaiting Installation",IF(ISNUMBER(J36),"In Transit","In Production")))) -> Completed | AL36: =IF(AND(N36="Pending",OR(AND(Y36=0,I36<AsOf),AND(Y36=1,L36<AsOf))),1,0) -> 0 | AM36: =IF(AL36=1,IF(Y36=0,AsOf-I36,AsOf-L36),"") | AN36: =IF(AL36=1,IF(Y36=0,"Delivery","Installation"),"") | AO36: =IF(AND(OR(fCat="All",F36=fCat),OR(fCust="All",D36=fCust),OR(fReg="All",E36=fReg)),1,0) -> 1 | AP36: =IF(AND(AL36=1,AO36=1),AM36+ROW()/100000,0) -> 0
A37: NHP-0036 | B37: 46079 | C37: CUST-4257 | D37: Commercial | E37: Bengaluru | F37: Heat Pump Water Heater | G37: 2 | H37: 264000 | I37: 46089 | J37: 46080 | K37: 46081 | L37: 46092 | M37: 46090 | N37: Completed | R37: Customer requested weekend install | S37: OK | T37: 1 | U37: 1 | V37: 1 | W37: =DATE(YEAR(B37),MONTH(B37),1) -> 46054 | X37: =IF(AND(N37<>"Cancelled",I37<=AsOf),1,0) -> 1 | Y37: =IF(AND(N37<>"Cancelled",OR(ISNUMBER(K37),N37="Completed")),1,0) -> 1 | Z37: =IF(AND(Y37=1,U37=1,ISNUMBER(K37)),K37-I37,"") -> -8 | AA37: =IF(Z37="","",IF(Z37<0,"Early",IF(Z37=0,"On Time","Late"))) -> Early | AB37: =IF(AND(N37<>"Cancelled",L37<=AsOf),1,0) -> 1 | AC37: =IF(AND(N37<>"Cancelled",OR(ISNUMBER(M37),N37="Completed")),1,0) -> 1 | AD37: =IF(AND(AC37=1,V37=1,ISNUMBER(M37)),M37-L37,"") -> -2 | AE37: =IF(AD37="","",IF(AD37<0,"Early",IF(AD37=0,"On Time","Late"))) -> Early | AF37: =IF(AND(T37=1,ISNUMBER(J37),N37<>"Cancelled"),J37-B37,"") -> 1 | AG37: =IF(AND(AF37<>"",Z37<>""),K37-J37,"") -> 1 | AH37: =IF(AND(Z37<>"",AD37<>""),M37-K37,"") -> 9 | AI37: =IF(Z37<>"",K37-B37,"") -> 2 | AJ37: =IF(AND(N37="Completed",AD37<>""),M37-B37,"") -> 11 | AK37: =IF(N37="Cancelled","Cancelled",IF(N37="Completed","Completed",IF(Y37=1,"Awaiting Installation",IF(ISNUMBER(J37),"In Transit","In Production")))) -> Completed | AL37: =IF(AND(N37="Pending",OR(AND(Y37=0,I37<AsOf),AND(Y37=1,L37<AsOf))),1,0) -> 0 | AM37: =IF(AL37=1,IF(Y37=0,AsOf-I37,AsOf-L37),"") | AN37: =IF(AL37=1,IF(Y37=0,"Delivery","Installation"),"") | AO37: =IF(AND(OR(fCat="All",F37=fCat),OR(fCust="All",D37=fCust),OR(fReg="All",E37=fReg)),1,0) -> 1 | AP37: =IF(AND(AL37=1,AO37=1),AM37+ROW()/100000,0) -> 0
A38: NHP-0037 | B38: 46080 | C38: CUST-5371 | D38: Commercial | E38: Bengaluru | F38: Commercial Heat Pump | G38: 1 | H38: 1055000 | I38: 46098 | J38: 46090 | K38: 46092 | L38: 46103 | M38: 46096 | N38: Completed | R38: Electrical load checked | S38: OK | T38: 1 | U38: 1 | V38: 1 | W38: =DATE(YEAR(B38),MONTH(B38),1) -> 46054 | X38: =IF(AND(N38<>"Cancelled",I38<=AsOf),1,0) -> 1 | Y38: =IF(AND(N38<>"Cancelled",OR(ISNUMBER(K38),N38="Completed")),1,0) -> 1 | Z38: =IF(AND(Y38=1,U38=1,ISNUMBER(K38)),K38-I38,"") -> -6 | AA38: =IF(Z38="","",IF(Z38<0,"Early",IF(Z38=0,"On Time","Late"))) -> Early | AB38: =IF(AND(N38<>"Cancelled",L38<=AsOf),1,0) -> 1 | AC38: =IF(AND(N38<>"Cancelled",OR(ISNUMBER(M38),N38="Completed")),1,0) -> 1 | AD38: =IF(AND(AC38=1,V38=1,ISNUMBER(M38)),M38-L38,"") -> -7 | AE38: =IF(AD38="","",IF(AD38<0,"Early",IF(AD38=0,"On Time","Late"))) -> Early | AF38: =IF(AND(T38=1,ISNUMBER(J38),N38<>"Cancelled"),J38-B38,"") -> 10 | AG38: =IF(AND(AF38<>"",Z38<>""),K38-J38,"") -> 2 | AH38: =IF(AND(Z38<>"",AD38<>""),M38-K38,"") -> 4 | AI38: =IF(Z38<>"",K38-B38,"") -> 12 | AJ38: =IF(AND(N38="Completed",AD38<>""),M38-B38,"") -> 16 | AK38: =IF(N38="Cancelled","Cancelled",IF(N38="Completed","Completed",IF(Y38=1,"Awaiting Installation",IF(ISNUMBER(J38),"In Transit","In Production")))) -> Completed | AL38: =IF(AND(N38="Pending",OR(AND(Y38=0,I38<AsOf),AND(Y38=1,L38<AsOf))),1,0) -> 0 | AM38: =IF(AL38=1,IF(Y38=0,AsOf-I38,AsOf-L38),"") | AN38: =IF(AL38=1,IF(Y38=0,"Delivery","Installation"),"") | AO38: =IF(AND(OR(fCat="All",F38=fCat),OR(fCust="All",D38=fCust),OR(fReg="All",E38=fReg)),1,0) -> 1 | AP38: =IF(AND(AL38=1,AO38=1),AM38+ROW()/100000,0) -> 0
A39: NHP-0038 | B39: 46082 | C39: CUST-4527 | D39: Institutional | E39: Bengaluru | F39: Heat Pump Dryer | G39: 1 | H39: 753000 | I39: 46103 | L39: 46108 | N39: Cancelled | Q39: Customer postponed project | R39: Electrical load checked | S39: OK | T39: 1 | U39: 1 | V39: 1 | W39: =DATE(YEAR(B39),MONTH(B39),1) -> 46082 | X39: =IF(AND(N39<>"Cancelled",I39<=AsOf),1,0) -> 0 | Y39: =IF(AND(N39<>"Cancelled",OR(ISNUMBER(K39),N39="Completed")),1,0) -> 0 | Z39: =IF(AND(Y39=1,U39=1,ISNUMBER(K39)),K39-I39,"") | AA39: =IF(Z39="","",IF(Z39<0,"Early",IF(Z39=0,"On Time","Late"))) | AB39: =IF(AND(N39<>"Cancelled",L39<=AsOf),1,0) -> 0 | AC39: =IF(AND(N39<>"Cancelled",OR(ISNUMBER(M39),N39="Completed")),1,0) -> 0 | AD39: =IF(AND(AC39=1,V39=1,ISNUMBER(M39)),M39-L39,"") | AE39: =IF(AD39="","",IF(AD39<0,"Early",IF(AD39=0,"On Time","Late"))) | AF39: =IF(AND(T39=1,ISNUMBER(J39),N39<>"Cancelled"),J39-B39,"") | AG39: =IF(AND(AF39<>"",Z39<>""),K39-J39,"") | AH39: =IF(AND(Z39<>"",AD39<>""),M39-K39,"") | AI39: =IF(Z39<>"",K39-B39,"") | AJ39: =IF(AND(N39="Completed",AD39<>""),M39-B39,"") | AK39: =IF(N39="Cancelled","Cancelled",IF(N39="Completed","Completed",IF(Y39=1,"Awaiting Installation",IF(ISNUMBER(J39),"In Transit","In Production")))) -> Cancelled | AL39: =IF(AND(N39="Pending",OR(AND(Y39=0,I39<AsOf),AND(Y39=1,L39<AsOf))),1,0) -> 0 | AM39: =IF(AL39=1,IF(Y39=0,AsOf-I39,AsOf-L39),"") | AN39: =IF(AL39=1,IF(Y39=0,"Delivery","Installation"),"") | AO39: =IF(AND(OR(fCat="All",F39=fCat),OR(fCust="All",D39=fCust),OR(fReg="All",E39=fReg)),1,0) -> 1 | AP39: =IF(AND(AL39=1,AO39=1),AM39+ROW()/100000,0) -> 0
A40: NHP-0039 | B40: 46082 | C40: CUST-7916 | D40: Institutional | E40: Bengaluru | F40: Heat Pump Water Heater | G40: 2 | H40: 260000 | I40: 46092 | J40: 46085 | K40: 46086 | L40: 46095 | M40: 46087 | N40: Completed | S40: OK | T40: 1 | U40: 1 | V40: 1 | W40: =DATE(YEAR(B40),MONTH(B40),1) -> 46082 | X40: =IF(AND(N40<>"Cancelled",I40<=AsOf),1,0) -> 1 | Y40: =IF(AND(N40<>"Cancelled",OR(ISNUMBER(K40),N40="Completed")),1,0) -> 1 | Z40: =IF(AND(Y40=1,U40=1,ISNUMBER(K40)),K40-I40,"") -> -6 | AA40: =IF(Z40="","",IF(Z40<0,"Early",IF(Z40=0,"On Time","Late"))) -> Early | AB40: =IF(AND(N40<>"Cancelled",L40<=AsOf),1,0) -> 1 | AC40: =IF(AND(N40<>"Cancelled",OR(ISNUMBER(M40),N40="Completed")),1,0) -> 1 | AD40: =IF(AND(AC40=1,V40=1,ISNUMBER(M40)),M40-L40,"") -> -8 | AE40: =IF(AD40="","",IF(AD40<0,"Early",IF(AD40=0,"On Time","Late"))) -> Early | AF40: =IF(AND(T40=1,ISNUMBER(J40),N40<>"Cancelled"),J40-B40,"") -> 3 | AG40: =IF(AND(AF40<>"",Z40<>""),K40-J40,"") -> 1 | AH40: =IF(AND(Z40<>"",AD40<>""),M40-K40,"") -> 1 | AI40: =IF(Z40<>"",K40-B40,"") -> 4 | AJ40: =IF(AND(N40="Completed",AD40<>""),M40-B40,"") -> 5 | AK40: =IF(N40="Cancelled","Cancelled",IF(N40="Completed","Completed",IF(Y40=1,"Awaiting Installation",IF(ISNUMBER(J40),"In Transit","In Production")))) -> Completed | AL40: =IF(AND(N40="Pending",OR(AND(Y40=0,I40<AsOf),AND(Y40=1,L40<AsOf))),1,0) -> 0 | AM40: =IF(AL40=1,IF(Y40=0,AsOf-I40,AsOf-L40),"") | AN40: =IF(AL40=1,IF(Y40=0,"Delivery","Installation"),"") | AO40: =IF(AND(OR(fCat="All",F40=fCat),OR(fCust="All",D40=fCust),OR(fReg="All",E40=fReg)),1,0) -> 1 | AP40: =IF(AND(AL40=1,AO40=1),AM40+ROW()/100000,0) -> 0
A41: NHP-0040 | B41: 46083 | C41: CUST-1916 | D41: Institutional | E41: Bengaluru | F41: Heat Pump Dryer | G41: 2 | H41: 1030000 | I41: 46104 | J41: 46098 | K41: 46099 | L41: 46109 | M41: 46114 | N41: Completed | P41: Customer site not ready | R41: Electrical load checked | S41: OK | T41: 1 | U41: 1 | V41: 1 | W41: =DATE(YEAR(B41),MONTH(B41),1) -> 46082 | X41: =IF(AND(N41<>"Cancelled",I41<=AsOf),1,0) -> 1 | Y41: =IF(AND(N41<>"Cancelled",OR(ISNUMBER(K41),N41="Completed")),1,0) -> 1 | Z41: =IF(AND(Y41=1,U41=1,ISNUMBER(K41)),K41-I41,"") -> -5 | AA41: =IF(Z41="","",IF(Z41<0,"Early",IF(Z41=0,"On Time","Late"))) -> Early | AB41: =IF(AND(N41<>"Cancelled",L41<=AsOf),1,0) -> 1 | AC41: =IF(AND(N41<>"Cancelled",OR(ISNUMBER(M41),N41="Completed")),1,0) -> 1 | AD41: =IF(AND(AC41=1,V41=1,ISNUMBER(M41)),M41-L41,"") -> 5 | AE41: =IF(AD41="","",IF(AD41<0,"Early",IF(AD41=0,"On Time","Late"))) -> Late | AF41: =IF(AND(T41=1,ISNUMBER(J41),N41<>"Cancelled"),J41-B41,"") -> 15 | AG41: =IF(AND(AF41<>"",Z41<>""),K41-J41,"") -> 1 | AH41: =IF(AND(Z41<>"",AD41<>""),M41-K41,"") -> 15 | AI41: =IF(Z41<>"",K41-B41,"") -> 16 | AJ41: =IF(AND(N41="Completed",AD41<>""),M41-B41,"") -> 31 | AK41: =IF(N41="Cancelled","Cancelled",IF(N41="Completed","Completed",IF(Y41=1,"Awaiting Installation",IF(ISNUMBER(J41),"In Transit","In Production")))) -> Completed | AL41: =IF(AND(N41="Pending",OR(AND(Y41=0,I41<AsOf),AND(Y41=1,L41<AsOf))),1,0) -> 0 | AM41: =IF(AL41=1,IF(Y41=0,AsOf-I41,AsOf-L41),"") | AN41: =IF(AL41=1,IF(Y41=0,"Delivery","Installation"),"") | AO41: =IF(AND(OR(fCat="All",F41=fCat),OR(fCust="All",D41=fCust),OR(fReg="All",E41=fReg)),1,0) -> 1 | AP41: =IF(AND(AL41=1,AO41=1),AM41+ROW()/100000,0) -> 0
A42: NHP-0041 | B42: 46084 | C42: CUST-2084 | D42: Commercial | E42: Bengaluru | F42: Swimming Pool Heat Pump | G42: 1 | H42: 426000 | I42: 46098 | J42: 46094 | K42: 46095 | L42: 46101 | M42: 46096 | N42: Completed | S42: OK | T42: 1 | U42: 1 | V42: 1 | W42: =DATE(YEAR(B42),MONTH(B42),1) -> 46082 | X42: =IF(AND(N42<>"Cancelled",I42<=AsOf),1,0) -> 1 | Y42: =IF(AND(N42<>"Cancelled",OR(ISNUMBER(K42),N42="Completed")),1,0) -> 1 | Z42: =IF(AND(Y42=1,U42=1,ISNUMBER(K42)),K42-I42,"") -> -3 | AA42: =IF(Z42="","",IF(Z42<0,"Early",IF(Z42=0,"On Time","Late"))) -> Early | AB42: =IF(AND(N42<>"Cancelled",L42<=AsOf),1,0) -> 1 | AC42: =IF(AND(N42<>"Cancelled",OR(ISNUMBER(M42),N42="Completed")),1,0) -> 1 | AD42: =IF(AND(AC42=1,V42=1,ISNUMBER(M42)),M42-L42,"") -> -5 | AE42: =IF(AD42="","",IF(AD42<0,"Early",IF(AD42=0,"On Time","Late"))) -> Early | AF42: =IF(AND(T42=1,ISNUMBER(J42),N42<>"Cancelled"),J42-B42,"") -> 10 | AG42: =IF(AND(AF42<>"",Z42<>""),K42-J42,"") -> 1 | AH42: =IF(AND(Z42<>"",AD42<>""),M42-K42,"") -> 1 | AI42: =IF(Z42<>"",K42-B42,"") -> 11 | AJ42: =IF(AND(N42="Completed",AD42<>""),M42-B42,"") -> 12 | AK42: =IF(N42="Cancelled","Cancelled",IF(N42="Completed","Completed",IF(Y42=1,"Awaiting Installation",IF(ISNUMBER(J42),"In Transit","In Production")))) -> Completed | AL42: =IF(AND(N42="Pending",OR(AND(Y42=0,I42<AsOf),AND(Y42=1,L42<AsOf))),1,0) -> 0 | AM42: =IF(AL42=1,IF(Y42=0,AsOf-I42,AsOf-L42),"") | AN42: =IF(AL42=1,IF(Y42=0,"Delivery","Installation"),"") | AO42: =IF(AND(OR(fCat="All",F42=fCat),OR(fCust="All",D42=fCust),OR(fReg="All",E42=fReg)),1,0) -> 1 | AP42: =IF(AND(AL42=1,AO42=1),AM42+ROW()/100000,0) -> 0
A43: NHP-0042 | B43: 46090 | C43: CUST-7912 | D43: Institutional | E43: Bengaluru | F43: Commercial Heat Pump | G43: 3 | H43: 1974000 | I43: 46108 | J43: 46102 | K43: 46104 | L43: 46113 | M43: 46108 | N43: Completed | R43: Electrical load checked | S43: OK | T43: 1 | U43: 1 | V43: 1 | W43: =DATE(YEAR(B43),MONTH(B43),1) -> 46082 | X43: =IF(AND(N43<>"Cancelled",I43<=AsOf),1,0) -> 1 | Y43: =IF(AND(N43<>"Cancelled",OR(ISNUMBER(K43),N43="Completed")),1,0) -> 1 | Z43: =IF(AND(Y43=1,U43=1,ISNUMBER(K43)),K43-I43,"") -> -4 | AA43: =IF(Z43="","",IF(Z43<0,"Early",IF(Z43=0,"On Time","Late"))) -> Early | AB43: =IF(AND(N43<>"Cancelled",L43<=AsOf),1,0) -> 1 | AC43: =IF(AND(N43<>"Cancelled",OR(ISNUMBER(M43),N43="Completed")),1,0) -> 1 | AD43: =IF(AND(AC43=1,V43=1,ISNUMBER(M43)),M43-L43,"") -> -5 | AE43: =IF(AD43="","",IF(AD43<0,"Early",IF(AD43=0,"On Time","Late"))) -> Early | AF43: =IF(AND(T43=1,ISNUMBER(J43),N43<>"Cancelled"),J43-B43,"") -> 12 | AG43: =IF(AND(AF43<>"",Z43<>""),K43-J43,"") -> 2 | AH43: =IF(AND(Z43<>"",AD43<>""),M43-K43,"") -> 4 | AI43: =IF(Z43<>"",K43-B43,"") -> 14 | AJ43: =IF(AND(N43="Completed",AD43<>""),M43-B43,"") -> 18 | AK43: =IF(N43="Cancelled","Cancelled",IF(N43="Completed","Completed",IF(Y43=1,"Awaiting Installation",IF(ISNUMBER(J43),"In Transit","In Production")))) -> Completed | AL43: =IF(AND(N43="Pending",OR(AND(Y43=0,I43<AsOf),AND(Y43=1,L43<AsOf))),1,0) -> 0 | AM43: =IF(AL43=1,IF(Y43=0,AsOf-I43,AsOf-L43),"") | AN43: =IF(AL43=1,IF(Y43=0,"Delivery","Installation"),"") | AO43: =IF(AND(OR(fCat="All",F43=fCat),OR(fCust="All",D43=fCust),OR(fReg="All",E43=fReg)),1,0) -> 1 | AP43: =IF(AND(AL43=1,AO43=1),AM43+ROW()/100000,0) -> 0
A44: NHP-0043 | B44: 46091 | C44: CUST-5741 | D44: Residential | E44: Bengaluru | F44: Swimming Pool Heat Pump | G44: 1 | H44: 225000 | I44: 46105 | J44: 46102 | K44: 46104 | L44: 46108 | M44: 46105 | N44: Completed | R44: Electrical load checked | S44: OK | T44: 1 | U44: 1 | V44: 1 | W44: =DATE(YEAR(B44),MONTH(B44),1) -> 46082 | X44: =IF(AND(N44<>"Cancelled",I44<=AsOf),1,0) -> 1 | Y44: =IF(AND(N44<>"Cancelled",OR(ISNUMBER(K44),N44="Completed")),1,0) -> 1 | Z44: =IF(AND(Y44=1,U44=1,ISNUMBER(K44)),K44-I44,"") -> -1 | AA44: =IF(Z44="","",IF(Z44<0,"Early",IF(Z44=0,"On Time","Late"))) -> Early | AB44: =IF(AND(N44<>"Cancelled",L44<=AsOf),1,0) -> 1 | AC44: =IF(AND(N44<>"Cancelled",OR(ISNUMBER(M44),N44="Completed")),1,0) -> 1 | AD44: =IF(AND(AC44=1,V44=1,ISNUMBER(M44)),M44-L44,"") -> -3 | AE44: =IF(AD44="","",IF(AD44<0,"Early",IF(AD44=0,"On Time","Late"))) -> Early | AF44: =IF(AND(T44=1,ISNUMBER(J44),N44<>"Cancelled"),J44-B44,"") -> 11 | AG44: =IF(AND(AF44<>"",Z44<>""),K44-J44,"") -> 2 | AH44: =IF(AND(Z44<>"",AD44<>""),M44-K44,"") -> 1 | AI44: =IF(Z44<>"",K44-B44,"") -> 13 | AJ44: =IF(AND(N44="Completed",AD44<>""),M44-B44,"") -> 14 | AK44: =IF(N44="Cancelled","Cancelled",IF(N44="Completed","Completed",IF(Y44=1,"Awaiting Installation",IF(ISNUMBER(J44),"In Transit","In Production")))) -> Completed | AL44: =IF(AND(N44="Pending",OR(AND(Y44=0,I44<AsOf),AND(Y44=1,L44<AsOf))),1,0) -> 0 | AM44: =IF(AL44=1,IF(Y44=0,AsOf-I44,AsOf-L44),"") | AN44: =IF(AL44=1,IF(Y44=0,"Delivery","Installation"),"") | AO44: =IF(AND(OR(fCat="All",F44=fCat),OR(fCust="All",D44=fCust),OR(fReg="All",E44=fReg)),1,0) -> 1 | AP44: =IF(AND(AL44=1,AO44=1),AM44+ROW()/100000,0) -> 0
A45: NHP-0044 | B45: 46095 | C45: CUST-6313 | D45: Commercial | E45: Bengaluru | F45: Swimming Pool Heat Pump | G45: 2 | H45: 1174000 | I45: 46109 | J45: 46106 | K45: 46108 | L45: 46112 | M45: 46110 | N45: Completed | S45: OK | T45: 1 | U45: 1 | V45: 1 | W45: =DATE(YEAR(B45),MONTH(B45),1) -> 46082 | X45: =IF(AND(N45<>"Cancelled",I45<=AsOf),1,0) -> 1 | Y45: =IF(AND(N45<>"Cancelled",OR(ISNUMBER(K45),N45="Completed")),1,0) -> 1 | Z45: =IF(AND(Y45=1,U45=1,ISNUMBER(K45)),K45-I45,"") -> -1 | AA45: =IF(Z45="","",IF(Z45<0,"Early",IF(Z45=0,"On Time","Late"))) -> Early | AB45: =IF(AND(N45<>"Cancelled",L45<=AsOf),1,0) -> 1 | AC45: =IF(AND(N45<>"Cancelled",OR(ISNUMBER(M45),N45="Completed")),1,0) -> 1 | AD45: =IF(AND(AC45=1,V45=1,ISNUMBER(M45)),M45-L45,"") -> -2 | AE45: =IF(AD45="","",IF(AD45<0,"Early",IF(AD45=0,"On Time","Late"))) -> Early | AF45: =IF(AND(T45=1,ISNUMBER(J45),N45<>"Cancelled"),J45-B45,"") -> 11 | AG45: =IF(AND(AF45<>"",Z45<>""),K45-J45,"") -> 2 | AH45: =IF(AND(Z45<>"",AD45<>""),M45-K45,"") -> 2 | AI45: =IF(Z45<>"",K45-B45,"") -> 13 | AJ45: =IF(AND(N45="Completed",AD45<>""),M45-B45,"") -> 15 | AK45: =IF(N45="Cancelled","Cancelled",IF(N45="Completed","Completed",IF(Y45=1,"Awaiting Installation",IF(ISNUMBER(J45),"In Transit","In Production")))) -> Completed | AL45: =IF(AND(N45="Pending",OR(AND(Y45=0,I45<AsOf),AND(Y45=1,L45<AsOf))),1,0) -> 0 | AM45: =IF(AL45=1,IF(Y45=0,AsOf-I45,AsOf-L45),"") | AN45: =IF(AL45=1,IF(Y45=0,"Delivery","Installation"),"") | AO45: =IF(AND(OR(fCat="All",F45=fCat),OR(fCust="All",D45=fCust),OR(fReg="All",E45=fReg)),1,0) -> 1 | AP45: =IF(AND(AL45=1,AO45=1),AM45+ROW()/100000,0) -> 0
A46: NHP-0045 | B46: 46096 | C46: CUST-9179 | D46: Residential | E46: Rest of Karnataka | F46: Swimming Pool Heat Pump | G46: 1 | H46: 499000 | I46: 46112 | J46: 46104 | K46: 46107 | L46: 46115 | M46: 46108 | N46: Completed | S46: OK | T46: 1 | U46: 1 | V46: 1 | W46: =DATE(YEAR(B46),MONTH(B46),1) -> 46082 | X46: =IF(AND(N46<>"Cancelled",I46<=AsOf),1,0) -> 1 | Y46: =IF(AND(N46<>"Cancelled",OR(ISNUMBER(K46),N46="Completed")),1,0) -> 1 | Z46: =IF(AND(Y46=1,U46=1,ISNUMBER(K46)),K46-I46,"") -> -5 | AA46: =IF(Z46="","",IF(Z46<0,"Early",IF(Z46=0,"On Time","Late"))) -> Early | AB46: =IF(AND(N46<>"Cancelled",L46<=AsOf),1,0) -> 1 | AC46: =IF(AND(N46<>"Cancelled",OR(ISNUMBER(M46),N46="Completed")),1,0) -> 1 | AD46: =IF(AND(AC46=1,V46=1,ISNUMBER(M46)),M46-L46,"") -> -7 | AE46: =IF(AD46="","",IF(AD46<0,"Early",IF(AD46=0,"On Time","Late"))) -> Early | AF46: =IF(AND(T46=1,ISNUMBER(J46),N46<>"Cancelled"),J46-B46,"") -> 8 | AG46: =IF(AND(AF46<>"",Z46<>""),K46-J46,"") -> 3 | AH46: =IF(AND(Z46<>"",AD46<>""),M46-K46,"") -> 1 | AI46: =IF(Z46<>"",K46-B46,"") -> 11 | AJ46: =IF(AND(N46="Completed",AD46<>""),M46-B46,"") -> 12 | AK46: =IF(N46="Cancelled","Cancelled",IF(N46="Completed","Completed",IF(Y46=1,"Awaiting Installation",IF(ISNUMBER(J46),"In Transit","In Production")))) -> Completed | AL46: =IF(AND(N46="Pending",OR(AND(Y46=0,I46<AsOf),AND(Y46=1,L46<AsOf))),1,0) -> 0 | AM46: =IF(AL46=1,IF(Y46=0,AsOf-I46,AsOf-L46),"") | AN46: =IF(AL46=1,IF(Y46=0,"Delivery","Installation"),"") | AO46: =IF(AND(OR(fCat="All",F46=fCat),OR(fCust="All",D46=fCust),OR(fReg="All",E46=fReg)),1,0) -> 1 | AP46: =IF(AND(AL46=1,AO46=1),AM46+ROW()/100000,0) -> 0
A47: NHP-0046 | B47: 46098 | C47: CUST-9830 | D47: Residential | E47: Bengaluru | F47: Heat Pump Water Heater | G47: 1 | H47: 197000 | I47: 46108 | J47: 46106 | K47: 46107 | L47: 46111 | M47: 46198 | N47: Completed | P47: Customer site not ready | R47: Site survey done | S47: OK | T47: 1 | U47: 1 | V47: 1 | W47: =DATE(YEAR(B47),MONTH(B47),1) -> 46082 | X47: =IF(AND(N47<>"Cancelled",I47<=AsOf),1,0) -> 1 | Y47: =IF(AND(N47<>"Cancelled",OR(ISNUMBER(K47),N47="Completed")),1,0) -> 1 | Z47: =IF(AND(Y47=1,U47=1,ISNUMBER(K47)),K47-I47,"") -> -1 | AA47: =IF(Z47="","",IF(Z47<0,"Early",IF(Z47=0,"On Time","Late"))) -> Early | AB47: =IF(AND(N47<>"Cancelled",L47<=AsOf),1,0) -> 1 | AC47: =IF(AND(N47<>"Cancelled",OR(ISNUMBER(M47),N47="Completed")),1,0) -> 1 | AD47: =IF(AND(AC47=1,V47=1,ISNUMBER(M47)),M47-L47,"") -> 87 | AE47: =IF(AD47="","",IF(AD47<0,"Early",IF(AD47=0,"On Time","Late"))) -> Late | AF47: =IF(AND(T47=1,ISNUMBER(J47),N47<>"Cancelled"),J47-B47,"") -> 8 | AG47: =IF(AND(AF47<>"",Z47<>""),K47-J47,"") -> 1 | AH47: =IF(AND(Z47<>"",AD47<>""),M47-K47,"") -> 91 | AI47: =IF(Z47<>"",K47-B47,"") -> 9 | AJ47: =IF(AND(N47="Completed",AD47<>""),M47-B47,"") -> 100 | AK47: =IF(N47="Cancelled","Cancelled",IF(N47="Completed","Completed",IF(Y47=1,"Awaiting Installation",IF(ISNUMBER(J47),"In Transit","In Production")))) -> Completed | AL47: =IF(AND(N47="Pending",OR(AND(Y47=0,I47<AsOf),AND(Y47=1,L47<AsOf))),1,0) -> 0 | AM47: =IF(AL47=1,IF(Y47=0,AsOf-I47,AsOf-L47),"") | AN47: =IF(AL47=1,IF(Y47=0,"Delivery","Installation"),"") | AO47: =IF(AND(OR(fCat="All",F47=fCat),OR(fCust="All",D47=fCust),OR(fReg="All",E47=fReg)),1,0) -> 1 | AP47: =IF(AND(AL47=1,AO47=1),AM47+ROW()/100000,0) -> 0
A48: NHP-0047 | B48: 46099 | C48: CUST-7224 | D48: Commercial | E48: Bengaluru | F48: Swimming Pool Heat Pump | G48: 1 | H48: 517000 | I48: 46113 | J48: 46106 | K48: 46108 | L48: 46116 | M48: 46109 | N48: Completed | R48: Electrical load checked | S48: OK | T48: 1 | U48: 1 | V48: 1 | W48: =DATE(YEAR(B48),MONTH(B48),1) -> 46082 | X48: =IF(AND(N48<>"Cancelled",I48<=AsOf),1,0) -> 1 | Y48: =IF(AND(N48<>"Cancelled",OR(ISNUMBER(K48),N48="Completed")),1,0) -> 1 | Z48: =IF(AND(Y48=1,U48=1,ISNUMBER(K48)),K48-I48,"") -> -5 | AA48: =IF(Z48="","",IF(Z48<0,"Early",IF(Z48=0,"On Time","Late"))) -> Early | AB48: =IF(AND(N48<>"Cancelled",L48<=AsOf),1,0) -> 1 | AC48: =IF(AND(N48<>"Cancelled",OR(ISNUMBER(M48),N48="Completed")),1,0) -> 1 | AD48: =IF(AND(AC48=1,V48=1,ISNUMBER(M48)),M48-L48,"") -> -7 | AE48: =IF(AD48="","",IF(AD48<0,"Early",IF(AD48=0,"On Time","Late"))) -> Early | AF48: =IF(AND(T48=1,ISNUMBER(J48),N48<>"Cancelled"),J48-B48,"") -> 7 | AG48: =IF(AND(AF48<>"",Z48<>""),K48-J48,"") -> 2 | AH48: =IF(AND(Z48<>"",AD48<>""),M48-K48,"") -> 1 | AI48: =IF(Z48<>"",K48-B48,"") -> 9 | AJ48: =IF(AND(N48="Completed",AD48<>""),M48-B48,"") -> 10 | AK48: =IF(N48="Cancelled","Cancelled",IF(N48="Completed","Completed",IF(Y48=1,"Awaiting Installation",IF(ISNUMBER(J48),"In Transit","In Production")))) -> Completed | AL48: =IF(AND(N48="Pending",OR(AND(Y48=0,I48<AsOf),AND(Y48=1,L48<AsOf))),1,0) -> 0 | AM48: =IF(AL48=1,IF(Y48=0,AsOf-I48,AsOf-L48),"") | AN48: =IF(AL48=1,IF(Y48=0,"Delivery","Installation"),"") | AO48: =IF(AND(OR(fCat="All",F48=fCat),OR(fCust="All",D48=fCust),OR(fReg="All",E48=fReg)),1,0) -> 1 | AP48: =IF(AND(AL48=1,AO48=1),AM48+ROW()/100000,0) -> 0
A49: NHP-0048 | B49: 46099 | C49: CUST-7252 | D49: Commercial | E49: Rest of Karnataka | F49: Swimming Pool Heat Pump | G49: 1 | H49: 469000 | I49: 46115 | J49: 46109 | K49: 46111 | L49: 46118 | M49: 46112 | N49: Completed | R49: Pipe routing confirmed | S49: OK | T49: 1 | U49: 1 | V49: 1 | W49: =DATE(YEAR(B49),MONTH(B49),1) -> 46082 | X49: =IF(AND(N49<>"Cancelled",I49<=AsOf),1,0) -> 1 | Y49: =IF(AND(N49<>"Cancelled",OR(ISNUMBER(K49),N49="Completed")),1,0) -> 1 | Z49: =IF(AND(Y49=1,U49=1,ISNUMBER(K49)),K49-I49,"") -> -4 | AA49: =IF(Z49="","",IF(Z49<0,"Early",IF(Z49=0,"On Time","Late"))) -> Early | AB49: =IF(AND(N49<>"Cancelled",L49<=AsOf),1,0) -> 1 | AC49: =IF(AND(N49<>"Cancelled",OR(ISNUMBER(M49),N49="Completed")),1,0) -> 1 | AD49: =IF(AND(AC49=1,V49=1,ISNUMBER(M49)),M49-L49,"") -> -6 | AE49: =IF(AD49="","",IF(AD49<0,"Early",IF(AD49=0,"On Time","Late"))) -> Early | AF49: =IF(AND(T49=1,ISNUMBER(J49),N49<>"Cancelled"),J49-B49,"") -> 10 | AG49: =IF(AND(AF49<>"",Z49<>""),K49-J49,"") -> 2 | AH49: =IF(AND(Z49<>"",AD49<>""),M49-K49,"") -> 1 | AI49: =IF(Z49<>"",K49-B49,"") -> 12 | AJ49: =IF(AND(N49="Completed",AD49<>""),M49-B49,"") -> 13 | AK49: =IF(N49="Cancelled","Cancelled",IF(N49="Completed","Completed",IF(Y49=1,"Awaiting Installation",IF(ISNUMBER(J49),"In Transit","In Production")))) -> Completed | AL49: =IF(AND(N49="Pending",OR(AND(Y49=0,I49<AsOf),AND(Y49=1,L49<AsOf))),1,0) -> 0 | AM49: =IF(AL49=1,IF(Y49=0,AsOf-I49,AsOf-L49),"") | AN49: =IF(AL49=1,IF(Y49=0,"Delivery","Installation"),"") | AO49: =IF(AND(OR(fCat="All",F49=fCat),OR(fCust="All",D49=fCust),OR(fReg="All",E49=fReg)),1,0) -> 1 | AP49: =IF(AND(AL49=1,AO49=1),AM49+ROW()/100000,0) -> 0
A50: NHP-0049 | B50: 46100 | C50: CUST-2291 | D50: Residential | E50: Bengaluru | F50: Heat Pump Water Heater | G50: 1 | H50: 198000 | I50: 46110 | J50: 46104 | K50: 46106 | L50: 46113 | M50: 46108 | N50: Completed | R50: Electrical load checked | S50: OK | T50: 1 | U50: 1 | V50: 1 | W50: =DATE(YEAR(B50),MONTH(B50),1) -> 46082 | X50: =IF(AND(N50<>"Cancelled",I50<=AsOf),1,0) -> 1 | Y50: =IF(AND(N50<>"Cancelled",OR(ISNUMBER(K50),N50="Completed")),1,0) -> 1 | Z50: =IF(AND(Y50=1,U50=1,ISNUMBER(K50)),K50-I50,"") -> -4 | AA50: =IF(Z50="","",IF(Z50<0,"Early",IF(Z50=0,"On Time","Late"))) -> Early | AB50: =IF(AND(N50<>"Cancelled",L50<=AsOf),1,0) -> 1 | AC50: =IF(AND(N50<>"Cancelled",OR(ISNUMBER(M50),N50="Completed")),1,0) -> 1 | AD50: =IF(AND(AC50=1,V50=1,ISNUMBER(M50)),M50-L50,"") -> -5 | AE50: =IF(AD50="","",IF(AD50<0,"Early",IF(AD50=0,"On Time","Late"))) -> Early | AF50: =IF(AND(T50=1,ISNUMBER(J50),N50<>"Cancelled"),J50-B50,"") -> 4 | AG50: =IF(AND(AF50<>"",Z50<>""),K50-J50,"") -> 2 | AH50: =IF(AND(Z50<>"",AD50<>""),M50-K50,"") -> 2 | AI50: =IF(Z50<>"",K50-B50,"") -> 6 | AJ50: =IF(AND(N50="Completed",AD50<>""),M50-B50,"") -> 8 | AK50: =IF(N50="Cancelled","Cancelled",IF(N50="Completed","Completed",IF(Y50=1,"Awaiting Installation",IF(ISNUMBER(J50),"In Transit","In Production")))) -> Completed | AL50: =IF(AND(N50="Pending",OR(AND(Y50=0,I50<AsOf),AND(Y50=1,L50<AsOf))),1,0) -> 0 | AM50: =IF(AL50=1,IF(Y50=0,AsOf-I50,AsOf-L50),"") | AN50: =IF(AL50=1,IF(Y50=0,"Delivery","Installation"),"") | AO50: =IF(AND(OR(fCat="All",F50=fCat),OR(fCust="All",D50=fCust),OR(fReg="All",E50=fReg)),1,0) -> 1 | AP50: =IF(AND(AL50=1,AO50=1),AM50+ROW()/100000,0) -> 0
A51: NHP-0050 | B51: 46100 | C51: CUST-2824 | D51: Institutional | E51: Other States | F51: Custom Requirement | G51: 1 | H51: 503000 | I51: 46134 | J51: 46129 | K51: 46144 | L51: 46139 | N51: Pending | O51: Transport scheduling | S51: OK | T51: 1 | U51: 1 | V51: 1 | W51: =DATE(YEAR(B51),MONTH(B51),1) -> 46082 | X51: =IF(AND(N51<>"Cancelled",I51<=AsOf),1,0) -> 1 | Y51: =IF(AND(N51<>"Cancelled",OR(ISNUMBER(K51),N51="Completed")),1,0) -> 1 | Z51: =IF(AND(Y51=1,U51=1,ISNUMBER(K51)),K51-I51,"") -> 10 | AA51: =IF(Z51="","",IF(Z51<0,"Early",IF(Z51=0,"On Time","Late"))) -> Late | AB51: =IF(AND(N51<>"Cancelled",L51<=AsOf),1,0) -> 1 | AC51: =IF(AND(N51<>"Cancelled",OR(ISNUMBER(M51),N51="Completed")),1,0) -> 0 | AD51: =IF(AND(AC51=1,V51=1,ISNUMBER(M51)),M51-L51,"") | AE51: =IF(AD51="","",IF(AD51<0,"Early",IF(AD51=0,"On Time","Late"))) | AF51: =IF(AND(T51=1,ISNUMBER(J51),N51<>"Cancelled"),J51-B51,"") -> 29 | AG51: =IF(AND(AF51<>"",Z51<>""),K51-J51,"") -> 15 | AH51: =IF(AND(Z51<>"",AD51<>""),M51-K51,"") | AI51: =IF(Z51<>"",K51-B51,"") -> 44 | AJ51: =IF(AND(N51="Completed",AD51<>""),M51-B51,"") | AK51: =IF(N51="Cancelled","Cancelled",IF(N51="Completed","Completed",IF(Y51=1,"Awaiting Installation",IF(ISNUMBER(J51),"In Transit","In Production")))) -> Awaiting Installation | AL51: =IF(AND(N51="Pending",OR(AND(Y51=0,I51<AsOf),AND(Y51=1,L51<AsOf))),1,0) -> 1 | AM51: =IF(AL51=1,IF(Y51=0,AsOf-I51,AsOf-L51),"") -> 64 | AN51: =IF(AL51=1,IF(Y51=0,"Delivery","Installation"),"") -> Installation | AO51: =IF(AND(OR(fCat="All",F51=fCat),OR(fCust="All",D51=fCust),OR(fReg="All",E51=fReg)),1,0) -> 1 | AP51: =IF(AND(AL51=1,AO51=1),AM51+ROW()/100000,0) -> 64.00051
A52: NHP-0051 | B52: 46102 | C52: CUST-2169 | D52: Commercial | E52: Bengaluru | F52: Swimming Pool Heat Pump | G52: 1 | H52: 347000 | I52: 46116 | J52: 46112 | K52: 46114 | L52: 46119 | M52: 46116 | N52: Completed | R52: Site survey done | S52: OK | T52: 1 | U52: 1 | V52: 1 | W52: =DATE(YEAR(B52),MONTH(B52),1) -> 46082 | X52: =IF(AND(N52<>"Cancelled",I52<=AsOf),1,0) -> 1 | Y52: =IF(AND(N52<>"Cancelled",OR(ISNUMBER(K52),N52="Completed")),1,0) -> 1 | Z52: =IF(AND(Y52=1,U52=1,ISNUMBER(K52)),K52-I52,"") -> -2 | AA52: =IF(Z52="","",IF(Z52<0,"Early",IF(Z52=0,"On Time","Late"))) -> Early | AB52: =IF(AND(N52<>"Cancelled",L52<=AsOf),1,0) -> 1 | AC52: =IF(AND(N52<>"Cancelled",OR(ISNUMBER(M52),N52="Completed")),1,0) -> 1 | AD52: =IF(AND(AC52=1,V52=1,ISNUMBER(M52)),M52-L52,"") -> -3 | AE52: =IF(AD52="","",IF(AD52<0,"Early",IF(AD52=0,"On Time","Late"))) -> Early | AF52: =IF(AND(T52=1,ISNUMBER(J52),N52<>"Cancelled"),J52-B52,"") -> 10 | AG52: =IF(AND(AF52<>"",Z52<>""),K52-J52,"") -> 2 | AH52: =IF(AND(Z52<>"",AD52<>""),M52-K52,"") -> 2 | AI52: =IF(Z52<>"",K52-B52,"") -> 12 | AJ52: =IF(AND(N52="Completed",AD52<>""),M52-B52,"") -> 14 | AK52: =IF(N52="Cancelled","Cancelled",IF(N52="Completed","Completed",IF(Y52=1,"Awaiting Installation",IF(ISNUMBER(J52),"In Transit","In Production")))) -> Completed | AL52: =IF(AND(N52="Pending",OR(AND(Y52=0,I52<AsOf),AND(Y52=1,L52<AsOf))),1,0) -> 0 | AM52: =IF(AL52=1,IF(Y52=0,AsOf-I52,AsOf-L52),"") | AN52: =IF(AL52=1,IF(Y52=0,"Delivery","Installation"),"") | AO52: =IF(AND(OR(fCat="All",F52=fCat),OR(fCust="All",D52=fCust),OR(fReg="All",E52=fReg)),1,0) -> 1 | AP52: =IF(AND(AL52=1,AO52=1),AM52+ROW()/100000,0) -> 0
A53: NHP-0052 | B53: 46106 | C53: CUST-5119 | D53: Residential | E53: Bengaluru | F53: Swimming Pool Heat Pump | G53: 1 | H53: 439000 | I53: 46120 | J53: 46117 | K53: 46119 | L53: 46123 | M53: 46120 | N53: Completed | R53: Site survey done | S53: OK | T53: 1 | U53: 1 | V53: 1 | W53: =DATE(YEAR(B53),MONTH(B53),1) -> 46082 | X53: =IF(AND(N53<>"Cancelled",I53<=AsOf),1,0) -> 1 | Y53: =IF(AND(N53<>"Cancelled",OR(ISNUMBER(K53),N53="Completed")),1,0) -> 1 | Z53: =IF(AND(Y53=1,U53=1,ISNUMBER(K53)),K53-I53,"") -> -1 | AA53: =IF(Z53="","",IF(Z53<0,"Early",IF(Z53=0,"On Time","Late"))) -> Early | AB53: =IF(AND(N53<>"Cancelled",L53<=AsOf),1,0) -> 1 | AC53: =IF(AND(N53<>"Cancelled",OR(ISNUMBER(M53),N53="Completed")),1,0) -> 1 | AD53: =IF(AND(AC53=1,V53=1,ISNUMBER(M53)),M53-L53,"") -> -3 | AE53: =IF(AD53="","",IF(AD53<0,"Early",IF(AD53=0,"On Time","Late"))) -> Early | AF53: =IF(AND(T53=1,ISNUMBER(J53),N53<>"Cancelled"),J53-B53,"") -> 11 | AG53: =IF(AND(AF53<>"",Z53<>""),K53-J53,"") -> 2 | AH53: =IF(AND(Z53<>"",AD53<>""),M53-K53,"") -> 1 | AI53: =IF(Z53<>"",K53-B53,"") -> 13 | AJ53: =IF(AND(N53="Completed",AD53<>""),M53-B53,"") -> 14 | AK53: =IF(N53="Cancelled","Cancelled",IF(N53="Completed","Completed",IF(Y53=1,"Awaiting Installation",IF(ISNUMBER(J53),"In Transit","In Production")))) -> Completed | AL53: =IF(AND(N53="Pending",OR(AND(Y53=0,I53<AsOf),AND(Y53=1,L53<AsOf))),1,0) -> 0 | AM53: =IF(AL53=1,IF(Y53=0,AsOf-I53,AsOf-L53),"") | AN53: =IF(AL53=1,IF(Y53=0,"Delivery","Installation"),"") | AO53: =IF(AND(OR(fCat="All",F53=fCat),OR(fCust="All",D53=fCust),OR(fReg="All",E53=fReg)),1,0) -> 1 | AP53: =IF(AND(AL53=1,AO53=1),AM53+ROW()/100000,0) -> 0
A54: NHP-0053 | B54: 46106 | C54: CUST-2169 | D54: Institutional | E54: Bengaluru | F54: Commercial Heat Pump | G54: 1 | H54: 1005000 | I54: 46124 | J54: 46118 | K54: 46119 | L54: 46129 | M54: 46124 | N54: Completed | R54: Customer requested weekend install | S54: OK | T54: 1 | U54: 1 | V54: 1 | W54: =DATE(YEAR(B54),MONTH(B54),1) -> 46082 | X54: =IF(AND(N54<>"Cancelled",I54<=AsOf),1,0) -> 1 | Y54: =IF(AND(N54<>"Cancelled",OR(ISNUMBER(K54),N54="Completed")),1,0) -> 1 | Z54: =IF(AND(Y54=1,U54=1,ISNUMBER(K54)),K54-I54,"") -> -5 | AA54: =IF(Z54="","",IF(Z54<0,"Early",IF(Z54=0,"On Time","Late"))) -> Early | AB54: =IF(AND(N54<>"Cancelled",L54<=AsOf),1,0) -> 1 | AC54: =IF(AND(N54<>"Cancelled",OR(ISNUMBER(M54),N54="Completed")),1,0) -> 1 | AD54: =IF(AND(AC54=1,V54=1,ISNUMBER(M54)),M54-L54,"") -> -5 | AE54: =IF(AD54="","",IF(AD54<0,"Early",IF(AD54=0,"On Time","Late"))) -> Early | AF54: =IF(AND(T54=1,ISNUMBER(J54),N54<>"Cancelled"),J54-B54,"") -> 12 | AG54: =IF(AND(AF54<>"",Z54<>""),K54-J54,"") -> 1 | AH54: =IF(AND(Z54<>"",AD54<>""),M54-K54,"") -> 5 | AI54: =IF(Z54<>"",K54-B54,"") -> 13 | AJ54: =IF(AND(N54="Completed",AD54<>""),M54-B54,"") -> 18 | AK54: =IF(N54="Cancelled","Cancelled",IF(N54="Completed","Completed",IF(Y54=1,"Awaiting Installation",IF(ISNUMBER(J54),"In Transit","In Production")))) -> Completed | AL54: =IF(AND(N54="Pending",OR(AND(Y54=0,I54<AsOf),AND(Y54=1,L54<AsOf))),1,0) -> 0 | AM54: =IF(AL54=1,IF(Y54=0,AsOf-I54,AsOf-L54),"") | AN54: =IF(AL54=1,IF(Y54=0,"Delivery","Installation"),"") | AO54: =IF(AND(OR(fCat="All",F54=fCat),OR(fCust="All",D54=fCust),OR(fReg="All",E54=fReg)),1,0) -> 1 | AP54: =IF(AND(AL54=1,AO54=1),AM54+ROW()/100000,0) -> 0
A55: NHP-0054 | B55: 46106 | C55: CUST-5304 | D55: Commercial | E55: Other States | F55: Heat Pump Water Heater | G55: 1 | H55: 117000 | I55: 46120 | J55: 46108 | K55: 46119 | L55: 46123 | M55: 46120 | N55: Completed | S55: OK | T55: 1 | U55: 1 | V55: 1 | W55: =DATE(YEAR(B55),MONTH(B55),1) -> 46082 | X55: =IF(AND(N55<>"Cancelled",I55<=AsOf),1,0) -> 1 | Y55: =IF(AND(N55<>"Cancelled",OR(ISNUMBER(K55),N55="Completed")),1,0) -> 1 | Z55: =IF(AND(Y55=1,U55=1,ISNUMBER(K55)),K55-I55,"") -> -1 | AA55: =IF(Z55="","",IF(Z55<0,"Early",IF(Z55=0,"On Time","Late"))) -> Early | AB55: =IF(AND(N55<>"Cancelled",L55<=AsOf),1,0) -> 1 | AC55: =IF(AND(N55<>"Cancelled",OR(ISNUMBER(M55),N55="Completed")),1,0) -> 1 | AD55: =IF(AND(AC55=1,V55=1,ISNUMBER(M55)),M55-L55,"") -> -3 | AE55: =IF(AD55="","",IF(AD55<0,"Early",IF(AD55=0,"On Time","Late"))) -> Early | AF55: =IF(AND(T55=1,ISNUMBER(J55),N55<>"Cancelled"),J55-B55,"") -> 2 | AG55: =IF(AND(AF55<>"",Z55<>""),K55-J55,"") -> 11 | AH55: =IF(AND(Z55<>"",AD55<>""),M55-K55,"") -> 1 | AI55: =IF(Z55<>"",K55-B55,"") -> 13 | AJ55: =IF(AND(N55="Completed",AD55<>""),M55-B55,"") -> 14 | AK55: =IF(N55="Cancelled","Cancelled",IF(N55="Completed","Completed",IF(Y55=1,"Awaiting Installation",IF(ISNUMBER(J55),"In Transit","In Production")))) -> Completed | AL55: =IF(AND(N55="Pending",OR(AND(Y55=0,I55<AsOf),AND(Y55=1,L55<AsOf))),1,0) -> 0 | AM55: =IF(AL55=1,IF(Y55=0,AsOf-I55,AsOf-L55),"") | AN55: =IF(AL55=1,IF(Y55=0,"Delivery","Installation"),"") | AO55: =IF(AND(OR(fCat="All",F55=fCat),OR(fCust="All",D55=fCust),OR(fReg="All",E55=fReg)),1,0) -> 1 | AP55: =IF(AND(AL55=1,AO55=1),AM55+ROW()/100000,0) -> 0
A56: NHP-0055 | B56: 46107 | C56: CUST-3287 | D56: Residential | E56: Other States | F56: Swimming Pool Heat Pump | G56: 1 | H56: 372000 | I56: 46125 | J56: 46118 | K56: 46126 | L56: 46128 | M56: 46127 | N56: Completed | O56: Dispatch scheduling | S56: OK | T56: 1 | U56: 1 | V56: 1 | W56: =DATE(YEAR(B56),MONTH(B56),1) -> 46082 | X56: =IF(AND(N56<>"Cancelled",I56<=AsOf),1,0) -> 1 | Y56: =IF(AND(N56<>"Cancelled",OR(ISNUMBER(K56),N56="Completed")),1,0) -> 1 | Z56: =IF(AND(Y56=1,U56=1,ISNUMBER(K56)),K56-I56,"") -> 1 | AA56: =IF(Z56="","",IF(Z56<0,"Early",IF(Z56=0,"On Time","Late"))) -> Late | AB56: =IF(AND(N56<>"Cancelled",L56<=AsOf),1,0) -> 1 | AC56: =IF(AND(N56<>"Cancelled",OR(ISNUMBER(M56),N56="Completed")),1,0) -> 1 | AD56: =IF(AND(AC56=1,V56=1,ISNUMBER(M56)),M56-L56,"") -> -1 | AE56: =IF(AD56="","",IF(AD56<0,"Early",IF(AD56=0,"On Time","Late"))) -> Early | AF56: =IF(AND(T56=1,ISNUMBER(J56),N56<>"Cancelled"),J56-B56,"") -> 11 | AG56: =IF(AND(AF56<>"",Z56<>""),K56-J56,"") -> 8 | AH56: =IF(AND(Z56<>"",AD56<>""),M56-K56,"") -> 1 | AI56: =IF(Z56<>"",K56-B56,"") -> 19 | AJ56: =IF(AND(N56="Completed",AD56<>""),M56-B56,"") -> 20 | AK56: =IF(N56="Cancelled","Cancelled",IF(N56="Completed","Completed",IF(Y56=1,"Awaiting Installation",IF(ISNUMBER(J56),"In Transit","In Production")))) -> Completed | AL56: =IF(AND(N56="Pending",OR(AND(Y56=0,I56<AsOf),AND(Y56=1,L56<AsOf))),1,0) -> 0 | AM56: =IF(AL56=1,IF(Y56=0,AsOf-I56,AsOf-L56),"") | AN56: =IF(AL56=1,IF(Y56=0,"Delivery","Installation"),"") | AO56: =IF(AND(OR(fCat="All",F56=fCat),OR(fCust="All",D56=fCust),OR(fReg="All",E56=fReg)),1,0) -> 1 | AP56: =IF(AND(AL56=1,AO56=1),AM56+ROW()/100000,0) -> 0
A57: NHP-0056 | B57: 46108 | C57: CUST-1488 | D57: Commercial | E57: Bengaluru | F57: Heat Pump Dryer | G57: 2 | H57: 1000000 | I57: 46129 | J57: 46120 | K57: 46121 | L57: 46134 | M57: 46126 | N57: Completed | R57: Pipe routing confirmed | S57: OK | T57: 1 | U57: 1 | V57: 1 | W57: =DATE(YEAR(B57),MONTH(B57),1) -> 46082 | X57: =IF(AND(N57<>"Cancelled",I57<=AsOf),1,0) -> 1 | Y57: =IF(AND(N57<>"Cancelled",OR(ISNUMBER(K57),N57="Completed")),1,0) -> 1 | Z57: =IF(AND(Y57=1,U57=1,ISNUMBER(K57)),K57-I57,"") -> -8 | AA57: =IF(Z57="","",IF(Z57<0,"Early",IF(Z57=0,"On Time","Late"))) -> Early | AB57: =IF(AND(N57<>"Cancelled",L57<=AsOf),1,0) -> 1 | AC57: =IF(AND(N57<>"Cancelled",OR(ISNUMBER(M57),N57="Completed")),1,0) -> 1 | AD57: =IF(AND(AC57=1,V57=1,ISNUMBER(M57)),M57-L57,"") -> -8 | AE57: =IF(AD57="","",IF(AD57<0,"Early",IF(AD57=0,"On Time","Late"))) -> Early | AF57: =IF(AND(T57=1,ISNUMBER(J57),N57<>"Cancelled"),J57-B57,"") -> 12 | AG57: =IF(AND(AF57<>"",Z57<>""),K57-J57,"") -> 1 | AH57: =IF(AND(Z57<>"",AD57<>""),M57-K57,"") -> 5 | AI57: =IF(Z57<>"",K57-B57,"") -> 13 | AJ57: =IF(AND(N57="Completed",AD57<>""),M57-B57,"") -> 18 | AK57: =IF(N57="Cancelled","Cancelled",IF(N57="Completed","Completed",IF(Y57=1,"Awaiting Installation",IF(ISNUMBER(J57),"In Transit","In Production")))) -> Completed | AL57: =IF(AND(N57="Pending",OR(AND(Y57=0,I57<AsOf),AND(Y57=1,L57<AsOf))),1,0) -> 0 | AM57: =IF(AL57=1,IF(Y57=0,AsOf-I57,AsOf-L57),"") | AN57: =IF(AL57=1,IF(Y57=0,"Delivery","Installation"),"") | AO57: =IF(AND(OR(fCat="All",F57=fCat),OR(fCust="All",D57=fCust),OR(fReg="All",E57=fReg)),1,0) -> 1 | AP57: =IF(AND(AL57=1,AO57=1),AM57+ROW()/100000,0) -> 0
A58: NHP-0057 | B58: 46108 | C58: CUST-9279 | D58: Residential | E58: Bengaluru | F58: Heat Pump Water Heater | G58: 1 | H58: 174000 | I58: 46118 | J58: 46109 | K58: 46110 | L58: 46121 | M58: 46111 | N58: Completed | R58: Electrical load checked | S58: OK | T58: 1 | U58: 1 | V58: 1 | W58: =DATE(YEAR(B58),MONTH(B58),1) -> 46082 | X58: =IF(AND(N58<>"Cancelled",I58<=AsOf),1,0) -> 1 | Y58: =IF(AND(N58<>"Cancelled",OR(ISNUMBER(K58),N58="Completed")),1,0) -> 1 | Z58: =IF(AND(Y58=1,U58=1,ISNUMBER(K58)),K58-I58,"") -> -8 | AA58: =IF(Z58="","",IF(Z58<0,"Early",IF(Z58=0,"On Time","Late"))) -> Early | AB58: =IF(AND(N58<>"Cancelled",L58<=AsOf),1,0) -> 1 | AC58: =IF(AND(N58<>"Cancelled",OR(ISNUMBER(M58),N58="Completed")),1,0) -> 1 | AD58: =IF(AND(AC58=1,V58=1,ISNUMBER(M58)),M58-L58,"") -> -10 | AE58: =IF(AD58="","",IF(AD58<0,"Early",IF(AD58=0,"On Time","Late"))) -> Early | AF58: =IF(AND(T58=1,ISNUMBER(J58),N58<>"Cancelled"),J58-B58,"") -> 1 | AG58: =IF(AND(AF58<>"",Z58<>""),K58-J58,"") -> 1 | AH58: =IF(AND(Z58<>"",AD58<>""),M58-K58,"") -> 1 | AI58: =IF(Z58<>"",K58-B58,"") -> 2 | AJ58: =IF(AND(N58="Completed",AD58<>""),M58-B58,"") -> 3 | AK58: =IF(N58="Cancelled","Cancelled",IF(N58="Completed","Completed",IF(Y58=1,"Awaiting Installation",IF(ISNUMBER(J58),"In Transit","In Production")))) -> Completed | AL58: =IF(AND(N58="Pending",OR(AND(Y58=0,I58<AsOf),AND(Y58=1,L58<AsOf))),1,0) -> 0 | AM58: =IF(AL58=1,IF(Y58=0,AsOf-I58,AsOf-L58),"") | AN58: =IF(AL58=1,IF(Y58=0,"Delivery","Installation"),"") | AO58: =IF(AND(OR(fCat="All",F58=fCat),OR(fCust="All",D58=fCust),OR(fReg="All",E58=fReg)),1,0) -> 1 | AP58: =IF(AND(AL58=1,AO58=1),AM58+ROW()/100000,0) -> 0
A59: NHP-0058 | B59: 46109 | C59: CUST-3266 | D59: Commercial | E59: Bengaluru | F59: Heat Pump Water Heater | G59: 1 | H59: 202000 | I59: 46119 | J59: 46112 | L59: 46122 | N59: Cancelled | Q59: Long lead time | R59: Site survey done | S59: OK | T59: 1 | U59: 1 | V59: 1 | W59: =DATE(YEAR(B59),MONTH(B59),1) -> 46082 | X59: =IF(AND(N59<>"Cancelled",I59<=AsOf),1,0) -> 0 | Y59: =IF(AND(N59<>"Cancelled",OR(ISNUMBER(K59),N59="Completed")),1,0) -> 0 | Z59: =IF(AND(Y59=1,U59=1,ISNUMBER(K59)),K59-I59,"") | AA59: =IF(Z59="","",IF(Z59<0,"Early",IF(Z59=0,"On Time","Late"))) | AB59: =IF(AND(N59<>"Cancelled",L59<=AsOf),1,0) -> 0 | AC59: =IF(AND(N59<>"Cancelled",OR(ISNUMBER(M59),N59="Completed")),1,0) -> 0 | AD59: =IF(AND(AC59=1,V59=1,ISNUMBER(M59)),M59-L59,"") | AE59: =IF(AD59="","",IF(AD59<0,"Early",IF(AD59=0,"On Time","Late"))) | AF59: =IF(AND(T59=1,ISNUMBER(J59),N59<>"Cancelled"),J59-B59,"") | AG59: =IF(AND(AF59<>"",Z59<>""),K59-J59,"") | AH59: =IF(AND(Z59<>"",AD59<>""),M59-K59,"") | AI59: =IF(Z59<>"",K59-B59,"") | AJ59: =IF(AND(N59="Completed",AD59<>""),M59-B59,"") | AK59: =IF(N59="Cancelled","Cancelled",IF(N59="Completed","Completed",IF(Y59=1,"Awaiting Installation",IF(ISNUMBER(J59),"In Transit","In Production")))) -> Cancelled | AL59: =IF(AND(N59="Pending",OR(AND(Y59=0,I59<AsOf),AND(Y59=1,L59<AsOf))),1,0) -> 0 | AM59: =IF(AL59=1,IF(Y59=0,AsOf-I59,AsOf-L59),"") | AN59: =IF(AL59=1,IF(Y59=0,"Delivery","Installation"),"") | AO59: =IF(AND(OR(fCat="All",F59=fCat),OR(fCust="All",D59=fCust),OR(fReg="All",E59=fReg)),1,0) -> 1 | AP59: =IF(AND(AL59=1,AO59=1),AM59+ROW()/100000,0) -> 0
A60: NHP-0059 | B60: 46109 | C60: CUST-9179 | D60: Residential | E60: Bengaluru | F60: Heat Pump Water Heater | G60: 1 | H60: 134000 | I60: 46119 | J60: 46116 | K60: 46117 | L60: 46122 | N60: Pending | P60: Customer site not ready | R60: Customer civil work in progress | S60: OK | T60: 1 | U60: 1 | V60: 1 | W60: =DATE(YEAR(B60),MONTH(B60),1) -> 46082 | X60: =IF(AND(N60<>"Cancelled",I60<=AsOf),1,0) -> 1 | Y60: =IF(AND(N60<>"Cancelled",OR(ISNUMBER(K60),N60="Completed")),1,0) -> 1 | Z60: =IF(AND(Y60=1,U60=1,ISNUMBER(K60)),K60-I60,"") -> -2 | AA60: =IF(Z60="","",IF(Z60<0,"Early",IF(Z60=0,"On Time","Late"))) -> Early | AB60: =IF(AND(N60<>"Cancelled",L60<=AsOf),1,0) -> 1 | AC60: =IF(AND(N60<>"Cancelled",OR(ISNUMBER(M60),N60="Completed")),1,0) -> 0 | AD60: =IF(AND(AC60=1,V60=1,ISNUMBER(M60)),M60-L60,"") | AE60: =IF(AD60="","",IF(AD60<0,"Early",IF(AD60=0,"On Time","Late"))) | AF60: =IF(AND(T60=1,ISNUMBER(J60),N60<>"Cancelled"),J60-B60,"") -> 7 | AG60: =IF(AND(AF60<>"",Z60<>""),K60-J60,"") -> 1 | AH60: =IF(AND(Z60<>"",AD60<>""),M60-K60,"") | AI60: =IF(Z60<>"",K60-B60,"") -> 8 | AJ60: =IF(AND(N60="Completed",AD60<>""),M60-B60,"") | AK60: =IF(N60="Cancelled","Cancelled",IF(N60="Completed","Completed",IF(Y60=1,"Awaiting Installation",IF(ISNUMBER(J60),"In Transit","In Production")))) -> Awaiting Installation | AL60: =IF(AND(N60="Pending",OR(AND(Y60=0,I60<AsOf),AND(Y60=1,L60<AsOf))),1,0) -> 1 | AM60: =IF(AL60=1,IF(Y60=0,AsOf-I60,AsOf-L60),"") -> 81 | AN60: =IF(AL60=1,IF(Y60=0,"Delivery","Installation"),"") -> Installation | AO60: =IF(AND(OR(fCat="All",F60=fCat),OR(fCust="All",D60=fCust),OR(fReg="All",E60=fReg)),1,0) -> 1 | AP60: =IF(AND(AL60=1,AO60=1),AM60+ROW()/100000,0) -> 81.0006
A61: NHP-0060 | B61: 46109 | C61: CUST-2307 | D61: Institutional | E61: Bengaluru | F61: Custom Requirement | G61: 1 | H61: 1023000 | I61: 46139 | J61: 46198 | K61: 46199 | L61: 46144 | M61: 46202 | N61: Completed | O61: Component shortage | P61: Knock-on from late delivery | R61: Pipe routing confirmed | S61: OK | T61: 1 | U61: 1 | V61: 1 | W61: =DATE(YEAR(B61),MONTH(B61),1) -> 46082 | X61: =IF(AND(N61<>"Cancelled",I61<=AsOf),1,0) -> 1 | Y61: =IF(AND(N61<>"Cancelled",OR(ISNUMBER(K61),N61="Completed")),1,0) -> 1 | Z61: =IF(AND(Y61=1,U61=1,ISNUMBER(K61)),K61-I61,"") -> 60 | AA61: =IF(Z61="","",IF(Z61<0,"Early",IF(Z61=0,"On Time","Late"))) -> Late | AB61: =IF(AND(N61<>"Cancelled",L61<=AsOf),1,0) -> 1 | AC61: =IF(AND(N61<>"Cancelled",OR(ISNUMBER(M61),N61="Completed")),1,0) -> 1 | AD61: =IF(AND(AC61=1,V61=1,ISNUMBER(M61)),M61-L61,"") -> 58 | AE61: =IF(AD61="","",IF(AD61<0,"Early",IF(AD61=0,"On Time","Late"))) -> Late | AF61: =IF(AND(T61=1,ISNUMBER(J61),N61<>"Cancelled"),J61-B61,"") -> 89 | AG61: =IF(AND(AF61<>"",Z61<>""),K61-J61,"") -> 1 | AH61: =IF(AND(Z61<>"",AD61<>""),M61-K61,"") -> 3 | AI61: =IF(Z61<>"",K61-B61,"") -> 90 | AJ61: =IF(AND(N61="Completed",AD61<>""),M61-B61,"") -> 93 | AK61: =IF(N61="Cancelled","Cancelled",IF(N61="Completed","Completed",IF(Y61=1,"Awaiting Installation",IF(ISNUMBER(J61),"In Transit","In Production")))) -> Completed | AL61: =IF(AND(N61="Pending",OR(AND(Y61=0,I61<AsOf),AND(Y61=1,L61<AsOf))),1,0) -> 0 | AM61: =IF(AL61=1,IF(Y61=0,AsOf-I61,AsOf-L61),"") | AN61: =IF(AL61=1,IF(Y61=0,"Delivery","Installation"),"") | AO61: =IF(AND(OR(fCat="All",F61=fCat),OR(fCust="All",D61=fCust),OR(fReg="All",E61=fReg)),1,0) -> 1 | AP61: =IF(AND(AL61=1,AO61=1),AM61+ROW()/100000,0) -> 0
A62: NHP-0061 | B62: 46111 | C62: CUST-4456 | D62: Residential | E62: Rest of Karnataka | F62: Swimming Pool Heat Pump | G62: 1 | H62: 498000 | I62: 46127 | J62: 46122 | K62: 46125 | L62: 46130 | M62: 46127 | N62: Completed | R62: Site survey done | S62: OK | T62: 1 | U62: 1 | V62: 1 | W62: =DATE(YEAR(B62),MONTH(B62),1) -> 46082 | X62: =IF(AND(N62<>"Cancelled",I62<=AsOf),1,0) -> 1 | Y62: =IF(AND(N62<>"Cancelled",OR(ISNUMBER(K62),N62="Completed")),1,0) -> 1 | Z62: =IF(AND(Y62=1,U62=1,ISNUMBER(K62)),K62-I62,"") -> -2 | AA62: =IF(Z62="","",IF(Z62<0,"Early",IF(Z62=0,"On Time","Late"))) -> Early | AB62: =IF(AND(N62<>"Cancelled",L62<=AsOf),1,0) -> 1 | AC62: =IF(AND(N62<>"Cancelled",OR(ISNUMBER(M62),N62="Completed")),1,0) -> 1 | AD62: =IF(AND(AC62=1,V62=1,ISNUMBER(M62)),M62-L62,"") -> -3 | AE62: =IF(AD62="","",IF(AD62<0,"Early",IF(AD62=0,"On Time","Late"))) -> Early | AF62: =IF(AND(T62=1,ISNUMBER(J62),N62<>"Cancelled"),J62-B62,"") -> 11 | AG62: =IF(AND(AF62<>"",Z62<>""),K62-J62,"") -> 3 | AH62: =IF(AND(Z62<>"",AD62<>""),M62-K62,"") -> 2 | AI62: =IF(Z62<>"",K62-B62,"") -> 14 | AJ62: =IF(AND(N62="Completed",AD62<>""),M62-B62,"") -> 16 | AK62: =IF(N62="Cancelled","Cancelled",IF(N62="Completed","Completed",IF(Y62=1,"Awaiting Installation",IF(ISNUMBER(J62),"In Transit","In Production")))) -> Completed | AL62: =IF(AND(N62="Pending",OR(AND(Y62=0,I62<AsOf),AND(Y62=1,L62<AsOf))),1,0) -> 0 | AM62: =IF(AL62=1,IF(Y62=0,AsOf-I62,AsOf-L62),"") | AN62: =IF(AL62=1,IF(Y62=0,"Delivery","Installation"),"") | AO62: =IF(AND(OR(fCat="All",F62=fCat),OR(fCust="All",D62=fCust),OR(fReg="All",E62=fReg)),1,0) -> 1 | AP62: =IF(AND(AL62=1,AO62=1),AM62+ROW()/100000,0) -> 0
A63: NHP-0062 | B63: 46112 | C63: CUST-3287 | D63: Institutional | E63: Other States | F63: Heat Pump Water Heater | G63: 2 | H63: 312000 | I63: 46126 | J63: 46117 | K63: 46123 | L63: 46129 | M63: 46195 | N63: Completed | R63: Electrical load checked | S63: OK | T63: 1 | U63: 1 | V63: 1 | W63: =DATE(YEAR(B63),MONTH(B63),1) -> 46082 | X63: =IF(AND(N63<>"Cancelled",I63<=AsOf),1,0) -> 1 | Y63: =IF(AND(N63<>"Cancelled",OR(ISNUMBER(K63),N63="Completed")),1,0) -> 1 | Z63: =IF(AND(Y63=1,U63=1,ISNUMBER(K63)),K63-I63,"") -> -3 | AA63: =IF(Z63="","",IF(Z63<0,"Early",IF(Z63=0,"On Time","Late"))) -> Early | AB63: =IF(AND(N63<>"Cancelled",L63<=AsOf),1,0) -> 1 | AC63: =IF(AND(N63<>"Cancelled",OR(ISNUMBER(M63),N63="Completed")),1,0) -> 1 | AD63: =IF(AND(AC63=1,V63=1,ISNUMBER(M63)),M63-L63,"") -> 66 | AE63: =IF(AD63="","",IF(AD63<0,"Early",IF(AD63=0,"On Time","Late"))) -> Late | AF63: =IF(AND(T63=1,ISNUMBER(J63),N63<>"Cancelled"),J63-B63,"") -> 5 | AG63: =IF(AND(AF63<>"",Z63<>""),K63-J63,"") -> 6 | AH63: =IF(AND(Z63<>"",AD63<>""),M63-K63,"") -> 72 | AI63: =IF(Z63<>"",K63-B63,"") -> 11 | AJ63: =IF(AND(N63="Completed",AD63<>""),M63-B63,"") -> 83 | AK63: =IF(N63="Cancelled","Cancelled",IF(N63="Completed","Completed",IF(Y63=1,"Awaiting Installation",IF(ISNUMBER(J63),"In Transit","In Production")))) -> Completed | AL63: =IF(AND(N63="Pending",OR(AND(Y63=0,I63<AsOf),AND(Y63=1,L63<AsOf))),1,0) -> 0 | AM63: =IF(AL63=1,IF(Y63=0,AsOf-I63,AsOf-L63),"") | AN63: =IF(AL63=1,IF(Y63=0,"Delivery","Installation"),"") | AO63: =IF(AND(OR(fCat="All",F63=fCat),OR(fCust="All",D63=fCust),OR(fReg="All",E63=fReg)),1,0) -> 1 | AP63: =IF(AND(AL63=1,AO63=1),AM63+ROW()/100000,0) -> 0
A64: NHP-0063 | B64: 46115 | C64: CUST-1106 | D64: Commercial | E64: Rest of Karnataka | F64: Swimming Pool Heat Pump | G64: 1 | H64: 225000 | I64: 46131 | J64: 46131 | K64: 46135 | L64: 46134 | M64: 46148 | N64: Completed | O64: Production backlog | P64: Customer site not ready | R64: Electrical load checked | S64: OK | T64: 1 | U64: 1 | V64: 1 | W64: =DATE(YEAR(B64),MONTH(B64),1) -> 46113 | X64: =IF(AND(N64<>"Cancelled",I64<=AsOf),1,0) -> 1 | Y64: =IF(AND(N64<>"Cancelled",OR(ISNUMBER(K64),N64="Completed")),1,0) -> 1 | Z64: =IF(AND(Y64=1,U64=1,ISNUMBER(K64)),K64-I64,"") -> 4 | AA64: =IF(Z64="","",IF(Z64<0,"Early",IF(Z64=0,"On Time","Late"))) -> Late | AB64: =IF(AND(N64<>"Cancelled",L64<=AsOf),1,0) -> 1 | AC64: =IF(AND(N64<>"Cancelled",OR(ISNUMBER(M64),N64="Completed")),1,0) -> 1 | AD64: =IF(AND(AC64=1,V64=1,ISNUMBER(M64)),M64-L64,"") -> 14 | AE64: =IF(AD64="","",IF(AD64<0,"Early",IF(AD64=0,"On Time","Late"))) -> Late | AF64: =IF(AND(T64=1,ISNUMBER(J64),N64<>"Cancelled"),J64-B64,"") -> 16 | AG64: =IF(AND(AF64<>"",Z64<>""),K64-J64,"") -> 4 | AH64: =IF(AND(Z64<>"",AD64<>""),M64-K64,"") -> 13 | AI64: =IF(Z64<>"",K64-B64,"") -> 20 | AJ64: =IF(AND(N64="Completed",AD64<>""),M64-B64,"") -> 33 | AK64: =IF(N64="Cancelled","Cancelled",IF(N64="Completed","Completed",IF(Y64=1,"Awaiting Installation",IF(ISNUMBER(J64),"In Transit","In Production")))) -> Completed | AL64: =IF(AND(N64="Pending",OR(AND(Y64=0,I64<AsOf),AND(Y64=1,L64<AsOf))),1,0) -> 0 | AM64: =IF(AL64=1,IF(Y64=0,AsOf-I64,AsOf-L64),"") | AN64: =IF(AL64=1,IF(Y64=0,"Delivery","Installation"),"") | AO64: =IF(AND(OR(fCat="All",F64=fCat),OR(fCust="All",D64=fCust),OR(fReg="All",E64=fReg)),1,0) -> 1 | AP64: =IF(AND(AL64=1,AO64=1),AM64+ROW()/100000,0) -> 0
A65: NHP-0064 | B65: 46116 | C65: CUST-3591 | D65: Residential | E65: Bengaluru | F65: Heat Pump Water Heater | G65: 1 | H65: 208000 | I65: 46126 | J65: 46123 | K65: 46125 | L65: 46129 | M65: 46127 | N65: Completed | S65: OK | T65: 1 | U65: 1 | V65: 1 | W65: =DATE(YEAR(B65),MONTH(B65),1) -> 46113 | X65: =IF(AND(N65<>"Cancelled",I65<=AsOf),1,0) -> 1 | Y65: =IF(AND(N65<>"Cancelled",OR(ISNUMBER(K65),N65="Completed")),1,0) -> 1 | Z65: =IF(AND(Y65=1,U65=1,ISNUMBER(K65)),K65-I65,"") -> -1 | AA65: =IF(Z65="","",IF(Z65<0,"Early",IF(Z65=0,"On Time","Late"))) -> Early | AB65: =IF(AND(N65<>"Cancelled",L65<=AsOf),1,0) -> 1 | AC65: =IF(AND(N65<>"Cancelled",OR(ISNUMBER(M65),N65="Completed")),1,0) -> 1 | AD65: =IF(AND(AC65=1,V65=1,ISNUMBER(M65)),M65-L65,"") -> -2 | AE65: =IF(AD65="","",IF(AD65<0,"Early",IF(AD65=0,"On Time","Late"))) -> Early | AF65: =IF(AND(T65=1,ISNUMBER(J65),N65<>"Cancelled"),J65-B65,"") -> 7 | AG65: =IF(AND(AF65<>"",Z65<>""),K65-J65,"") -> 2 | AH65: =IF(AND(Z65<>"",AD65<>""),M65-K65,"") -> 2 | AI65: =IF(Z65<>"",K65-B65,"") -> 9 | AJ65: =IF(AND(N65="Completed",AD65<>""),M65-B65,"") -> 11 | AK65: =IF(N65="Cancelled","Cancelled",IF(N65="Completed","Completed",IF(Y65=1,"Awaiting Installation",IF(ISNUMBER(J65),"In Transit","In Production")))) -> Completed | AL65: =IF(AND(N65="Pending",OR(AND(Y65=0,I65<AsOf),AND(Y65=1,L65<AsOf))),1,0) -> 0 | AM65: =IF(AL65=1,IF(Y65=0,AsOf-I65,AsOf-L65),"") | AN65: =IF(AL65=1,IF(Y65=0,"Delivery","Installation"),"") | AO65: =IF(AND(OR(fCat="All",F65=fCat),OR(fCust="All",D65=fCust),OR(fReg="All",E65=fReg)),1,0) -> 1 | AP65: =IF(AND(AL65=1,AO65=1),AM65+ROW()/100000,0) -> 0
A66: NHP-0065 | B66: 46116 | C66: CUST-2876 | D66: Commercial | E66: Bengaluru | F66: Commercial Heat Pump | G66: 4 | H66: 1348000 | I66: 46134 | J66: 46130 | K66: 46131 | L66: 46139 | M66: 46172 | N66: Completed | P66: Customer site not ready | S66: OK | T66: 1 | U66: 1 | V66: 1 | W66: =DATE(YEAR(B66),MONTH(B66),1) -> 46113 | X66: =IF(AND(N66<>"Cancelled",I66<=AsOf),1,0) -> 1 | Y66: =IF(AND(N66<>"Cancelled",OR(ISNUMBER(K66),N66="Completed")),1,0) -> 1 | Z66: =IF(AND(Y66=1,U66=1,ISNUMBER(K66)),K66-I66,"") -> -3 | AA66: =IF(Z66="","",IF(Z66<0,"Early",IF(Z66=0,"On Time","Late"))) -> Early | AB66: =IF(AND(N66<>"Cancelled",L66<=AsOf),1,0) -> 1 | AC66: =IF(AND(N66<>"Cancelled",OR(ISNUMBER(M66),N66="Completed")),1,0) -> 1 | AD66: =IF(AND(AC66=1,V66=1,ISNUMBER(M66)),M66-L66,"") -> 33 | AE66: =IF(AD66="","",IF(AD66<0,"Early",IF(AD66=0,"On Time","Late"))) -> Late | AF66: =IF(AND(T66=1,ISNUMBER(J66),N66<>"Cancelled"),J66-B66,"") -> 14 | AG66: =IF(AND(AF66<>"",Z66<>""),K66-J66,"") -> 1 | AH66: =IF(AND(Z66<>"",AD66<>""),M66-K66,"") -> 41 | AI66: =IF(Z66<>"",K66-B66,"") -> 15 | AJ66: =IF(AND(N66="Completed",AD66<>""),M66-B66,"") -> 56 | AK66: =IF(N66="Cancelled","Cancelled",IF(N66="Completed","Completed",IF(Y66=1,"Awaiting Installation",IF(ISNUMBER(J66),"In Transit","In Production")))) -> Completed | AL66: =IF(AND(N66="Pending",OR(AND(Y66=0,I66<AsOf),AND(Y66=1,L66<AsOf))),1,0) -> 0 | AM66: =IF(AL66=1,IF(Y66=0,AsOf-I66,AsOf-L66),"") | AN66: =IF(AL66=1,IF(Y66=0,"Delivery","Installation"),"") | AO66: =IF(AND(OR(fCat="All",F66=fCat),OR(fCust="All",D66=fCust),OR(fReg="All",E66=fReg)),1,0) -> 1 | AP66: =IF(AND(AL66=1,AO66=1),AM66+ROW()/100000,0) -> 0
A67: NHP-0066 | B67: 46117 | C67: CUST-3677 | D67: Institutional | E67: Bengaluru | F67: Commercial Heat Pump | G67: 4 | H67: 1476000 | I67: 46135 | J67: 46135 | K67: 46136 | L67: 46140 | M67: 46139 | N67: Completed | O67: Production backlog | S67: OK | T67: 1 | U67: 1 | V67: 1 | W67: =DATE(YEAR(B67),MONTH(B67),1) -> 46113 | X67: =IF(AND(N67<>"Cancelled",I67<=AsOf),1,0) -> 1 | Y67: =IF(AND(N67<>"Cancelled",OR(ISNUMBER(K67),N67="Completed")),1,0) -> 1 | Z67: =IF(AND(Y67=1,U67=1,ISNUMBER(K67)),K67-I67,"") -> 1 | AA67: =IF(Z67="","",IF(Z67<0,"Early",IF(Z67=0,"On Time","Late"))) -> Late | AB67: =IF(AND(N67<>"Cancelled",L67<=AsOf),1,0) -> 1 | AC67: =IF(AND(N67<>"Cancelled",OR(ISNUMBER(M67),N67="Completed")),1,0) -> 1 | AD67: =IF(AND(AC67=1,V67=1,ISNUMBER(M67)),M67-L67,"") -> -1 | AE67: =IF(AD67="","",IF(AD67<0,"Early",IF(AD67=0,"On Time","Late"))) -> Early | AF67: =IF(AND(T67=1,ISNUMBER(J67),N67<>"Cancelled"),J67-B67,"") -> 18 | AG67: =IF(AND(AF67<>"",Z67<>""),K67-J67,"") -> 1 | AH67: =IF(AND(Z67<>"",AD67<>""),M67-K67,"") -> 3 | AI67: =IF(Z67<>"",K67-B67,"") -> 19 | AJ67: =IF(AND(N67="Completed",AD67<>""),M67-B67,"") -> 22 | AK67: =IF(N67="Cancelled","Cancelled",IF(N67="Completed","Completed",IF(Y67=1,"Awaiting Installation",IF(ISNUMBER(J67),"In Transit","In Production")))) -> Completed | AL67: =IF(AND(N67="Pending",OR(AND(Y67=0,I67<AsOf),AND(Y67=1,L67<AsOf))),1,0) -> 0 | AM67: =IF(AL67=1,IF(Y67=0,AsOf-I67,AsOf-L67),"") | AN67: =IF(AL67=1,IF(Y67=0,"Delivery","Installation"),"") | AO67: =IF(AND(OR(fCat="All",F67=fCat),OR(fCust="All",D67=fCust),OR(fReg="All",E67=fReg)),1,0) -> 1 | AP67: =IF(AND(AL67=1,AO67=1),AM67+ROW()/100000,0) -> 0
A68: NHP-0067 | B68: 46117 | C68: CUST-5554 | D68: Commercial | E68: Other States | F68: Commercial Heat Pump | G68: 2 | H68: 1190000 | I68: 46139 | J68: 46131 | K68: 46138 | L68: 46144 | M68: 46143 | N68: Completed | R68: Pipe routing confirmed | S68: OK | T68: 1 | U68: 1 | V68: 1 | W68: =DATE(YEAR(B68),MONTH(B68),1) -> 46113 | X68: =IF(AND(N68<>"Cancelled",I68<=AsOf),1,0) -> 1 | Y68: =IF(AND(N68<>"Cancelled",OR(ISNUMBER(K68),N68="Completed")),1,0) -> 1 | Z68: =IF(AND(Y68=1,U68=1,ISNUMBER(K68)),K68-I68,"") -> -1 | AA68: =IF(Z68="","",IF(Z68<0,"Early",IF(Z68=0,"On Time","Late"))) -> Early | AB68: =IF(AND(N68<>"Cancelled",L68<=AsOf),1,0) -> 1 | AC68: =IF(AND(N68<>"Cancelled",OR(ISNUMBER(M68),N68="Completed")),1,0) -> 1 | AD68: =IF(AND(AC68=1,V68=1,ISNUMBER(M68)),M68-L68,"") -> -1 | AE68: =IF(AD68="","",IF(AD68<0,"Early",IF(AD68=0,"On Time","Late"))) -> Early | AF68: =IF(AND(T68=1,ISNUMBER(J68),N68<>"Cancelled"),J68-B68,"") -> 14 | AG68: =IF(AND(AF68<>"",Z68<>""),K68-J68,"") -> 7 | AH68: =IF(AND(Z68<>"",AD68<>""),M68-K68,"") -> 5 | AI68: =IF(Z68<>"",K68-B68,"") -> 21 | AJ68: =IF(AND(N68="Completed",AD68<>""),M68-B68,"") -> 26 | AK68: =IF(N68="Cancelled","Cancelled",IF(N68="Completed","Completed",IF(Y68=1,"Awaiting Installation",IF(ISNUMBER(J68),"In Transit","In Production")))) -> Completed | AL68: =IF(AND(N68="Pending",OR(AND(Y68=0,I68<AsOf),AND(Y68=1,L68<AsOf))),1,0) -> 0 | AM68: =IF(AL68=1,IF(Y68=0,AsOf-I68,AsOf-L68),"") | AN68: =IF(AL68=1,IF(Y68=0,"Delivery","Installation"),"") | AO68: =IF(AND(OR(fCat="All",F68=fCat),OR(fCust="All",D68=fCust),OR(fReg="All",E68=fReg)),1,0) -> 1 | AP68: =IF(AND(AL68=1,AO68=1),AM68+ROW()/100000,0) -> 0
A69: NHP-0068 | B69: 46120 | C69: CUST-1520 | D69: Residential | E69: Bengaluru | F69: Heat Pump Water Heater | G69: 1 | H69: 213000 | I69: 46130 | J69: 46123 | L69: 46133 | N69: Cancelled | Q69: Price / budget | S69: OK | T69: 1 | U69: 1 | V69: 1 | W69: =DATE(YEAR(B69),MONTH(B69),1) -> 46113 | X69: =IF(AND(N69<>"Cancelled",I69<=AsOf),1,0) -> 0 | Y69: =IF(AND(N69<>"Cancelled",OR(ISNUMBER(K69),N69="Completed")),1,0) -> 0 | Z69: =IF(AND(Y69=1,U69=1,ISNUMBER(K69)),K69-I69,"") | AA69: =IF(Z69="","",IF(Z69<0,"Early",IF(Z69=0,"On Time","Late"))) | AB69: =IF(AND(N69<>"Cancelled",L69<=AsOf),1,0) -> 0 | AC69: =IF(AND(N69<>"Cancelled",OR(ISNUMBER(M69),N69="Completed")),1,0) -> 0 | AD69: =IF(AND(AC69=1,V69=1,ISNUMBER(M69)),M69-L69,"") | AE69: =IF(AD69="","",IF(AD69<0,"Early",IF(AD69=0,"On Time","Late"))) | AF69: =IF(AND(T69=1,ISNUMBER(J69),N69<>"Cancelled"),J69-B69,"") | AG69: =IF(AND(AF69<>"",Z69<>""),K69-J69,"") | AH69: =IF(AND(Z69<>"",AD69<>""),M69-K69,"") | AI69: =IF(Z69<>"",K69-B69,"") | AJ69: =IF(AND(N69="Completed",AD69<>""),M69-B69,"") | AK69: =IF(N69="Cancelled","Cancelled",IF(N69="Completed","Completed",IF(Y69=1,"Awaiting Installation",IF(ISNUMBER(J69),"In Transit","In Production")))) -> Cancelled | AL69: =IF(AND(N69="Pending",OR(AND(Y69=0,I69<AsOf),AND(Y69=1,L69<AsOf))),1,0) -> 0 | AM69: =IF(AL69=1,IF(Y69=0,AsOf-I69,AsOf-L69),"") | AN69: =IF(AL69=1,IF(Y69=0,"Delivery","Installation"),"") | AO69: =IF(AND(OR(fCat="All",F69=fCat),OR(fCust="All",D69=fCust),OR(fReg="All",E69=fReg)),1,0) -> 1 | AP69: =IF(AND(AL69=1,AO69=1),AM69+ROW()/100000,0) -> 0
A70: NHP-0069 | B70: 46120 | C70: CUST-6635 | D70: Residential | E70: Other States | F70: Heat Pump Water Heater | G70: 1 | H70: 175000 | I70: 46134 | J70: 46128 | K70: 46136 | L70: 46137 | N70: Pending | P70: Customer site not ready | R70: Customer civil work in progress | S70: OK | T70: 1 | U70: 1 | V70: 1 | W70: =DATE(YEAR(B70),MONTH(B70),1) -> 46113 | X70: =IF(AND(N70<>"Cancelled",I70<=AsOf),1,0) -> 1 | Y70: =IF(AND(N70<>"Cancelled",OR(ISNUMBER(K70),N70="Completed")),1,0) -> 1 | Z70: =IF(AND(Y70=1,U70=1,ISNUMBER(K70)),K70-I70,"") -> 2 | AA70: =IF(Z70="","",IF(Z70<0,"Early",IF(Z70=0,"On Time","Late"))) -> Late | AB70: =IF(AND(N70<>"Cancelled",L70<=AsOf),1,0) -> 1 | AC70: =IF(AND(N70<>"Cancelled",OR(ISNUMBER(M70),N70="Completed")),1,0) -> 0 | AD70: =IF(AND(AC70=1,V70=1,ISNUMBER(M70)),M70-L70,"") | AE70: =IF(AD70="","",IF(AD70<0,"Early",IF(AD70=0,"On Time","Late"))) | AF70: =IF(AND(T70=1,ISNUMBER(J70),N70<>"Cancelled"),J70-B70,"") -> 8 | AG70: =IF(AND(AF70<>"",Z70<>""),K70-J70,"") -> 8 | AH70: =IF(AND(Z70<>"",AD70<>""),M70-K70,"") | AI70: =IF(Z70<>"",K70-B70,"") -> 16 | AJ70: =IF(AND(N70="Completed",AD70<>""),M70-B70,"") | AK70: =IF(N70="Cancelled","Cancelled",IF(N70="Completed","Completed",IF(Y70=1,"Awaiting Installation",IF(ISNUMBER(J70),"In Transit","In Production")))) -> Awaiting Installation | AL70: =IF(AND(N70="Pending",OR(AND(Y70=0,I70<AsOf),AND(Y70=1,L70<AsOf))),1,0) -> 1 | AM70: =IF(AL70=1,IF(Y70=0,AsOf-I70,AsOf-L70),"") -> 66 | AN70: =IF(AL70=1,IF(Y70=0,"Delivery","Installation"),"") -> Installation | AO70: =IF(AND(OR(fCat="All",F70=fCat),OR(fCust="All",D70=fCust),OR(fReg="All",E70=fReg)),1,0) -> 1 | AP70: =IF(AND(AL70=1,AO70=1),AM70+ROW()/100000,0) -> 66.0007
A71: NHP-0070 | B71: 46121 | C71: CUST-2674 | D71: Institutional | E71: Rest of Karnataka | F71: Commercial Heat Pump | G71: 1 | H71: 433000 | I71: 46141 | J71: 46132 | K71: 46135 | L71: 46146 | M71: 46145 | N71: Completed | R71: Site survey done | S71: OK | T71: 1 | U71: 1 | V71: 1 | W71: =DATE(YEAR(B71),MONTH(B71),1) -> 46113 | X71: =IF(AND(N71<>"Cancelled",I71<=AsOf),1,0) -> 1 | Y71: =IF(AND(N71<>"Cancelled",OR(ISNUMBER(K71),N71="Completed")),1,0) -> 1 | Z71: =IF(AND(Y71=1,U71=1,ISNUMBER(K71)),K71-I71,"") -> -6 | AA71: =IF(Z71="","",IF(Z71<0,"Early",IF(Z71=0,"On Time","Late"))) -> Early | AB71: =IF(AND(N71<>"Cancelled",L71<=AsOf),1,0) -> 1 | AC71: =IF(AND(N71<>"Cancelled",OR(ISNUMBER(M71),N71="Completed")),1,0) -> 1 | AD71: =IF(AND(AC71=1,V71=1,ISNUMBER(M71)),M71-L71,"") -> -1 | AE71: =IF(AD71="","",IF(AD71<0,"Early",IF(AD71=0,"On Time","Late"))) -> Early | AF71: =IF(AND(T71=1,ISNUMBER(J71),N71<>"Cancelled"),J71-B71,"") -> 11 | AG71: =IF(AND(AF71<>"",Z71<>""),K71-J71,"") -> 3 | AH71: =IF(AND(Z71<>"",AD71<>""),M71-K71,"") -> 10 | AI71: =IF(Z71<>"",K71-B71,"") -> 14 | AJ71: =IF(AND(N71="Completed",AD71<>""),M71-B71,"") -> 24 | AK71: =IF(N71="Cancelled","Cancelled",IF(N71="Completed","Completed",IF(Y71=1,"Awaiting Installation",IF(ISNUMBER(J71),"In Transit","In Production")))) -> Completed | AL71: =IF(AND(N71="Pending",OR(AND(Y71=0,I71<AsOf),AND(Y71=1,L71<AsOf))),1,0) -> 0 | AM71: =IF(AL71=1,IF(Y71=0,AsOf-I71,AsOf-L71),"") | AN71: =IF(AL71=1,IF(Y71=0,"Delivery","Installation"),"") | AO71: =IF(AND(OR(fCat="All",F71=fCat),OR(fCust="All",D71=fCust),OR(fReg="All",E71=fReg)),1,0) -> 1 | AP71: =IF(AND(AL71=1,AO71=1),AM71+ROW()/100000,0) -> 0
A72: NHP-0071 | B72: 46124 | C72: CUST-4257 | D72: Commercial | E72: Bengaluru | F72: Heat Pump Water Heater | G72: 1 | H72: 147000 | I72: 46134 | J72: 46134 | K72: 46135 | L72: 46137 | M72: 46136 | N72: Completed | R72: Replacement of old geyser | S72: OK | T72: 1 | U72: 1 | V72: 1 | W72: =DATE(YEAR(B72),MONTH(B72),1) -> 46113 | X72: =IF(AND(N72<>"Cancelled",I72<=AsOf),1,0) -> 1 | Y72: =IF(AND(N72<>"Cancelled",OR(ISNUMBER(K72),N72="Completed")),1,0) -> 1 | Z72: =IF(AND(Y72=1,U72=1,ISNUMBER(K72)),K72-I72,"") -> 1 | AA72: =IF(Z72="","",IF(Z72<0,"Early",IF(Z72=0,"On Time","Late"))) -> Late | AB72: =IF(AND(N72<>"Cancelled",L72<=AsOf),1,0) -> 1 | AC72: =IF(AND(N72<>"Cancelled",OR(ISNUMBER(M72),N72="Completed")),1,0) -> 1 | AD72: =IF(AND(AC72=1,V72=1,ISNUMBER(M72)),M72-L72,"") -> -1 | AE72: =IF(AD72="","",IF(AD72<0,"Early",IF(AD72=0,"On Time","Late"))) -> Early | AF72: =IF(AND(T72=1,ISNUMBER(J72),N72<>"Cancelled"),J72-B72,"") -> 10 | AG72: =IF(AND(AF72<>"",Z72<>""),K72-J72,"") -> 1 | AH72: =IF(AND(Z72<>"",AD72<>""),M72-K72,"") -> 1 | AI72: =IF(Z72<>"",K72-B72,"") -> 11 | AJ72: =IF(AND(N72="Completed",AD72<>""),M72-B72,"") -> 12 | AK72: =IF(N72="Cancelled","Cancelled",IF(N72="Completed","Completed",IF(Y72=1,"Awaiting Installation",IF(ISNUMBER(J72),"In Transit","In Production")))) -> Completed | AL72: =IF(AND(N72="Pending",OR(AND(Y72=0,I72<AsOf),AND(Y72=1,L72<AsOf))),1,0) -> 0 | AM72: =IF(AL72=1,IF(Y72=0,AsOf-I72,AsOf-L72),"") | AN72: =IF(AL72=1,IF(Y72=0,"Delivery","Installation"),"") | AO72: =IF(AND(OR(fCat="All",F72=fCat),OR(fCust="All",D72=fCust),OR(fReg="All",E72=fReg)),1,0) -> 1 | AP72: =IF(AND(AL72=1,AO72=1),AM72+ROW()/100000,0) -> 0
A73: NHP-0072 | B73: 46124 | C73: CUST-6925 | D73: Commercial | E73: Bengaluru | F73: Commercial Heat Pump | G73: 2 | H73: 1284000 | I73: 46142 | J73: 46142 | K73: 46143 | L73: 46147 | M73: 46147 | N73: Completed | R73: Replacement of old geyser | S73: OK | T73: 1 | U73: 1 | V73: 1 | W73: =DATE(YEAR(B73),MONTH(B73),1) -> 46113 | X73: =IF(AND(N73<>"Cancelled",I73<=AsOf),1,0) -> 1 | Y73: =IF(AND(N73<>"Cancelled",OR(ISNUMBER(K73),N73="Completed")),1,0) -> 1 | Z73: =IF(AND(Y73=1,U73=1,ISNUMBER(K73)),K73-I73,"") -> 1 | AA73: =IF(Z73="","",IF(Z73<0,"Early",IF(Z73=0,"On Time","Late"))) -> Late | AB73: =IF(AND(N73<>"Cancelled",L73<=AsOf),1,0) -> 1 | AC73: =IF(AND(N73<>"Cancelled",OR(ISNUMBER(M73),N73="Completed")),1,0) -> 1 | AD73: =IF(AND(AC73=1,V73=1,ISNUMBER(M73)),M73-L73,"") -> 0 | AE73: =IF(AD73="","",IF(AD73<0,"Early",IF(AD73=0,"On Time","Late"))) -> On Time | AF73: =IF(AND(T73=1,ISNUMBER(J73),N73<>"Cancelled"),J73-B73,"") -> 18 | AG73: =IF(AND(AF73<>"",Z73<>""),K73-J73,"") -> 1 | AH73: =IF(AND(Z73<>"",AD73<>""),M73-K73,"") -> 4 | AI73: =IF(Z73<>"",K73-B73,"") -> 19 | AJ73: =IF(AND(N73="Completed",AD73<>""),M73-B73,"") -> 23 | AK73: =IF(N73="Cancelled","Cancelled",IF(N73="Completed","Completed",IF(Y73=1,"Awaiting Installation",IF(ISNUMBER(J73),"In Transit","In Production")))) -> Completed | AL73: =IF(AND(N73="Pending",OR(AND(Y73=0,I73<AsOf),AND(Y73=1,L73<AsOf))),1,0) -> 0 | AM73: =IF(AL73=1,IF(Y73=0,AsOf-I73,AsOf-L73),"") | AN73: =IF(AL73=1,IF(Y73=0,"Delivery","Installation"),"") | AO73: =IF(AND(OR(fCat="All",F73=fCat),OR(fCust="All",D73=fCust),OR(fReg="All",E73=fReg)),1,0) -> 1 | AP73: =IF(AND(AL73=1,AO73=1),AM73+ROW()/100000,0) -> 0
A74: NHP-0073 | B74: 46126 | C74: CUST-6514 | D74: Institutional | E74: Bengaluru | F74: Commercial Heat Pump | G74: 2 | H74: 692000 | I74: 46144 | J74: 46142 | K74: 46144 | L74: 46149 | M74: 46147 | N74: Completed | R74: Customer requested weekend install | S74: OK | T74: 1 | U74: 1 | V74: 1 | W74: =DATE(YEAR(B74),MONTH(B74),1) -> 46113 | X74: =IF(AND(N74<>"Cancelled",I74<=AsOf),1,0) -> 1 | Y74: =IF(AND(N74<>"Cancelled",OR(ISNUMBER(K74),N74="Completed")),1,0) -> 1 | Z74: =IF(AND(Y74=1,U74=1,ISNUMBER(K74)),K74-I74,"") -> 0 | AA74: =IF(Z74="","",IF(Z74<0,"Early",IF(Z74=0,"On Time","Late"))) -> On Time | AB74: =IF(AND(N74<>"Cancelled",L74<=AsOf),1,0) -> 1 | AC74: =IF(AND(N74<>"Cancelled",OR(ISNUMBER(M74),N74="Completed")),1,0) -> 1 | AD74: =IF(AND(AC74=1,V74=1,ISNUMBER(M74)),M74-L74,"") -> -2 | AE74: =IF(AD74="","",IF(AD74<0,"Early",IF(AD74=0,"On Time","Late"))) -> Early | AF74: =IF(AND(T74=1,ISNUMBER(J74),N74<>"Cancelled"),J74-B74,"") -> 16 | AG74: =IF(AND(AF74<>"",Z74<>""),K74-J74,"") -> 2 | AH74: =IF(AND(Z74<>"",AD74<>""),M74-K74,"") -> 3 | AI74: =IF(Z74<>"",K74-B74,"") -> 18 | AJ74: =IF(AND(N74="Completed",AD74<>""),M74-B74,"") -> 21 | AK74: =IF(N74="Cancelled","Cancelled",IF(N74="Completed","Completed",IF(Y74=1,"Awaiting Installation",IF(ISNUMBER(J74),"In Transit","In Production")))) -> Completed | AL74: =IF(AND(N74="Pending",OR(AND(Y74=0,I74<AsOf),AND(Y74=1,L74<AsOf))),1,0) -> 0 | AM74: =IF(AL74=1,IF(Y74=0,AsOf-I74,AsOf-L74),"") | AN74: =IF(AL74=1,IF(Y74=0,"Delivery","Installation"),"") | AO74: =IF(AND(OR(fCat="All",F74=fCat),OR(fCust="All",D74=fCust),OR(fReg="All",E74=fReg)),1,0) -> 1 | AP74: =IF(AND(AL74=1,AO74=1),AM74+ROW()/100000,0) -> 0
A75: NHP-0074 | B75: 46127 | C75: CUST-7216 | D75: Residential | E75: Bengaluru | F75: Swimming Pool Heat Pump | G75: 1 | H75: 597000 | I75: 46141 | J75: 46134 | K75: 46135 | L75: 46144 | M75: 46138 | N75: Completed | R75: Customer requested weekend install | S75: OK | T75: 1 | U75: 1 | V75: 1 | W75: =DATE(YEAR(B75),MONTH(B75),1) -> 46113 | X75: =IF(AND(N75<>"Cancelled",I75<=AsOf),1,0) -> 1 | Y75: =IF(AND(N75<>"Cancelled",OR(ISNUMBER(K75),N75="Completed")),1,0) -> 1 | Z75: =IF(AND(Y75=1,U75=1,ISNUMBER(K75)),K75-I75,"") -> -6 | AA75: =IF(Z75="","",IF(Z75<0,"Early",IF(Z75=0,"On Time","Late"))) -> Early | AB75: =IF(AND(N75<>"Cancelled",L75<=AsOf),1,0) -> 1 | AC75: =IF(AND(N75<>"Cancelled",OR(ISNUMBER(M75),N75="Completed")),1,0) -> 1 | AD75: =IF(AND(AC75=1,V75=1,ISNUMBER(M75)),M75-L75,"") -> -6 | AE75: =IF(AD75="","",IF(AD75<0,"Early",IF(AD75=0,"On Time","Late"))) -> Early | AF75: =IF(AND(T75=1,ISNUMBER(J75),N75<>"Cancelled"),J75-B75,"") -> 7 | AG75: =IF(AND(AF75<>"",Z75<>""),K75-J75,"") -> 1 | AH75: =IF(AND(Z75<>"",AD75<>""),M75-K75,"") -> 3 | AI75: =IF(Z75<>"",K75-B75,"") -> 8 | AJ75: =IF(AND(N75="Completed",AD75<>""),M75-B75,"") -> 11 | AK75: =IF(N75="Cancelled","Cancelled",IF(N75="Completed","Completed",IF(Y75=1,"Awaiting Installation",IF(ISNUMBER(J75),"In Transit","In Production")))) -> Completed | AL75: =IF(AND(N75="Pending",OR(AND(Y75=0,I75<AsOf),AND(Y75=1,L75<AsOf))),1,0) -> 0 | AM75: =IF(AL75=1,IF(Y75=0,AsOf-I75,AsOf-L75),"") | AN75: =IF(AL75=1,IF(Y75=0,"Delivery","Installation"),"") | AO75: =IF(AND(OR(fCat="All",F75=fCat),OR(fCust="All",D75=fCust),OR(fReg="All",E75=fReg)),1,0) -> 1 | AP75: =IF(AND(AL75=1,AO75=1),AM75+ROW()/100000,0) -> 0
A76: NHP-0075 | B76: 46127 | C76: CUST-7224 | D76: Residential | E76: Bengaluru | F76: Swimming Pool Heat Pump | G76: 1 | I76: 46141 | J76: 46136 | K76: 46138 | L76: 46144 | M76: 46140 | N76: Completed | S76: Order value missing | T76: 1 | U76: 1 | V76: 1 | W76: =DATE(YEAR(B76),MONTH(B76),1) -> 46113 | X76: =IF(AND(N76<>"Cancelled",I76<=AsOf),1,0) -> 1 | Y76: =IF(AND(N76<>"Cancelled",OR(ISNUMBER(K76),N76="Completed")),1,0) -> 1 | Z76: =IF(AND(Y76=1,U76=1,ISNUMBER(K76)),K76-I76,"") -> -3 | AA76: =IF(Z76="","",IF(Z76<0,"Early",IF(Z76=0,"On Time","Late"))) -> Early | AB76: =IF(AND(N76<>"Cancelled",L76<=AsOf),1,0) -> 1 | AC76: =IF(AND(N76<>"Cancelled",OR(ISNUMBER(M76),N76="Completed")),1,0) -> 1 | AD76: =IF(AND(AC76=1,V76=1,ISNUMBER(M76)),M76-L76,"") -> -4 | AE76: =IF(AD76="","",IF(AD76<0,"Early",IF(AD76=0,"On Time","Late"))) -> Early | AF76: =IF(AND(T76=1,ISNUMBER(J76),N76<>"Cancelled"),J76-B76,"") -> 9 | AG76: =IF(AND(AF76<>"",Z76<>""),K76-J76,"") -> 2 | AH76: =IF(AND(Z76<>"",AD76<>""),M76-K76,"") -> 2 | AI76: =IF(Z76<>"",K76-B76,"") -> 11 | AJ76: =IF(AND(N76="Completed",AD76<>""),M76-B76,"") -> 13 | AK76: =IF(N76="Cancelled","Cancelled",IF(N76="Completed","Completed",IF(Y76=1,"Awaiting Installation",IF(ISNUMBER(J76),"In Transit","In Production")))) -> Completed | AL76: =IF(AND(N76="Pending",OR(AND(Y76=0,I76<AsOf),AND(Y76=1,L76<AsOf))),1,0) -> 0 | AM76: =IF(AL76=1,IF(Y76=0,AsOf-I76,AsOf-L76),"") | AN76: =IF(AL76=1,IF(Y76=0,"Delivery","Installation"),"") | AO76: =IF(AND(OR(fCat="All",F76=fCat),OR(fCust="All",D76=fCust),OR(fReg="All",E76=fReg)),1,0) -> 1 | AP76: =IF(AND(AL76=1,AO76=1),AM76+ROW()/100000,0) -> 0
A77: NHP-0076 | B77: 46132 | C77: CUST-4752 | D77: Commercial | E77: Other States | F77: Commercial Heat Pump | G77: 2 | H77: 708000 | I77: 46154 | J77: 46150 | K77: 46162 | L77: 46159 | N77: Pending | O77: Transport scheduling | P77: Customer site not ready | R77: Customer civil work in progress | S77: OK | T77: 1 | U77: 1 | V77: 1 | W77: =DATE(YEAR(B77),MONTH(B77),1) -> 46113 | X77: =IF(AND(N77<>"Cancelled",I77<=AsOf),1,0) -> 1 | Y77: =IF(AND(N77<>"Cancelled",OR(ISNUMBER(K77),N77="Completed")),1,0) -> 1 | Z77: =IF(AND(Y77=1,U77=1,ISNUMBER(K77)),K77-I77,"") -> 8 | AA77: =IF(Z77="","",IF(Z77<0,"Early",IF(Z77=0,"On Time","Late"))) -> Late | AB77: =IF(AND(N77<>"Cancelled",L77<=AsOf),1,0) -> 1 | AC77: =IF(AND(N77<>"Cancelled",OR(ISNUMBER(M77),N77="Completed")),1,0) -> 0 | AD77: =IF(AND(AC77=1,V77=1,ISNUMBER(M77)),M77-L77,"") | AE77: =IF(AD77="","",IF(AD77<0,"Early",IF(AD77=0,"On Time","Late"))) | AF77: =IF(AND(T77=1,ISNUMBER(J77),N77<>"Cancelled"),J77-B77,"") -> 18 | AG77: =IF(AND(AF77<>"",Z77<>""),K77-J77,"") -> 12 | AH77: =IF(AND(Z77<>"",AD77<>""),M77-K77,"") | AI77: =IF(Z77<>"",K77-B77,"") -> 30 | AJ77: =IF(AND(N77="Completed",AD77<>""),M77-B77,"") | AK77: =IF(N77="Cancelled","Cancelled",IF(N77="Completed","Completed",IF(Y77=1,"Awaiting Installation",IF(ISNUMBER(J77),"In Transit","In Production")))) -> Awaiting Installation | AL77: =IF(AND(N77="Pending",OR(AND(Y77=0,I77<AsOf),AND(Y77=1,L77<AsOf))),1,0) -> 1 | AM77: =IF(AL77=1,IF(Y77=0,AsOf-I77,AsOf-L77),"") -> 44 | AN77: =IF(AL77=1,IF(Y77=0,"Delivery","Installation"),"") -> Installation | AO77: =IF(AND(OR(fCat="All",F77=fCat),OR(fCust="All",D77=fCust),OR(fReg="All",E77=fReg)),1,0) -> 1 | AP77: =IF(AND(AL77=1,AO77=1),AM77+ROW()/100000,0) -> 44.00077
A78: NHP-0077 | B78: 46132 | C78: CUST-1188 | D78: Commercial | E78: Bengaluru | F78: Commercial Heat Pump | G78: 3 | H78: 2628000 | I78: 46150 | J78: 46153 | K78: 46155 | L78: 46155 | M78: 46158 | N78: Completed | O78: Production backlog | P78: Knock-on from late delivery | S78: OK | T78: 1 | U78: 1 | V78: 1 | W78: =DATE(YEAR(B78),MONTH(B78),1) -> 46113 | X78: =IF(AND(N78<>"Cancelled",I78<=AsOf),1,0) -> 1 | Y78: =IF(AND(N78<>"Cancelled",OR(ISNUMBER(K78),N78="Completed")),1,0) -> 1 | Z78: =IF(AND(Y78=1,U78=1,ISNUMBER(K78)),K78-I78,"") -> 5 | AA78: =IF(Z78="","",IF(Z78<0,"Early",IF(Z78=0,"On Time","Late"))) -> Late | AB78: =IF(AND(N78<>"Cancelled",L78<=AsOf),1,0) -> 1 | AC78: =IF(AND(N78<>"Cancelled",OR(ISNUMBER(M78),N78="Completed")),1,0) -> 1 | AD78: =IF(AND(AC78=1,V78=1,ISNUMBER(M78)),M78-L78,"") -> 3 | AE78: =IF(AD78="","",IF(AD78<0,"Early",IF(AD78=0,"On Time","Late"))) -> Late | AF78: =IF(AND(T78=1,ISNUMBER(J78),N78<>"Cancelled"),J78-B78,"") -> 21 | AG78: =IF(AND(AF78<>"",Z78<>""),K78-J78,"") -> 2 | AH78: =IF(AND(Z78<>"",AD78<>""),M78-K78,"") -> 3 | AI78: =IF(Z78<>"",K78-B78,"") -> 23 | AJ78: =IF(AND(N78="Completed",AD78<>""),M78-B78,"") -> 26 | AK78: =IF(N78="Cancelled","Cancelled",IF(N78="Completed","Completed",IF(Y78=1,"Awaiting Installation",IF(ISNUMBER(J78),"In Transit","In Production")))) -> Completed | AL78: =IF(AND(N78="Pending",OR(AND(Y78=0,I78<AsOf),AND(Y78=1,L78<AsOf))),1,0) -> 0 | AM78: =IF(AL78=1,IF(Y78=0,AsOf-I78,AsOf-L78),"") | AN78: =IF(AL78=1,IF(Y78=0,"Delivery","Installation"),"") | AO78: =IF(AND(OR(fCat="All",F78=fCat),OR(fCust="All",D78=fCust),OR(fReg="All",E78=fReg)),1,0) -> 1 | AP78: =IF(AND(AL78=1,AO78=1),AM78+ROW()/100000,0) -> 0
A79: NHP-0078 | B79: 46132 | C79: CUST-4432 | D79: Commercial | E79: Rest of Karnataka | F79: Commercial Heat Pump | G79: 1 | H79: 1175000 | I79: 46152 | J79: 46159 | K79: 46163 | L79: 46157 | M79: 46167 | N79: Completed | O79: Production backlog | R79: Electrical load checked | S79: OK | T79: 1 | U79: 1 | V79: 1 | W79: =DATE(YEAR(B79),MONTH(B79),1) -> 46113 | X79: =IF(AND(N79<>"Cancelled",I79<=AsOf),1,0) -> 1 | Y79: =IF(AND(N79<>"Cancelled",OR(ISNUMBER(K79),N79="Completed")),1,0) -> 1 | Z79: =IF(AND(Y79=1,U79=1,ISNUMBER(K79)),K79-I79,"") -> 11 | AA79: =IF(Z79="","",IF(Z79<0,"Early",IF(Z79=0,"On Time","Late"))) -> Late | AB79: =IF(AND(N79<>"Cancelled",L79<=AsOf),1,0) -> 1 | AC79: =IF(AND(N79<>"Cancelled",OR(ISNUMBER(M79),N79="Completed")),1,0) -> 1 | AD79: =IF(AND(AC79=1,V79=1,ISNUMBER(M79)),M79-L79,"") -> 10 | AE79: =IF(AD79="","",IF(AD79<0,"Early",IF(AD79=0,"On Time","Late"))) -> Late | AF79: =IF(AND(T79=1,ISNUMBER(J79),N79<>"Cancelled"),J79-B79,"") -> 27 | AG79: =IF(AND(AF79<>"",Z79<>""),K79-J79,"") -> 4 | AH79: =IF(AND(Z79<>"",AD79<>""),M79-K79,"") -> 4 | AI79: =IF(Z79<>"",K79-B79,"") -> 31 | AJ79: =IF(AND(N79="Completed",AD79<>""),M79-B79,"") -> 35 | AK79: =IF(N79="Cancelled","Cancelled",IF(N79="Completed","Completed",IF(Y79=1,"Awaiting Installation",IF(ISNUMBER(J79),"In Transit","In Production")))) -> Completed | AL79: =IF(AND(N79="Pending",OR(AND(Y79=0,I79<AsOf),AND(Y79=1,L79<AsOf))),1,0) -> 0 | AM79: =IF(AL79=1,IF(Y79=0,AsOf-I79,AsOf-L79),"") | AN79: =IF(AL79=1,IF(Y79=0,"Delivery","Installation"),"") | AO79: =IF(AND(OR(fCat="All",F79=fCat),OR(fCust="All",D79=fCust),OR(fReg="All",E79=fReg)),1,0) -> 1 | AP79: =IF(AND(AL79=1,AO79=1),AM79+ROW()/100000,0) -> 0
A80: NHP-0079 | B80: 46134 | C80: CUST-2519 | D80: Commercial | E80: Bengaluru | F80: Custom Requirement | G80: 1 | H80: 801000 | I80: 46164 | J80: 46171 | K80: 46172 | L80: 46169 | M80: 46177 | N80: Completed | O80: Component shortage | P80: Knock-on from late delivery | R80: Customer requested weekend install | S80: OK | T80: 1 | U80: 1 | V80: 1 | W80: =DATE(YEAR(B80),MONTH(B80),1) -> 46113 | X80: =IF(AND(N80<>"Cancelled",I80<=AsOf),1,0) -> 1 | Y80: =IF(AND(N80<>"Cancelled",OR(ISNUMBER(K80),N80="Completed")),1,0) -> 1 | Z80: =IF(AND(Y80=1,U80=1,ISNUMBER(K80)),K80-I80,"") -> 8 | AA80: =IF(Z80="","",IF(Z80<0,"Early",IF(Z80=0,"On Time","Late"))) -> Late | AB80: =IF(AND(N80<>"Cancelled",L80<=AsOf),1,0) -> 1 | AC80: =IF(AND(N80<>"Cancelled",OR(ISNUMBER(M80),N80="Completed")),1,0) -> 1 | AD80: =IF(AND(AC80=1,V80=1,ISNUMBER(M80)),M80-L80,"") -> 8 | AE80: =IF(AD80="","",IF(AD80<0,"Early",IF(AD80=0,"On Time","Late"))) -> Late | AF80: =IF(AND(T80=1,ISNUMBER(J80),N80<>"Cancelled"),J80-B80,"") -> 37 | AG80: =IF(AND(AF80<>"",Z80<>""),K80-J80,"") -> 1 | AH80: =IF(AND(Z80<>"",AD80<>""),M80-K80,"") -> 5 | AI80: =IF(Z80<>"",K80-B80,"") -> 38 | AJ80: =IF(AND(N80="Completed",AD80<>""),M80-B80,"") -> 43 | AK80: =IF(N80="Cancelled","Cancelled",IF(N80="Completed","Completed",IF(Y80=1,"Awaiting Installation",IF(ISNUMBER(J80),"In Transit","In Production")))) -> Completed | AL80: =IF(AND(N80="Pending",OR(AND(Y80=0,I80<AsOf),AND(Y80=1,L80<AsOf))),1,0) -> 0 | AM80: =IF(AL80=1,IF(Y80=0,AsOf-I80,AsOf-L80),"") | AN80: =IF(AL80=1,IF(Y80=0,"Delivery","Installation"),"") | AO80: =IF(AND(OR(fCat="All",F80=fCat),OR(fCust="All",D80=fCust),OR(fReg="All",E80=fReg)),1,0) -> 1 | AP80: =IF(AND(AL80=1,AO80=1),AM80+ROW()/100000,0) -> 0
A81: NHP-0080 | B81: 46135 | C81: CUST-2679 | D81: Commercial | E81: Rest of Karnataka | F81: Heat Pump Water Heater | G81: 1 | H81: 179000 | I81: 46147 | J81: 46144 | K81: 46147 | L81: 46150 | M81: 46154 | N81: Completed | P81: Customer site not ready | R81: Customer requested weekend install | S81: OK | T81: 1 | U81: 1 | V81: 1 | W81: =DATE(YEAR(B81),MONTH(B81),1) -> 46113 | X81: =IF(AND(N81<>"Cancelled",I81<=AsOf),1,0) -> 1 | Y81: =IF(AND(N81<>"Cancelled",OR(ISNUMBER(K81),N81="Completed")),1,0) -> 1 | Z81: =IF(AND(Y81=1,U81=1,ISNUMBER(K81)),K81-I81,"") -> 0 | AA81: =IF(Z81="","",IF(Z81<0,"Early",IF(Z81=0,"On Time","Late"))) -> On Time | AB81: =IF(AND(N81<>"Cancelled",L81<=AsOf),1,0) -> 1 | AC81: =IF(AND(N81<>"Cancelled",OR(ISNUMBER(M81),N81="Completed")),1,0) -> 1 | AD81: =IF(AND(AC81=1,V81=1,ISNUMBER(M81)),M81-L81,"") -> 4 | AE81: =IF(AD81="","",IF(AD81<0,"Early",IF(AD81=0,"On Time","Late"))) -> Late | AF81: =IF(AND(T81=1,ISNUMBER(J81),N81<>"Cancelled"),J81-B81,"") -> 9 | AG81: =IF(AND(AF81<>"",Z81<>""),K81-J81,"") -> 3 | AH81: =IF(AND(Z81<>"",AD81<>""),M81-K81,"") -> 7 | AI81: =IF(Z81<>"",K81-B81,"") -> 12 | AJ81: =IF(AND(N81="Completed",AD81<>""),M81-B81,"") -> 19 | AK81: =IF(N81="Cancelled","Cancelled",IF(N81="Completed","Completed",IF(Y81=1,"Awaiting Installation",IF(ISNUMBER(J81),"In Transit","In Production")))) -> Completed | AL81: =IF(AND(N81="Pending",OR(AND(Y81=0,I81<AsOf),AND(Y81=1,L81<AsOf))),1,0) -> 0 | AM81: =IF(AL81=1,IF(Y81=0,AsOf-I81,AsOf-L81),"") | AN81: =IF(AL81=1,IF(Y81=0,"Delivery","Installation"),"") | AO81: =IF(AND(OR(fCat="All",F81=fCat),OR(fCust="All",D81=fCust),OR(fReg="All",E81=fReg)),1,0) -> 1 | AP81: =IF(AND(AL81=1,AO81=1),AM81+ROW()/100000,0) -> 0
A82: NHP-0081 | B82: 46136 | C82: CUST-1520 | D82: Commercial | E82: Bengaluru | F82: Heat Pump Dryer | G82: 2 | H82: 1116000 | I82: 46157 | J82: 46154 | K82: 46155 | L82: 46162 | M82: 46170 | N82: Completed | S82: OK | T82: 1 | U82: 1 | V82: 1 | W82: =DATE(YEAR(B82),MONTH(B82),1) -> 46113 | X82: =IF(AND(N82<>"Cancelled",I82<=AsOf),1,0) -> 1 | Y82: =IF(AND(N82<>"Cancelled",OR(ISNUMBER(K82),N82="Completed")),1,0) -> 1 | Z82: =IF(AND(Y82=1,U82=1,ISNUMBER(K82)),K82-I82,"") -> -2 | AA82: =IF(Z82="","",IF(Z82<0,"Early",IF(Z82=0,"On Time","Late"))) -> Early | AB82: =IF(AND(N82<>"Cancelled",L82<=AsOf),1,0) -> 1 | AC82: =IF(AND(N82<>"Cancelled",OR(ISNUMBER(M82),N82="Completed")),1,0) -> 1 | AD82: =IF(AND(AC82=1,V82=1,ISNUMBER(M82)),M82-L82,"") -> 8 | AE82: =IF(AD82="","",IF(AD82<0,"Early",IF(AD82=0,"On Time","Late"))) -> Late | AF82: =IF(AND(T82=1,ISNUMBER(J82),N82<>"Cancelled"),J82-B82,"") -> 18 | AG82: =IF(AND(AF82<>"",Z82<>""),K82-J82,"") -> 1 | AH82: =IF(AND(Z82<>"",AD82<>""),M82-K82,"") -> 15 | AI82: =IF(Z82<>"",K82-B82,"") -> 19 | AJ82: =IF(AND(N82="Completed",AD82<>""),M82-B82,"") -> 34 | AK82: =IF(N82="Cancelled","Cancelled",IF(N82="Completed","Completed",IF(Y82=1,"Awaiting Installation",IF(ISNUMBER(J82),"In Transit","In Production")))) -> Completed | AL82: =IF(AND(N82="Pending",OR(AND(Y82=0,I82<AsOf),AND(Y82=1,L82<AsOf))),1,0) -> 0 | AM82: =IF(AL82=1,IF(Y82=0,AsOf-I82,AsOf-L82),"") | AN82: =IF(AL82=1,IF(Y82=0,"Delivery","Installation"),"") | AO82: =IF(AND(OR(fCat="All",F82=fCat),OR(fCust="All",D82=fCust),OR(fReg="All",E82=fReg)),1,0) -> 1 | AP82: =IF(AND(AL82=1,AO82=1),AM82+ROW()/100000,0) -> 0
A83: NHP-0082 | B83: 46136 | C83: CUST-2743 | D83: Residential | E83: Bengaluru | F83: Swimming Pool Heat Pump | G83: 1 | H83: 233000 | I83: 46150 | J83: 46023 | K83: 46152 | L83: 46153 | M83: 46153 | N83: Completed | R83: Electrical load checked | S83: Dispatch before order date | T83: 0 | U83: 1 | V83: 1 | W83: =DATE(YEAR(B83),MONTH(B83),1) -> 46113 | X83: =IF(AND(N83<>"Cancelled",I83<=AsOf),1,0) -> 1 | Y83: =IF(AND(N83<>"Cancelled",OR(ISNUMBER(K83),N83="Completed")),1,0) -> 1 | Z83: =IF(AND(Y83=1,U83=1,ISNUMBER(K83)),K83-I83,"") -> 2 | AA83: =IF(Z83="","",IF(Z83<0,"Early",IF(Z83=0,"On Time","Late"))) -> Late | AB83: =IF(AND(N83<>"Cancelled",L83<=AsOf),1,0) -> 1 | AC83: =IF(AND(N83<>"Cancelled",OR(ISNUMBER(M83),N83="Completed")),1,0) -> 1 | AD83: =IF(AND(AC83=1,V83=1,ISNUMBER(M83)),M83-L83,"") -> 0 | AE83: =IF(AD83="","",IF(AD83<0,"Early",IF(AD83=0,"On Time","Late"))) -> On Time | AF83: =IF(AND(T83=1,ISNUMBER(J83),N83<>"Cancelled"),J83-B83,"") | AG83: =IF(AND(AF83<>"",Z83<>""),K83-J83,"") | AH83: =IF(AND(Z83<>"",AD83<>""),M83-K83,"") -> 1 | AI83: =IF(Z83<>"",K83-B83,"") -> 16 | AJ83: =IF(AND(N83="Completed",AD83<>""),M83-B83,"") -> 17 | AK83: =IF(N83="Cancelled","Cancelled",IF(N83="Completed","Completed",IF(Y83=1,"Awaiting Installation",IF(ISNUMBER(J83),"In Transit","In Production")))) -> Completed | AL83: =IF(AND(N83="Pending",OR(AND(Y83=0,I83<AsOf),AND(Y83=1,L83<AsOf))),1,0) -> 0 | AM83: =IF(AL83=1,IF(Y83=0,AsOf-I83,AsOf-L83),"") | AN83: =IF(AL83=1,IF(Y83=0,"Delivery","Installation"),"") | AO83: =IF(AND(OR(fCat="All",F83=fCat),OR(fCust="All",D83=fCust),OR(fReg="All",E83=fReg)),1,0) -> 1 | AP83: =IF(AND(AL83=1,AO83=1),AM83+ROW()/100000,0) -> 0
A84: NHP-0083 | B84: 46138 | C84: CUST-4593 | D84: Commercial | E84: Other States | F84: Swimming Pool Heat Pump | G84: 1 | H84: 593000 | I84: 46156 | J84: 46140 | K84: 46150 | L84: 46159 | M84: 46152 | N84: Completed | R84: Replacement of old geyser | S84: OK | T84: 1 | U84: 1 | V84: 1 | W84: =DATE(YEAR(B84),MONTH(B84),1) -> 46113 | X84: =IF(AND(N84<>"Cancelled",I84<=AsOf),1,0) -> 1 | Y84: =IF(AND(N84<>"Cancelled",OR(ISNUMBER(K84),N84="Completed")),1,0) -> 1 | Z84: =IF(AND(Y84=1,U84=1,ISNUMBER(K84)),K84-I84,"") -> -6 | AA84: =IF(Z84="","",IF(Z84<0,"Early",IF(Z84=0,"On Time","Late"))) -> Early | AB84: =IF(AND(N84<>"Cancelled",L84<=AsOf),1,0) -> 1 | AC84: =IF(AND(N84<>"Cancelled",OR(ISNUMBER(M84),N84="Completed")),1,0) -> 1 | AD84: =IF(AND(AC84=1,V84=1,ISNUMBER(M84)),M84-L84,"") -> -7 | AE84: =IF(AD84="","",IF(AD84<0,"Early",IF(AD84=0,"On Time","Late"))) -> Early | AF84: =IF(AND(T84=1,ISNUMBER(J84),N84<>"Cancelled"),J84-B84,"") -> 2 | AG84: =IF(AND(AF84<>"",Z84<>""),K84-J84,"") -> 10 | AH84: =IF(AND(Z84<>"",AD84<>""),M84-K84,"") -> 2 | AI84: =IF(Z84<>"",K84-B84,"") -> 12 | AJ84: =IF(AND(N84="Completed",AD84<>""),M84-B84,"") -> 14 | AK84: =IF(N84="Cancelled","Cancelled",IF(N84="Completed","Completed",IF(Y84=1,"Awaiting Installation",IF(ISNUMBER(J84),"In Transit","In Production")))) -> Completed | AL84: =IF(AND(N84="Pending",OR(AND(Y84=0,I84<AsOf),AND(Y84=1,L84<AsOf))),1,0) -> 0 | AM84: =IF(AL84=1,IF(Y84=0,AsOf-I84,AsOf-L84),"") | AN84: =IF(AL84=1,IF(Y84=0,"Delivery","Installation"),"") | AO84: =IF(AND(OR(fCat="All",F84=fCat),OR(fCust="All",D84=fCust),OR(fReg="All",E84=fReg)),1,0) -> 1 | AP84: =IF(AND(AL84=1,AO84=1),AM84+ROW()/100000,0) -> 0
A85: NHP-0084 | B85: 46139 | C85: CUST-9928 | D85: Residential | E85: Bengaluru | F85: Heat Pump Water Heater | G85: 1 | H85: 117000 | I85: 46149 | J85: 46144 | K85: 46145 | L85: 46152 | M85: 46155 | N85: Completed | P85: Customer site not ready | S85: OK | T85: 1 | U85: 1 | V85: 1 | W85: =DATE(YEAR(B85),MONTH(B85),1) -> 46113 | X85: =IF(AND(N85<>"Cancelled",I85<=AsOf),1,0) -> 1 | Y85: =IF(AND(N85<>"Cancelled",OR(ISNUMBER(K85),N85="Completed")),1,0) -> 1 | Z85: =IF(AND(Y85=1,U85=1,ISNUMBER(K85)),K85-I85,"") -> -4 | AA85: =IF(Z85="","",IF(Z85<0,"Early",IF(Z85=0,"On Time","Late"))) -> Early | AB85: =IF(AND(N85<>"Cancelled",L85<=AsOf),1,0) -> 1 | AC85: =IF(AND(N85<>"Cancelled",OR(ISNUMBER(M85),N85="Completed")),1,0) -> 1 | AD85: =IF(AND(AC85=1,V85=1,ISNUMBER(M85)),M85-L85,"") -> 3 | AE85: =IF(AD85="","",IF(AD85<0,"Early",IF(AD85=0,"On Time","Late"))) -> Late | AF85: =IF(AND(T85=1,ISNUMBER(J85),N85<>"Cancelled"),J85-B85,"") -> 5 | AG85: =IF(AND(AF85<>"",Z85<>""),K85-J85,"") -> 1 | AH85: =IF(AND(Z85<>"",AD85<>""),M85-K85,"") -> 10 | AI85: =IF(Z85<>"",K85-B85,"") -> 6 | AJ85: =IF(AND(N85="Completed",AD85<>""),M85-B85,"") -> 16 | AK85: =IF(N85="Cancelled","Cancelled",IF(N85="Completed","Completed",IF(Y85=1,"Awaiting Installation",IF(ISNUMBER(J85),"In Transit","In Production")))) -> Completed | AL85: =IF(AND(N85="Pending",OR(AND(Y85=0,I85<AsOf),AND(Y85=1,L85<AsOf))),1,0) -> 0 | AM85: =IF(AL85=1,IF(Y85=0,AsOf-I85,AsOf-L85),"") | AN85: =IF(AL85=1,IF(Y85=0,"Delivery","Installation"),"") | AO85: =IF(AND(OR(fCat="All",F85=fCat),OR(fCust="All",D85=fCust),OR(fReg="All",E85=fReg)),1,0) -> 1 | AP85: =IF(AND(AL85=1,AO85=1),AM85+ROW()/100000,0) -> 0
A86: NHP-0085 | B86: 46139 | C86: CUST-9317 | D86: Commercial | E86: Bengaluru | F86: Commercial Heat Pump | G86: 2 | H86: 944000 | I86: 46157 | J86: 46147 | K86: 46149 | L86: 46162 | N86: Pending | R86: Customer requested weekend install | S86: OK | T86: 1 | U86: 1 | V86: 1 | W86: =DATE(YEAR(B86),MONTH(B86),1) -> 46113 | X86: =IF(AND(N86<>"Cancelled",I86<=AsOf),1,0) -> 1 | Y86: =IF(AND(N86<>"Cancelled",OR(ISNUMBER(K86),N86="Completed")),1,0) -> 1 | Z86: =IF(AND(Y86=1,U86=1,ISNUMBER(K86)),K86-I86,"") -> -8 | AA86: =IF(Z86="","",IF(Z86<0,"Early",IF(Z86=0,"On Time","Late"))) -> Early | AB86: =IF(AND(N86<>"Cancelled",L86<=AsOf),1,0) -> 1 | AC86: =IF(AND(N86<>"Cancelled",OR(ISNUMBER(M86),N86="Completed")),1,0) -> 0 | AD86: =IF(AND(AC86=1,V86=1,ISNUMBER(M86)),M86-L86,"") | AE86: =IF(AD86="","",IF(AD86<0,"Early",IF(AD86=0,"On Time","Late"))) | AF86: =IF(AND(T86=1,ISNUMBER(J86),N86<>"Cancelled"),J86-B86,"") -> 8 | AG86: =IF(AND(AF86<>"",Z86<>""),K86-J86,"") -> 2 | AH86: =IF(AND(Z86<>"",AD86<>""),M86-K86,"") | AI86: =IF(Z86<>"",K86-B86,"") -> 10 | AJ86: =IF(AND(N86="Completed",AD86<>""),M86-B86,"") | AK86: =IF(N86="Cancelled","Cancelled",IF(N86="Completed","Completed",IF(Y86=1,"Awaiting Installation",IF(ISNUMBER(J86),"In Transit","In Production")))) -> Awaiting Installation | AL86: =IF(AND(N86="Pending",OR(AND(Y86=0,I86<AsOf),AND(Y86=1,L86<AsOf))),1,0) -> 1 | AM86: =IF(AL86=1,IF(Y86=0,AsOf-I86,AsOf-L86),"") -> 41 | AN86: =IF(AL86=1,IF(Y86=0,"Delivery","Installation"),"") -> Installation | AO86: =IF(AND(OR(fCat="All",F86=fCat),OR(fCust="All",D86=fCust),OR(fReg="All",E86=fReg)),1,0) -> 1 | AP86: =IF(AND(AL86=1,AO86=1),AM86+ROW()/100000,0) -> 41.00086
A87: NHP-0086 | B87: 46139 | C87: CUST-8019 | D87: Commercial | E87: Bengaluru | F87: Heat Pump Water Heater | G87: 2 | H87: 328000 | I87: 46149 | J87: 46143 | K87: 46145 | L87: 46152 | M87: 46157 | N87: Completed | P87: Customer site not ready | R87: Site survey done | S87: OK | T87: 1 | U87: 1 | V87: 1 | W87: =DATE(YEAR(B87),MONTH(B87),1) -> 46113 | X87: =IF(AND(N87<>"Cancelled",I87<=AsOf),1,0) -> 1 | Y87: =IF(AND(N87<>"Cancelled",OR(ISNUMBER(K87),N87="Completed")),1,0) -> 1 | Z87: =IF(AND(Y87=1,U87=1,ISNUMBER(K87)),K87-I87,"") -> -4 | AA87: =IF(Z87="","",IF(Z87<0,"Early",IF(Z87=0,"On Time","Late"))) -> Early | AB87: =IF(AND(N87<>"Cancelled",L87<=AsOf),1,0) -> 1 | AC87: =IF(AND(N87<>"Cancelled",OR(ISNUMBER(M87),N87="Completed")),1,0) -> 1 | AD87: =IF(AND(AC87=1,V87=1,ISNUMBER(M87)),M87-L87,"") -> 5 | AE87: =IF(AD87="","",IF(AD87<0,"Early",IF(AD87=0,"On Time","Late"))) -> Late | AF87: =IF(AND(T87=1,ISNUMBER(J87),N87<>"Cancelled"),J87-B87,"") -> 4 | AG87: =IF(AND(AF87<>"",Z87<>""),K87-J87,"") -> 2 | AH87: =IF(AND(Z87<>"",AD87<>""),M87-K87,"") -> 12 | AI87: =IF(Z87<>"",K87-B87,"") -> 6 | AJ87: =IF(AND(N87="Completed",AD87<>""),M87-B87,"") -> 18 | AK87: =IF(N87="Cancelled","Cancelled",IF(N87="Completed","Completed",IF(Y87=1,"Awaiting Installation",IF(ISNUMBER(J87),"In Transit","In Production")))) -> Completed | AL87: =IF(AND(N87="Pending",OR(AND(Y87=0,I87<AsOf),AND(Y87=1,L87<AsOf))),1,0) -> 0 | AM87: =IF(AL87=1,IF(Y87=0,AsOf-I87,AsOf-L87),"") | AN87: =IF(AL87=1,IF(Y87=0,"Delivery","Installation"),"") | AO87: =IF(AND(OR(fCat="All",F87=fCat),OR(fCust="All",D87=fCust),OR(fReg="All",E87=fReg)),1,0) -> 1 | AP87: =IF(AND(AL87=1,AO87=1),AM87+ROW()/100000,0) -> 0
A88: NHP-0087 | B88: 46139 | C88: CUST-4593 | D88: Commercial | E88: Bengaluru | F88: Commercial Heat Pump | G88: 3 | H88: 1158000 | I88: 46157 | J88: 46147 | K88: 46149 | L88: 46162 | M88: 46158 | N88: Completed | S88: OK | T88: 1 | U88: 1 | V88: 1 | W88: =DATE(YEAR(B88),MONTH(B88),1) -> 46113 | X88: =IF(AND(N88<>"Cancelled",I88<=AsOf),1,0) -> 1 | Y88: =IF(AND(N88<>"Cancelled",OR(ISNUMBER(K88),N88="Completed")),1,0) -> 1 | Z88: =IF(AND(Y88=1,U88=1,ISNUMBER(K88)),K88-I88,"") -> -8 | AA88: =IF(Z88="","",IF(Z88<0,"Early",IF(Z88=0,"On Time","Late"))) -> Early | AB88: =IF(AND(N88<>"Cancelled",L88<=AsOf),1,0) -> 1 | AC88: =IF(AND(N88<>"Cancelled",OR(ISNUMBER(M88),N88="Completed")),1,0) -> 1 | AD88: =IF(AND(AC88=1,V88=1,ISNUMBER(M88)),M88-L88,"") -> -4 | AE88: =IF(AD88="","",IF(AD88<0,"Early",IF(AD88=0,"On Time","Late"))) -> Early | AF88: =IF(AND(T88=1,ISNUMBER(J88),N88<>"Cancelled"),J88-B88,"") -> 8 | AG88: =IF(AND(AF88<>"",Z88<>""),K88-J88,"") -> 2 | AH88: =IF(AND(Z88<>"",AD88<>""),M88-K88,"") -> 9 | AI88: =IF(Z88<>"",K88-B88,"") -> 10 | AJ88: =IF(AND(N88="Completed",AD88<>""),M88-B88,"") -> 19 | AK88: =IF(N88="Cancelled","Cancelled",IF(N88="Completed","Completed",IF(Y88=1,"Awaiting Installation",IF(ISNUMBER(J88),"In Transit","In Production")))) -> Completed | AL88: =IF(AND(N88="Pending",OR(AND(Y88=0,I88<AsOf),AND(Y88=1,L88<AsOf))),1,0) -> 0 | AM88: =IF(AL88=1,IF(Y88=0,AsOf-I88,AsOf-L88),"") | AN88: =IF(AL88=1,IF(Y88=0,"Delivery","Installation"),"") | AO88: =IF(AND(OR(fCat="All",F88=fCat),OR(fCust="All",D88=fCust),OR(fReg="All",E88=fReg)),1,0) -> 1 | AP88: =IF(AND(AL88=1,AO88=1),AM88+ROW()/100000,0) -> 0
A89: NHP-0088 | B89: 46139 | C89: CUST-1711 | D89: Commercial | E89: Bengaluru | F89: Heat Pump Dryer | G89: 1 | H89: 410000 | I89: 46160 | J89: 46158 | K89: 46160 | L89: 46165 | M89: 46163 | N89: Completed | R89: Site survey done | S89: OK | T89: 1 | U89: 1 | V89: 1 | W89: =DATE(YEAR(B89),MONTH(B89),1) -> 46113 | X89: =IF(AND(N89<>"Cancelled",I89<=AsOf),1,0) -> 1 | Y89: =IF(AND(N89<>"Cancelled",OR(ISNUMBER(K89),N89="Completed")),1,0) -> 1 | Z89: =IF(AND(Y89=1,U89=1,ISNUMBER(K89)),K89-I89,"") -> 0 | AA89: =IF(Z89="","",IF(Z89<0,"Early",IF(Z89=0,"On Time","Late"))) -> On Time | AB89: =IF(AND(N89<>"Cancelled",L89<=AsOf),1,0) -> 1 | AC89: =IF(AND(N89<>"Cancelled",OR(ISNUMBER(M89),N89="Completed")),1,0) -> 1 | AD89: =IF(AND(AC89=1,V89=1,ISNUMBER(M89)),M89-L89,"") -> -2 | AE89: =IF(AD89="","",IF(AD89<0,"Early",IF(AD89=0,"On Time","Late"))) -> Early | AF89: =IF(AND(T89=1,ISNUMBER(J89),N89<>"Cancelled"),J89-B89,"") -> 19 | AG89: =IF(AND(AF89<>"",Z89<>""),K89-J89,"") -> 2 | AH89: =IF(AND(Z89<>"",AD89<>""),M89-K89,"") -> 3 | AI89: =IF(Z89<>"",K89-B89,"") -> 21 | AJ89: =IF(AND(N89="Completed",AD89<>""),M89-B89,"") -> 24 | AK89: =IF(N89="Cancelled","Cancelled",IF(N89="Completed","Completed",IF(Y89=1,"Awaiting Installation",IF(ISNUMBER(J89),"In Transit","In Production")))) -> Completed | AL89: =IF(AND(N89="Pending",OR(AND(Y89=0,I89<AsOf),AND(Y89=1,L89<AsOf))),1,0) -> 0 | AM89: =IF(AL89=1,IF(Y89=0,AsOf-I89,AsOf-L89),"") | AN89: =IF(AL89=1,IF(Y89=0,"Delivery","Installation"),"") | AO89: =IF(AND(OR(fCat="All",F89=fCat),OR(fCust="All",D89=fCust),OR(fReg="All",E89=fReg)),1,0) -> 1 | AP89: =IF(AND(AL89=1,AO89=1),AM89+ROW()/100000,0) -> 0
A90: NHP-0089 | B90: 46143 | C90: CUST-3266 | D90: Institutional | E90: Bengaluru | F90: Commercial Heat Pump | G90: 2 | H90: 924000 | I90: 46161 | J90: 46155 | K90: 46157 | L90: 46166 | M90: 46161 | N90: Completed | R90: Pipe routing confirmed | S90: OK | T90: 1 | U90: 1 | V90: 1 | W90: =DATE(YEAR(B90),MONTH(B90),1) -> 46143 | X90: =IF(AND(N90<>"Cancelled",I90<=AsOf),1,0) -> 1 | Y90: =IF(AND(N90<>"Cancelled",OR(ISNUMBER(K90),N90="Completed")),1,0) -> 1 | Z90: =IF(AND(Y90=1,U90=1,ISNUMBER(K90)),K90-I90,"") -> -4 | AA90: =IF(Z90="","",IF(Z90<0,"Early",IF(Z90=0,"On Time","Late"))) -> Early | AB90: =IF(AND(N90<>"Cancelled",L90<=AsOf),1,0) -> 1 | AC90: =IF(AND(N90<>"Cancelled",OR(ISNUMBER(M90),N90="Completed")),1,0) -> 1 | AD90: =IF(AND(AC90=1,V90=1,ISNUMBER(M90)),M90-L90,"") -> -5 | AE90: =IF(AD90="","",IF(AD90<0,"Early",IF(AD90=0,"On Time","Late"))) -> Early | AF90: =IF(AND(T90=1,ISNUMBER(J90),N90<>"Cancelled"),J90-B90,"") -> 12 | AG90: =IF(AND(AF90<>"",Z90<>""),K90-J90,"") -> 2 | AH90: =IF(AND(Z90<>"",AD90<>""),M90-K90,"") -> 4 | AI90: =IF(Z90<>"",K90-B90,"") -> 14 | AJ90: =IF(AND(N90="Completed",AD90<>""),M90-B90,"") -> 18 | AK90: =IF(N90="Cancelled","Cancelled",IF(N90="Completed","Completed",IF(Y90=1,"Awaiting Installation",IF(ISNUMBER(J90),"In Transit","In Production")))) -> Completed | AL90: =IF(AND(N90="Pending",OR(AND(Y90=0,I90<AsOf),AND(Y90=1,L90<AsOf))),1,0) -> 0 | AM90: =IF(AL90=1,IF(Y90=0,AsOf-I90,AsOf-L90),"") | AN90: =IF(AL90=1,IF(Y90=0,"Delivery","Installation"),"") | AO90: =IF(AND(OR(fCat="All",F90=fCat),OR(fCust="All",D90=fCust),OR(fReg="All",E90=fReg)),1,0) -> 1 | AP90: =IF(AND(AL90=1,AO90=1),AM90+ROW()/100000,0) -> 0
A91: NHP-0090 | B91: 46145 | C91: CUST-9348 | D91: Commercial | E91: Bengaluru | F91: Commercial Heat Pump | G91: 1 | H91: 661000 | I91: 46163 | J91: 46173 | K91: 46175 | L91: 46168 | M91: 46178 | N91: Completed | O91: Component shortage | P91: Knock-on from late delivery | R91: Site survey done | S91: OK | T91: 1 | U91: 1 | V91: 1 | W91: =DATE(YEAR(B91),MONTH(B91),1) -> 46143 | X91: =IF(AND(N91<>"Cancelled",I91<=AsOf),1,0) -> 1 | Y91: =IF(AND(N91<>"Cancelled",OR(ISNUMBER(K91),N91="Completed")),1,0) -> 1 | Z91: =IF(AND(Y91=1,U91=1,ISNUMBER(K91)),K91-I91,"") -> 12 | AA91: =IF(Z91="","",IF(Z91<0,"Early",IF(Z91=0,"On Time","Late"))) -> Late | AB91: =IF(AND(N91<>"Cancelled",L91<=AsOf),1,0) -> 1 | AC91: =IF(AND(N91<>"Cancelled",OR(ISNUMBER(M91),N91="Completed")),1,0) -> 1 | AD91: =IF(AND(AC91=1,V91=1,ISNUMBER(M91)),M91-L91,"") -> 10 | AE91: =IF(AD91="","",IF(AD91<0,"Early",IF(AD91=0,"On Time","Late"))) -> Late | AF91: =IF(AND(T91=1,ISNUMBER(J91),N91<>"Cancelled"),J91-B91,"") -> 28 | AG91: =IF(AND(AF91<>"",Z91<>""),K91-J91,"") -> 2 | AH91: =IF(AND(Z91<>"",AD91<>""),M91-K91,"") -> 3 | AI91: =IF(Z91<>"",K91-B91,"") -> 30 | AJ91: =IF(AND(N91="Completed",AD91<>""),M91-B91,"") -> 33 | AK91: =IF(N91="Cancelled","Cancelled",IF(N91="Completed","Completed",IF(Y91=1,"Awaiting Installation",IF(ISNUMBER(J91),"In Transit","In Production")))) -> Completed | AL91: =IF(AND(N91="Pending",OR(AND(Y91=0,I91<AsOf),AND(Y91=1,L91<AsOf))),1,0) -> 0 | AM91: =IF(AL91=1,IF(Y91=0,AsOf-I91,AsOf-L91),"") | AN91: =IF(AL91=1,IF(Y91=0,"Delivery","Installation"),"") | AO91: =IF(AND(OR(fCat="All",F91=fCat),OR(fCust="All",D91=fCust),OR(fReg="All",E91=fReg)),1,0) -> 1 | AP91: =IF(AND(AL91=1,AO91=1),AM91+ROW()/100000,0) -> 0
A92: NHP-0091 | B92: 46145 | C92: CUST-6977 | D92: Commercial | E92: Other States | F92: Commercial Heat Pump | G92: 1 | H92: 1161000 | I92: 46167 | J92: 46154 | K92: 46163 | L92: 46172 | M92: 46174 | N92: Completed | R92: Customer requested weekend install | S92: OK | T92: 1 | U92: 1 | V92: 1 | W92: =DATE(YEAR(B92),MONTH(B92),1) -> 46143 | X92: =IF(AND(N92<>"Cancelled",I92<=AsOf),1,0) -> 1 | Y92: =IF(AND(N92<>"Cancelled",OR(ISNUMBER(K92),N92="Completed")),1,0) -> 1 | Z92: =IF(AND(Y92=1,U92=1,ISNUMBER(K92)),K92-I92,"") -> -4 | AA92: =IF(Z92="","",IF(Z92<0,"Early",IF(Z92=0,"On Time","Late"))) -> Early | AB92: =IF(AND(N92<>"Cancelled",L92<=AsOf),1,0) -> 1 | AC92: =IF(AND(N92<>"Cancelled",OR(ISNUMBER(M92),N92="Completed")),1,0) -> 1 | AD92: =IF(AND(AC92=1,V92=1,ISNUMBER(M92)),M92-L92,"") -> 2 | AE92: =IF(AD92="","",IF(AD92<0,"Early",IF(AD92=0,"On Time","Late"))) -> Late | AF92: =IF(AND(T92=1,ISNUMBER(J92),N92<>"Cancelled"),J92-B92,"") -> 9 | AG92: =IF(AND(AF92<>"",Z92<>""),K92-J92,"") -> 9 | AH92: =IF(AND(Z92<>"",AD92<>""),M92-K92,"") -> 11 | AI92: =IF(Z92<>"",K92-B92,"") -> 18 | AJ92: =IF(AND(N92="Completed",AD92<>""),M92-B92,"") -> 29 | AK92: =IF(N92="Cancelled","Cancelled",IF(N92="Completed","Completed",IF(Y92=1,"Awaiting Installation",IF(ISNUMBER(J92),"In Transit","In Production")))) -> Completed | AL92: =IF(AND(N92="Pending",OR(AND(Y92=0,I92<AsOf),AND(Y92=1,L92<AsOf))),1,0) -> 0 | AM92: =IF(AL92=1,IF(Y92=0,AsOf-I92,AsOf-L92),"") | AN92: =IF(AL92=1,IF(Y92=0,"Delivery","Installation"),"") | AO92: =IF(AND(OR(fCat="All",F92=fCat),OR(fCust="All",D92=fCust),OR(fReg="All",E92=fReg)),1,0) -> 1 | AP92: =IF(AND(AL92=1,AO92=1),AM92+ROW()/100000,0) -> 0
A93: NHP-0092 | B93: 46145 | C93: CUST-9279 | D93: Commercial | E93: Rest of Karnataka | F93: Commercial Heat Pump | G93: 1 | H93: 306000 | I93: 46165 | L93: 46170 | N93: Cancelled | Q93: Long lead time | R93: Site survey done | S93: OK | T93: 1 | U93: 1 | V93: 1 | W93: =DATE(YEAR(B93),MONTH(B93),1) -> 46143 | X93: =IF(AND(N93<>"Cancelled",I93<=AsOf),1,0) -> 0 | Y93: =IF(AND(N93<>"Cancelled",OR(ISNUMBER(K93),N93="Completed")),1,0) -> 0 | Z93: =IF(AND(Y93=1,U93=1,ISNUMBER(K93)),K93-I93,"") | AA93: =IF(Z93="","",IF(Z93<0,"Early",IF(Z93=0,"On Time","Late"))) | AB93: =IF(AND(N93<>"Cancelled",L93<=AsOf),1,0) -> 0 | AC93: =IF(AND(N93<>"Cancelled",OR(ISNUMBER(M93),N93="Completed")),1,0) -> 0 | AD93: =IF(AND(AC93=1,V93=1,ISNUMBER(M93)),M93-L93,"") | AE93: =IF(AD93="","",IF(AD93<0,"Early",IF(AD93=0,"On Time","Late"))) | AF93: =IF(AND(T93=1,ISNUMBER(J93),N93<>"Cancelled"),J93-B93,"") | AG93: =IF(AND(AF93<>"",Z93<>""),K93-J93,"") | AH93: =IF(AND(Z93<>"",AD93<>""),M93-K93,"") | AI93: =IF(Z93<>"",K93-B93,"") | AJ93: =IF(AND(N93="Completed",AD93<>""),M93-B93,"") | AK93: =IF(N93="Cancelled","Cancelled",IF(N93="Completed","Completed",IF(Y93=1,"Awaiting Installation",IF(ISNUMBER(J93),"In Transit","In Production")))) -> Cancelled | AL93: =IF(AND(N93="Pending",OR(AND(Y93=0,I93<AsOf),AND(Y93=1,L93<AsOf))),1,0) -> 0 | AM93: =IF(AL93=1,IF(Y93=0,AsOf-I93,AsOf-L93),"") | AN93: =IF(AL93=1,IF(Y93=0,"Delivery","Installation"),"") | AO93: =IF(AND(OR(fCat="All",F93=fCat),OR(fCust="All",D93=fCust),OR(fReg="All",E93=fReg)),1,0) -> 1 | AP93: =IF(AND(AL93=1,AO93=1),AM93+ROW()/100000,0) -> 0
A94: NHP-0093 | B94: 46148 | C94: CUST-3591 | D94: Residential | E94: Rest of Karnataka | F94: Swimming Pool Heat Pump | G94: 1 | H94: 584000 | I94: 46164 | J94: 46153 | K94: 46157 | L94: 46167 | M94: 46160 | N94: Completed | R94: Electrical load checked | S94: OK | T94: 1 | U94: 1 | V94: 1 | W94: =DATE(YEAR(B94),MONTH(B94),1) -> 46143 | X94: =IF(AND(N94<>"Cancelled",I94<=AsOf),1,0) -> 1 | Y94: =IF(AND(N94<>"Cancelled",OR(ISNUMBER(K94),N94="Completed")),1,0) -> 1 | Z94: =IF(AND(Y94=1,U94=1,ISNUMBER(K94)),K94-I94,"") -> -7 | AA94: =IF(Z94="","",IF(Z94<0,"Early",IF(Z94=0,"On Time","Late"))) -> Early | AB94: =IF(AND(N94<>"Cancelled",L94<=AsOf),1,0) -> 1 | AC94: =IF(AND(N94<>"Cancelled",OR(ISNUMBER(M94),N94="Completed")),1,0) -> 1 | AD94: =IF(AND(AC94=1,V94=1,ISNUMBER(M94)),M94-L94,"") -> -7 | AE94: =IF(AD94="","",IF(AD94<0,"Early",IF(AD94=0,"On Time","Late"))) -> Early | AF94: =IF(AND(T94=1,ISNUMBER(J94),N94<>"Cancelled"),J94-B94,"") -> 5 | AG94: =IF(AND(AF94<>"",Z94<>""),K94-J94,"") -> 4 | AH94: =IF(AND(Z94<>"",AD94<>""),M94-K94,"") -> 3 | AI94: =IF(Z94<>"",K94-B94,"") -> 9 | AJ94: =IF(AND(N94="Completed",AD94<>""),M94-B94,"") -> 12 | AK94: =IF(N94="Cancelled","Cancelled",IF(N94="Completed","Completed",IF(Y94=1,"Awaiting Installation",IF(ISNUMBER(J94),"In Transit","In Production")))) -> Completed | AL94: =IF(AND(N94="Pending",OR(AND(Y94=0,I94<AsOf),AND(Y94=1,L94<AsOf))),1,0) -> 0 | AM94: =IF(AL94=1,IF(Y94=0,AsOf-I94,AsOf-L94),"") | AN94: =IF(AL94=1,IF(Y94=0,"Delivery","Installation"),"") | AO94: =IF(AND(OR(fCat="All",F94=fCat),OR(fCust="All",D94=fCust),OR(fReg="All",E94=fReg)),1,0) -> 1 | AP94: =IF(AND(AL94=1,AO94=1),AM94+ROW()/100000,0) -> 0
A95: NHP-0094 | B95: 46148 | C95: CUST-3287 | D95: Institutional | E95: Rest of Karnataka | F95: Custom Requirement | G95: 1 | H95: 1017000 | I95: 46180 | J95: 46179 | K95: 46182 | L95: 46185 | M95: 46185 | N95: Completed | O95: Production backlog | R95: Pipe routing confirmed | S95: OK | T95: 1 | U95: 1 | V95: 1 | W95: =DATE(YEAR(B95),MONTH(B95),1) -> 46143 | X95: =IF(AND(N95<>"Cancelled",I95<=AsOf),1,0) -> 1 | Y95: =IF(AND(N95<>"Cancelled",OR(ISNUMBER(K95),N95="Completed")),1,0) -> 1 | Z95: =IF(AND(Y95=1,U95=1,ISNUMBER(K95)),K95-I95,"") -> 2 | AA95: =IF(Z95="","",IF(Z95<0,"Early",IF(Z95=0,"On Time","Late"))) -> Late | AB95: =IF(AND(N95<>"Cancelled",L95<=AsOf),1,0) -> 1 | AC95: =IF(AND(N95<>"Cancelled",OR(ISNUMBER(M95),N95="Completed")),1,0) -> 1 | AD95: =IF(AND(AC95=1,V95=1,ISNUMBER(M95)),M95-L95,"") -> 0 | AE95: =IF(AD95="","",IF(AD95<0,"Early",IF(AD95=0,"On Time","Late"))) -> On Time | AF95: =IF(AND(T95=1,ISNUMBER(J95),N95<>"Cancelled"),J95-B95,"") -> 31 | AG95: =IF(AND(AF95<>"",Z95<>""),K95-J95,"") -> 3 | AH95: =IF(AND(Z95<>"",AD95<>""),M95-K95,"") -> 3 | AI95: =IF(Z95<>"",K95-B95,"") -> 34 | AJ95: =IF(AND(N95="Completed",AD95<>""),M95-B95,"") -> 37 | AK95: =IF(N95="Cancelled","Cancelled",IF(N95="Completed","Completed",IF(Y95=1,"Awaiting Installation",IF(ISNUMBER(J95),"In Transit","In Production")))) -> Completed | AL95: =IF(AND(N95="Pending",OR(AND(Y95=0,I95<AsOf),AND(Y95=1,L95<AsOf))),1,0) -> 0 | AM95: =IF(AL95=1,IF(Y95=0,AsOf-I95,AsOf-L95),"") | AN95: =IF(AL95=1,IF(Y95=0,"Delivery","Installation"),"") | AO95: =IF(AND(OR(fCat="All",F95=fCat),OR(fCust="All",D95=fCust),OR(fReg="All",E95=fReg)),1,0) -> 1 | AP95: =IF(AND(AL95=1,AO95=1),AM95+ROW()/100000,0) -> 0
A96: NHP-0095 | B96: 46152 | C96: CUST-2584 | D96: Institutional | E96: Rest of Karnataka | F96: Custom Requirement | G96: 2 | H96: 2722000 | I96: 46184 | J96: 46191 | K96: 46194 | L96: 46189 | N96: Pending | O96: Component shortage | P96: Customer site not ready | R96: Customer civil work in progress | S96: OK | T96: 1 | U96: 1 | V96: 1 | W96: =DATE(YEAR(B96),MONTH(B96),1) -> 46143 | X96: =IF(AND(N96<>"Cancelled",I96<=AsOf),1,0) -> 1 | Y96: =IF(AND(N96<>"Cancelled",OR(ISNUMBER(K96),N96="Completed")),1,0) -> 1 | Z96: =IF(AND(Y96=1,U96=1,ISNUMBER(K96)),K96-I96,"") -> 10 | AA96: =IF(Z96="","",IF(Z96<0,"Early",IF(Z96=0,"On Time","Late"))) -> Late | AB96: =IF(AND(N96<>"Cancelled",L96<=AsOf),1,0) -> 1 | AC96: =IF(AND(N96<>"Cancelled",OR(ISNUMBER(M96),N96="Completed")),1,0) -> 0 | AD96: =IF(AND(AC96=1,V96=1,ISNUMBER(M96)),M96-L96,"") | AE96: =IF(AD96="","",IF(AD96<0,"Early",IF(AD96=0,"On Time","Late"))) | AF96: =IF(AND(T96=1,ISNUMBER(J96),N96<>"Cancelled"),J96-B96,"") -> 39 | AG96: =IF(AND(AF96<>"",Z96<>""),K96-J96,"") -> 3 | AH96: =IF(AND(Z96<>"",AD96<>""),M96-K96,"") | AI96: =IF(Z96<>"",K96-B96,"") -> 42 | AJ96: =IF(AND(N96="Completed",AD96<>""),M96-B96,"") | AK96: =IF(N96="Cancelled","Cancelled",IF(N96="Completed","Completed",IF(Y96=1,"Awaiting Installation",IF(ISNUMBER(J96),"In Transit","In Production")))) -> Awaiting Installation | AL96: =IF(AND(N96="Pending",OR(AND(Y96=0,I96<AsOf),AND(Y96=1,L96<AsOf))),1,0) -> 1 | AM96: =IF(AL96=1,IF(Y96=0,AsOf-I96,AsOf-L96),"") -> 14 | AN96: =IF(AL96=1,IF(Y96=0,"Delivery","Installation"),"") -> Installation | AO96: =IF(AND(OR(fCat="All",F96=fCat),OR(fCust="All",D96=fCust),OR(fReg="All",E96=fReg)),1,0) -> 1 | AP96: =IF(AND(AL96=1,AO96=1),AM96+ROW()/100000,0) -> 14.00096
A97: NHP-0096 | B97: 46153 | C97: CUST-6977 | D97: Institutional | E97: Bengaluru | F97: Custom Requirement | G97: 1 | H97: 669000 | I97: 46183 | J97: 46172 | K97: 46173 | L97: 46188 | M97: 46178 | N97: Completed | R97: Pipe routing confirmed | S97: OK | T97: 1 | U97: 1 | V97: 1 | W97: =DATE(YEAR(B97),MONTH(B97),1) -> 46143 | X97: =IF(AND(N97<>"Cancelled",I97<=AsOf),1,0) -> 1 | Y97: =IF(AND(N97<>"Cancelled",OR(ISNUMBER(K97),N97="Completed")),1,0) -> 1 | Z97: =IF(AND(Y97=1,U97=1,ISNUMBER(K97)),K97-I97,"") -> -10 | AA97: =IF(Z97="","",IF(Z97<0,"Early",IF(Z97=0,"On Time","Late"))) -> Early | AB97: =IF(AND(N97<>"Cancelled",L97<=AsOf),1,0) -> 1 | AC97: =IF(AND(N97<>"Cancelled",OR(ISNUMBER(M97),N97="Completed")),1,0) -> 1 | AD97: =IF(AND(AC97=1,V97=1,ISNUMBER(M97)),M97-L97,"") -> -10 | AE97: =IF(AD97="","",IF(AD97<0,"Early",IF(AD97=0,"On Time","Late"))) -> Early | AF97: =IF(AND(T97=1,ISNUMBER(J97),N97<>"Cancelled"),J97-B97,"") -> 19 | AG97: =IF(AND(AF97<>"",Z97<>""),K97-J97,"") -> 1 | AH97: =IF(AND(Z97<>"",AD97<>""),M97-K97,"") -> 5 | AI97: =IF(Z97<>"",K97-B97,"") -> 20 | AJ97: =IF(AND(N97="Completed",AD97<>""),M97-B97,"") -> 25 | AK97: =IF(N97="Cancelled","Cancelled",IF(N97="Completed","Completed",IF(Y97=1,"Awaiting Installation",IF(ISNUMBER(J97),"In Transit","In Production")))) -> Completed | AL97: =IF(AND(N97="Pending",OR(AND(Y97=0,I97<AsOf),AND(Y97=1,L97<AsOf))),1,0) -> 0 | AM97: =IF(AL97=1,IF(Y97=0,AsOf-I97,AsOf-L97),"") | AN97: =IF(AL97=1,IF(Y97=0,"Delivery","Installation"),"") | AO97: =IF(AND(OR(fCat="All",F97=fCat),OR(fCust="All",D97=fCust),OR(fReg="All",E97=fReg)),1,0) -> 1 | AP97: =IF(AND(AL97=1,AO97=1),AM97+ROW()/100000,0) -> 0
A98: NHP-0097 | B98: 46154 | C98: CUST-4258 | D98: Residential | E98: Bengaluru | F98: Heat Pump Water Heater | G98: 1 | H98: 144000 | I98: 46164 | J98: 46155 | K98: 46157 | L98: 46167 | M98: 46159 | N98: Completed | R98: Pipe routing confirmed | S98: OK | T98: 1 | U98: 1 | V98: 1 | W98: =DATE(YEAR(B98),MONTH(B98),1) -> 46143 | X98: =IF(AND(N98<>"Cancelled",I98<=AsOf),1,0) -> 1 | Y98: =IF(AND(N98<>"Cancelled",OR(ISNUMBER(K98),N98="Completed")),1,0) -> 1 | Z98: =IF(AND(Y98=1,U98=1,ISNUMBER(K98)),K98-I98,"") -> -7 | AA98: =IF(Z98="","",IF(Z98<0,"Early",IF(Z98=0,"On Time","Late"))) -> Early | AB98: =IF(AND(N98<>"Cancelled",L98<=AsOf),1,0) -> 1 | AC98: =IF(AND(N98<>"Cancelled",OR(ISNUMBER(M98),N98="Completed")),1,0) -> 1 | AD98: =IF(AND(AC98=1,V98=1,ISNUMBER(M98)),M98-L98,"") -> -8 | AE98: =IF(AD98="","",IF(AD98<0,"Early",IF(AD98=0,"On Time","Late"))) -> Early | AF98: =IF(AND(T98=1,ISNUMBER(J98),N98<>"Cancelled"),J98-B98,"") -> 1 | AG98: =IF(AND(AF98<>"",Z98<>""),K98-J98,"") -> 2 | AH98: =IF(AND(Z98<>"",AD98<>""),M98-K98,"") -> 2 | AI98: =IF(Z98<>"",K98-B98,"") -> 3 | AJ98: =IF(AND(N98="Completed",AD98<>""),M98-B98,"") -> 5 | AK98: =IF(N98="Cancelled","Cancelled",IF(N98="Completed","Completed",IF(Y98=1,"Awaiting Installation",IF(ISNUMBER(J98),"In Transit","In Production")))) -> Completed | AL98: =IF(AND(N98="Pending",OR(AND(Y98=0,I98<AsOf),AND(Y98=1,L98<AsOf))),1,0) -> 0 | AM98: =IF(AL98=1,IF(Y98=0,AsOf-I98,AsOf-L98),"") | AN98: =IF(AL98=1,IF(Y98=0,"Delivery","Installation"),"") | AO98: =IF(AND(OR(fCat="All",F98=fCat),OR(fCust="All",D98=fCust),OR(fReg="All",E98=fReg)),1,0) -> 1 | AP98: =IF(AND(AL98=1,AO98=1),AM98+ROW()/100000,0) -> 0
A99: NHP-0098 | B99: 46154 | C99: CUST-9179 | D99: Commercial | E99: Rest of Karnataka | F99: Heat Pump Water Heater | G99: 1 | H99: 118000 | I99: 46166 | J99: 46159 | K99: 46161 | L99: 46169 | M99: 46173 | N99: Completed | P99: Customer site not ready | S99: OK | T99: 1 | U99: 1 | V99: 1 | W99: =DATE(YEAR(B99),MONTH(B99),1) -> 46143 | X99: =IF(AND(N99<>"Cancelled",I99<=AsOf),1,0) -> 1 | Y99: =IF(AND(N99<>"Cancelled",OR(ISNUMBER(K99),N99="Completed")),1,0) -> 1 | Z99: =IF(AND(Y99=1,U99=1,ISNUMBER(K99)),K99-I99,"") -> -5 | AA99: =IF(Z99="","",IF(Z99<0,"Early",IF(Z99=0,"On Time","Late"))) -> Early | AB99: =IF(AND(N99<>"Cancelled",L99<=AsOf),1,0) -> 1 | AC99: =IF(AND(N99<>"Cancelled",OR(ISNUMBER(M99),N99="Completed")),1,0) -> 1 | AD99: =IF(AND(AC99=1,V99=1,ISNUMBER(M99)),M99-L99,"") -> 4 | AE99: =IF(AD99="","",IF(AD99<0,"Early",IF(AD99=0,"On Time","Late"))) -> Late | AF99: =IF(AND(T99=1,ISNUMBER(J99),N99<>"Cancelled"),J99-B99,"") -> 5 | AG99: =IF(AND(AF99<>"",Z99<>""),K99-J99,"") -> 2 | AH99: =IF(AND(Z99<>"",AD99<>""),M99-K99,"") -> 12 | AI99: =IF(Z99<>"",K99-B99,"") -> 7 | AJ99: =IF(AND(N99="Completed",AD99<>""),M99-B99,"") -> 19 | AK99: =IF(N99="Cancelled","Cancelled",IF(N99="Completed","Completed",IF(Y99=1,"Awaiting Installation",IF(ISNUMBER(J99),"In Transit","In Production")))) -> Completed | AL99: =IF(AND(N99="Pending",OR(AND(Y99=0,I99<AsOf),AND(Y99=1,L99<AsOf))),1,0) -> 0 | AM99: =IF(AL99=1,IF(Y99=0,AsOf-I99,AsOf-L99),"") | AN99: =IF(AL99=1,IF(Y99=0,"Delivery","Installation"),"") | AO99: =IF(AND(OR(fCat="All",F99=fCat),OR(fCust="All",D99=fCust),OR(fReg="All",E99=fReg)),1,0) -> 1 | AP99: =IF(AND(AL99=1,AO99=1),AM99+ROW()/100000,0) -> 0
A100: NHP-0099 | B100: 46155 | C100: CUST-7482 | D100: Institutional | E100: Bengaluru | F100: Commercial Heat Pump | G100: 1 | H100: 502000 | I100: 46173 | J100: 46166 | K100: 46167 | L100: 46178 | M100: 46172 | N100: Completed | S100: OK | T100: 1 | U100: 1 | V100: 1 | W100: =DATE(YEAR(B100),MONTH(B100),1) -> 46143 | X100: =IF(AND(N100<>"Cancelled",I100<=AsOf),1,0) -> 1 | Y100: =IF(AND(N100<>"Cancelled",OR(ISNUMBER(K100),N100="Completed")),1,0) -> 1 | Z100: =IF(AND(Y100=1,U100=1,ISNUMBER(K100)),K100-I100,"") -> -6 | AA100: =IF(Z100="","",IF(Z100<0,"Early",IF(Z100=0,"On Time","Late"))) -> Early | AB100: =IF(AND(N100<>"Cancelled",L100<=AsOf),1,0) -> 1 | AC100: =IF(AND(N100<>"Cancelled",OR(ISNUMBER(M100),N100="Completed")),1,0) -> 1 | AD100: =IF(AND(AC100=1,V100=1,ISNUMBER(M100)),M100-L100,"") -> -6 | AE100: =IF(AD100="","",IF(AD100<0,"Early",IF(AD100=0,"On Time","Late"))) -> Early | AF100: =IF(AND(T100=1,ISNUMBER(J100),N100<>"Cancelled"),J100-B100,"") -> 11 | AG100: =IF(AND(AF100<>"",Z100<>""),K100-J100,"") -> 1 | AH100: =IF(AND(Z100<>"",AD100<>""),M100-K100,"") -> 5 | AI100: =IF(Z100<>"",K100-B100,"") -> 12 | AJ100: =IF(AND(N100="Completed",AD100<>""),M100-B100,"") -> 17 | AK100: =IF(N100="Cancelled","Cancelled",IF(N100="Completed","Completed",IF(Y100=1,"Awaiting Installation",IF(ISNUMBER(J100),"In Transit","In Production")))) -> Completed | AL100: =IF(AND(N100="Pending",OR(AND(Y100=0,I100<AsOf),AND(Y100=1,L100<AsOf))),1,0) -> 0 | AM100: =IF(AL100=1,IF(Y100=0,AsOf-I100,AsOf-L100),"") | AN100: =IF(AL100=1,IF(Y100=0,"Delivery","Installation"),"") | AO100: =IF(AND(OR(fCat="All",F100=fCat),OR(fCust="All",D100=fCust),OR(fReg="All",E100=fReg)),1,0) -> 1 | AP100: =IF(AND(AL100=1,AO100=1),AM100+ROW()/100000,0) -> 0
...

Sheet KPI ANALYSIS
A1: KPI ANALYSIS - all results are live formulas on CLEANED DATA
A2: SIMULATED DATA - synthetic records created for a portfolio case study. Not real company performance.
B4: Report as-of date ► | C4: 46203 | D4: Yellow = editable input. End of the Jan-Jun 2026 review period. 'Due' and 'overdue' are judged against this date, never against today's date.
A6: # | B6: KPI | C6: Result | D6: Unit | E6: Numerator | F6: Denominator | G6: Formula (plain English) | H6: Business meaning | I6: Applicable records / exclusions | J6: Interpretation (data as of 30-Jun-2026)
A7: A. ORDER MANAGEMENT
A8: 1 | B8: Total Orders | C8: =COUNTA('CLEANED DATA'!$A$2:$A$1000) -> 160 | D8: count | G8: Count of unique Order IDs | H8: Size of the workload in the period | I8: All 160 cleaned orders (3 duplicate rows already removed) | J8: 160 orders booked Jan-Jun 2026.
A9: 2 | B9: Completed Orders | C9: =COUNTIF('CLEANED DATA'!$N$2:$N$1000,"Completed") -> 121 | D9: count | G9: Orders with status Completed (= installed) | H9: Orders fully delivered and installed | I9: Status = Completed | J9: 121 orders fully closed.
A10: 3 | B10: Pending Orders | C10: =COUNTIF('CLEANED DATA'!$N$2:$N$1000,"Pending") -> 30 | D10: count | G10: Orders with status Pending | H10: Open orders still being worked on | I10: Status = Pending ('In Progress' standardised to Pending) | J10: 30 orders still open.
A11: 4 | B11: Cancelled Orders | C11: =COUNTIF('CLEANED DATA'!$N$2:$N$1000,"Cancelled") -> 9 | D11: count | G11: Orders with status Cancelled | H11: Lost or withdrawn orders | I11: Status = Cancelled | J11: 9 cancellations - excluded from every delivery and installation KPI.
A12: ✓ | B12: Status reconciliation check | C12: =IF('KPI ANALYSIS'!$C$9+'KPI ANALYSIS'!$C$10+'KPI ANALYSIS'!$C$11='KPI ANALYSIS'!$C$8,"OK - statuses add up","CHECK - statuses do not add up") -> OK - statuses add up | D12: check | G12: Completed + Pending + Cancelled = Total | H12: Proves no order is lost or double counted | I12: All orders | J12: Must always read OK.
A13: 5 | B13: Active (non-cancelled) Orders | C13: ='KPI ANALYSIS'!$C$8-'KPI ANALYSIS'!$C$11 -> 151 | D13: count | G13: Total - Cancelled | H13: Orders the business still has to fulfil | I13: Excludes cancelled | J13: 151 orders.
A14: 6 | B14: Order Completion Rate | C14: =IFERROR('KPI ANALYSIS'!$C$9/'KPI ANALYSIS'!$C$13,"n/a") -> 0.8013245 | D14: % | E14: ='KPI ANALYSIS'!$C$9 -> 121 | F14: ='KPI ANALYSIS'!$C$13 -> 151 | G14: Completed ÷ Active (non-cancelled) orders | H14: Share of committed orders that are fully closed | I14: Cancelled orders removed from the denominator; recent orders not yet due still count as open | J14: 80.1%. Lower in June because many June orders are not due yet - read together with Overdue Orders.
A15: 7 | B15: Cancellation Rate | C15: =IFERROR('KPI ANALYSIS'!$C$11/'KPI ANALYSIS'!$C$8,"n/a") -> 0.05625 | D15: % | E15: ='KPI ANALYSIS'!$C$11 -> 9 | F15: ='KPI ANALYSIS'!$C$8 -> 160 | G15: Cancelled ÷ Total orders | H15: Lost demand | I15: All orders | J15: 5.6%; every cancellation has a recorded reason.
A16: 8 | B16: Current Order Backlog (orders) | C16: ='KPI ANALYSIS'!$C$10 -> 30 | D16: count | G16: Pending orders on the report date | H16: Open work still to deliver and/or install | I16: Status = Pending | J16: 30 open orders; 9 of them are overdue (see D).
A17: 9 | B17: Backlog Value (INR, simulated) | C17: =SUMIFS('CLEANED DATA'!$H$2:$H$1000,'CLEANED DATA'!$N$2:$N$1000,"Pending") -> 27374000 | D17: INR | G17: Sum of order value of Pending orders | H17: Revenue tied up in open orders | I17: Pending orders with a value | J17: ₹2.74 crore (simulated values).
A18: B. DELIVERY PERFORMANCE
A19: 10 | B19: Total Deliveries Due | C19: =SUM('CLEANED DATA'!$X$2:$X$1000) -> 132 | D19: count | G19: Non-cancelled orders with promised delivery on/before as-of date | H19: Deliveries the business had committed to make by now | I19: Excludes cancelled and orders promised after the as-of date (not yet due is NOT overdue) | J19: 132 deliveries were due.
